Workbook

Sheet Leeswijzer
A1: Database pakketadviezen Zorginstituut Nederland (ZIN) – geneesmiddelen
A2: Versie 1.0 · index-snapshot ZIN-website 09-09-2026 · opgebouwd met Claude · webcheck volledigheid t.o.v. ZIN-website 24-09-2026 (overzichtspagina 17-09-2026 + werkagenda 22-09-2026): 149/149 gepubliceerde sluisadviezen in index; 3 adviezen buiten de overzichtspagina toegevoegd (INT-160 t/m INT-162) · 24-09-2026: GVS-historie verwerkt (287 adviezen met basisgegevens, 2015–2026; 12 zonder pdf, 16 lopend); Intramuraal 163 volledig, 10 lopend, INT-172 zonder pdf.
A4: Doel
A5: Doel | B5: Alle pakketadviezen van ZIN over geneesmiddelen op één plek, gesplitst naar traject (GVS/extramuraal vs. intramuraal/sluis), met per dossier de kerngegevens én de argumenten die ZIN heeft gehanteerd, zodat die bij toekomstige dossiers als precedent kunnen worden ingezet.
A7: Opbouw van het bestand
A8: Intramuraal | B8: Register van sluisadviezen en overige adviezen over specialistische geneesmiddelen. Nu gevuld met de complete ZIN-index: 148 afgeronde adviezen (dec 2015 – aug 2026) plus 11 lopende beoordelingen. Eén rij per advies.
A9: GVS | B9: Register van GVS-adviezen (extramuraal). GVS-001 t/m GVS-016: lopende beoordelingen (werkagenda). GVS-101 e.v.: alle sinds 2015 gepubliceerde GVS-adviezen (productadviezen, bijlage 2-wijzigingen, klassebrede adviezen), toegevoegd op 24-09-2026 uit een inventaris van de ZIN-site via het Internet Archive; status 'Index' = nog niet inhoudelijk verwerkt.
A10: Argumenten | B10: De kern van de database: één rij per argument dat ZIN gebruikt, gecodeerd naar pakketcriterium en thema, met parafrase, positie t.o.v. de claim van de fabrikant, gewicht, precedentwaarde en bronverwijzing. Koppelt via Dossier-ID aan Intramuraal of GVS (geneesmiddel en datum worden automatisch opgehaald).
A11: Codeboek | B11: Keuzelijsten (bron van alle dropdowns) en definities. Pas de lijsten hier aan; de dropdowns volgen automatisch.
A12: Overzicht | B12: Tellingen per jaar/uitkomst, per pakketcriterium, extractievoortgang en therapeutisch gebied. Alles formules.
A14: Legenda kolomkleuren
A15: Grijze kop | B15: Automatisch overgenomen uit de ZIN-index. Kolommen met * zijn afgeleid uit de titel van het advies (stofnaam, merknaam, indicatie, gebied, uitkomst) – controleer ze bij gebruik.
A16: Gele kop | B16: Handmatig vullen uit het dossier (brief aan de minister, farmacotherapeutisch rapport, FE-rapport, BIA, ACP-verslag).
A17: Groene kop | B17: Formule – niet overschrijven.
A19: Invulvoorbeeld (verwacht formaat per handmatige kolom)
A20: Registratiehouder | B20: Bristol Myers Squibb
A21: Weesgeneesmiddel | B21: Ja / Nee (dropdown)
A22: Indicatiegroep (ziekte)* | B22: Folliculair lymfoom (dropdown; automatisch uit titel, controleren)
A23: Behandellijn* | B23: 3e lijn of later (dropdown; automatisch uit titel, controleren)
A24: Stand van wetenschap en praktijk (ZIN) | B24: Voldoet (dropdown)
A25: SW&P: kernreden oordeel (categorie) | B25: Indirecte vergelijking geaccepteerd (effect groot/consistent) (dropdown)
A26: SW&P: waarom positief/negatief (onderbouwing) | B26: Positief. Enkelarmige studie indirect vergeleken met ...; ZIN accepteerde dit omdat ...; GRADE zeer laag maar effect groot; voorwaarde: herbeoordeling na ... jaar.
A27: Therapeutische waarde t.o.v. comparator (ZIN) | B27: Meerwaarde (dropdown)
A28: Comparator (ZIN) | B28: docetaxel (tweedelijns NSCLC)
A29: Ziektelast (0–1) | B29: 0,85
A30: Referentiewaarde (€/QALY) | B30: 80.000 (dropdown)
A31: ICER fabrikant / ICER ZIN (€/QALY) | B31: 96.000 / 134.000 (alleen getallen)
... A39: Precedentwaarde | B39: Acceptatie van een NMA als basis voor meerwaarde bij ontbrekende directe vergelijking.
A41: Werkwijze om de database te vullen
A42: Stap 1 – Index actueel houden | B42: Nieuwe adviezen verschijnen op de ZIN-overzichtspagina van sluismiddelen (zie bronnen). Voeg een rij toe met ID, datum, titel en URL; kolom Jaar en het tabblad Overzicht lopen automatisch mee.
A43: Stap 2 – Basisgegevens | B43: Open de documentpagina (URL) en neem uit de brief aan de minister en het FE-rapport de gele kolommen over. Zet Status extractie op 'Basisgegevens'.
A44: Stap 3 – Argumenten | B44: Loop de brief, het farmacotherapeutisch rapport, het FE-rapport en het ACP-verslag door en leg elk relevant argument vast als aparte rij in tabblad Argumenten: criterium, thema, parafrase, positie, gewicht, precedentwaarde, bron + pagina. Zet Status extractie op 'Argumenten volledig'.
A45: Stap 4 – Controle | B45: Laat een collega steekproefsgewijs controleren en zet Status extractie op 'Gecontroleerd'.
A46: GVS-historie | B46: Zoek historische GVS-adviezen via de publicatiezoeker op zorginstituutnederland.nl (soort: Advies, trefwoord 'GVS-advies' of stofnaam) of via de Staatscourant-wijzigingen van de Regeling zorgverzekering; voeg ze als rij toe in tabblad GVS met nieuw ID (GVS-xxx).
A47: Zoeken naar precedenten | B47: Filter tabblad Argumenten op Thema (bijv. 'Indirecte vergelijking / NMA') en Positie ('Ondersteunt claim fabrikant') om snel alle dossiers te vinden waarin ZIN een vergelijkbare redenering heeft geaccepteerd; via Dossier-ID kom je bij de bron.
A49: Bronnen
A50: Index sluisadviezen (compleet, 2015–heden) | B50: https://www.zorginstituutnederland.nl/wat-wij-doen/programmas-en-samenwerkingsverbanden/horizonscan-geneesmiddelen/sluis-voor-dure-geneesmiddelen/overzicht-sluismiddelen-waarover-het-zorginstituut-heeft-geadviseerd
A51: Lopende pakketadviezen (sluis) | B51: https://www.zorginstituutnederland.nl/werkagenda/overzicht-pakketadviezen
A52: Lopende GVS-adviezen | B52: https://www.zorginstituutnederland.nl/werkagenda/overzicht-gvs-adviezen
A53: Licentie broninformatie | B53: De webcontent van ZIN is gepubliceerd onder CC0 1.0 (vermeld in de metadata van de overzichtspagina's); titels, data en URL's mogen vrij worden hergebruikt.
A55: Beperkingen van deze versie
A56: 1 | B56: Uitkomst advies is alleen gevuld voor adviezen vanaf 2024 (staat sindsdien in de ZIN-titel). Oudere adviezen: kolom K nog invullen.
A57: 2 | B57: Registratiehouder, therapeutische waarde, ICER, budgetimpact, ACP-advies en argumenten zijn nog niet geëxtraheerd (Status extractie = Index).
A58: 3 | B58: Stofnaam, merknaam, indicatie en therapeutisch gebied zijn automatisch uit de titels afgeleid; combinatietherapieën tonen alleen het eerste middel als 'Stofnaam (hoofd)'.
A59: 4 | B59: GVS-tabblad bevat alleen de lopende beoordelingen; de historie moet nog worden opgebouwd.
A61: OVERDRACHT 24-09-2026 (GVS-verdieping)
A62: Status: Intramuraal 163 dossiers 'Argumenten volledig' (10 lopend, INT-172 zonder pdf). GVS: 287 dossiers 'Basisgegevens' = velden uit kernzinnen van de brief, ~1 argument bij 54 precedentdossiers; nog te verdiepen tot hetzelfde niveau als intramuraal (alle velden uit brief + FT/FE/BIA/ACP, 3–7 argumenten per dossier). Werkinstructie, to-do-lijst en bouwscripts: ZIN_werkinstructie_GVS_verdieping.md, GVS_todo_verdieping.csv, ZIN_bouwscripts_batch39-50.zip (uitvoermap). Pdf's: ZIN_lijst_GVS_deel1–8_20260924.zip (opnieuw uploaden). Volgorde: stap A (prijs-/afwijzings-/herbeoordelings-/klasseadviezen, ~70) → stap B (rest). Compleetheid vóór tempo.

Sheet Intramuraal
A1: ID | B1: Status | C1: Datum advies | D1: Jaar | E1: Type advies* | F1: Geneesmiddel (uit titel)* | G1: Stofnaam (hoofd)* | H1: Merknaam* | I1: Indicatie (uit titel)* | J1: Therapeutisch gebied* | K1: Uitkomst advies | L1: Titel advies (ZIN) | M1: URL documentpagina ZIN | N1: Indicatiegroep (ziekte)* | O1: Behandellijn* | P1: Registratiehouder | Q1: Weesgeneesmiddel | R1: Datum sluisplaatsing | S1: Claim fabrikant | T1: Stand van wetenschap en praktijk (ZIN) | U1: SW&P: kernreden oordeel (categorie) | V1: SW&P: waarom positief/negatief (onderbouwing) | W1: Therapeutische waarde t.o.v. comparator (ZIN) | X1: Comparator (ZIN) | Y1: Ziektelast (0–1) | Z1: Referentiewaarde (€/QALY) | AA1: ICER fabrikant (€/QALY) | AB1: ICER ZIN basecase (€/QALY) | AC1: Kosteneffectief volgens ZIN | AD1: Geadviseerde prijsreductie (%) | AE1: Budgetimpact ZIN (€ mln/jaar) | AF1: Aantal patiënten/jaar (ZIN) | AG1: ACP-advies (kern) | AH1: Voorwaarden / gepast gebruik | AI1: Kernargumenten ZIN (samenvatting) | AJ1: Besluit minister / uitkomst onderhandeling | AK1: Datum opname basispakket | AL1: Status extractie | AM1: Opmerkingen
A2: INT-149 | B2: Lopend | D2: =IF(C2="","",YEAR(C2)) | E2: Initieel | F2: teprotumumab (Tepezza®) | G2: teprotumumab | H2: Tepezza | I2: de oogziekte van Graves | J2: Oogheelkunde | L2: Advies - wel of niet vergoeden teprotumumab (Tepezza®) voor de behandeling van de oogziekte van Graves | M2: https://www.zorginstituutnederland.nl/werkagenda/bloed-en-immuunsysteem/pakketadvies-sluisgeneesmiddel-teprotumumab-tepezza-voor-de-oogziekte-van-graves | N2: Niet-oncologisch (zie Indicatie) | O2: n.v.t. / onbekend | AL2: Index
A3: INT-150 | B3: Lopend | D3: =IF(C3="","",YEAR(C3)) | E3: Initieel | F3: amivantamab (Rybrevant®) in combinatie met chemotherapie | G3: amivantamab | H3: Rybrevant | I3: gevorderde niet-kleincellige longkanker | J3: Oncologie (solide tumoren) | L3: Advies - wel of niet vergoeden amivantamab (Rybrevant®) in combinatie met chemotherapie voor de behandeling van gevorderde niet-kleincellige longkanker | M3: https://www.zorginstituutnederland.nl/werkagenda/kanker/pakketadvies-sluisgeneesmiddel-amivantamab-rybrevant-in-combinatie-met-chemotherapie-voor-de-behandeling-van-gevorderde-niet-kleincellige-longkanker | N3: Solide tumor (zie Indicatie) | O3: n.v.t. / onbekend | AL3: Index
A4: INT-151 | B4: Lopend | D4: =IF(C4="","",YEAR(C4)) | E4: Initieel | F4: ciltacabtagene autoleucel (Carvykti®) | G4: ciltacabtagene autoleucel | H4: Carvykti | I4: multipel myeloom vanaf de tweede behandellijn | J4: Hemato-oncologie | L4: Advies - wel of niet vergoeden ciltacabtagene autoleucel (Carvykti®) voor de behandeling van multipel myeloom vanaf de tweede behandellijn | M4: https://www.zorginstituutnederland.nl/werkagenda/kanker/pakketadvies-sluisgeneesmiddel-ciltacabtagene-autoleucel-carvykti-bij-multipel-myeloom | N4: Multipel myeloom | O4: n.v.t. / onbekend | AL4: Index
A5: INT-152 | B5: Lopend | D5: =IF(C5="","",YEAR(C5)) | E5: Initieel | F5: durvalumab (Imfinzi®) | G5: durvalumab | H5: Imfinzi | I5: spierinvasieve blaaskanker | J5: Oncologie (solide tumoren) | L5: Advies - wel of niet vergoeden durvalumab (Imfinzi®) voor de behandeling van spierinvasieve blaaskanker | M5: https://www.zorginstituutnederland.nl/werkagenda/kanker/pakketadvies-sluisgeneesmiddel-durvalumab-imfinzi-bij-spierinvasieve-blaaskanker | N5: Solide tumor (zie Indicatie) | O5: n.v.t. / onbekend | AL5: Index
A6: INT-153 | B6: Afgerond advies | C6: 46279 | D6: =IF(C6="","",YEAR(C6)) -> 2026 | E6: Initieel | F6: inavolisib (Itovebi®) in combinatie met palbociclib en fulvestrant | G6: inavolisib | H6: Itovebi | I6: borstkanker | J6: Oncologie (solide tumoren) | K6: Alleen vergoeden na prijsdaling | L6: Advies - alleen vergoeden na prijsdaling inavolisib (Itovebi®) in combinatie met palbociclib en fulvestrant voor de behandeling van borstkanker | M6: https://www.zorginstituutnederland.nl/documenten/2026/09/14/pakketadvies-sluisgeneesmiddel-inavolisib-itovebi-in-combinatie-met-palbociclib-en-fulvestrant-voor-de-behandeling-van-borstkanker | N6: Borstkanker | O6: 1e lijn | P6: Roche | Q6: Nee | S6: Meerwaarde | T6: Voldoet | U6: Directe RCT met klinisch relevant effect | V6: Positief. Bewijs: RCT INAVO120 (inavolisib + palbociclib + fulvestrant vs. placebo + palbociclib + fulvestrant) bij PIK3CA-gemuteerde HR+/HER2- gevorderde borstkanker met recidief op/binnen 12 maanden na adjuvante endocriene therapie: klinisch relevante mediane OS-winst van 7 maanden; meer ernstige bijwerkingen en stakers; QoL ongepubliceerd maar volgens CSR-data niet negatief beïnvloed en achteruitgang mogelijk 11 maanden uitgesteld. CDK4/6-remmers zijn onderling gelijkwaardig (eerder ZIN-oordeel), dus één comparator volstaat; ctDNA- (studie) en weefseltest (NL) beide acceptabel. Studie representatief, al wordt in NL meer alpelisib in 2L gegeven → SWP, meerwaarde t.o.v. CDK4/6 + fulvestrant. | W6: Meerwaarde | X6: CDK4/6-remmer + fulvestrant (INAVO120: palbociclib + fulvestrant) | Y6: Hoog (referentiewaarde €80.000; relatief jonge groep, gem. 54 jaar; OS ~30 mnd, PIK3CA ~8 mnd korter) | Z6: 80000 | AA6: Basecase ZIN 613.940 | AB6: 613.940 (basecase ZIN; vervolgbehandelingen conform INAVO120 → 92% korting); scenario met vervolgbehandelingen naar NL-praktijk 575.638 (→ ~86%) | AC6: Nee | AD6: 89 (ZIN: midden tussen 92 en 86 na inspraak); ACP: ten minste 92 | AE6: 42,3 macrokosten (jaar 3); 39,2 na substitutie van CDK4/6 + fulvestrant; 37,8 incl. substitutie van alpelisib 2L; ca. 6,2 bij 89% korting | AF6: 163 in jaar 3; €330.035 per patiënt per behandeling, waarvan €289.248 inavolisib | AG6: ACP: basecase (92%) biedt de beste onderbouwing → niet opnemen tenzij ≥92% korting; weegt mee: aanzienlijke BI, dynamisch behandellandschap, verwachte indicatie-uitbreidingen, grote onzekerheid over uptake → kort financieel arrangement; geheime prijsafspraken voor (vervolg)behandelingen waar mogelijk meenemen; duidelijke gepast-gebruikafspraken met de beroepsgroep en bevordering van doelmatige inzet. | AH6: Korting 89% (ZIN) – ACP ≥92%; kort arrangement; PIK3CA-diagnostiek: CieBOD doet een uitspraak over de te gebruiken test (ZIN acht opname daarmee uitvoerbaar); gepast-gebruikafspraken; nettoprijzen van (vervolg)behandelingen meewegen. | AI6: INAVO120: OS +7 mnd → meerwaarde t.o.v. CDK4/6 + fulvestrant; QoL alleen via CSR. KE: ICER €613.940 (ZIN-basecase, INAVO120-vervolgbehandelingen) → 92%; NL-praktijkscenario €575.638 → 86%; ZIN kiest na inspraak het midden: 89% – de ACP houdt vast aan 92%. Utiliteit van één gezondheidstoestand zeer onzeker (kleine, geselecteerde groep). BI €39 mln op vraagprijs, €6 mln na korting. Hoogste kortingspercentage voor een RCT-onderbouwd middel in de database. | AJ6: Nog aanvullen (niet in dossier); index: alleen vergoeden na prijsdaling | AL6: Argumenten volledig | AM6: Bron: brief 14-09-2026 (5 p., gedateerd 8 september) + ACP-advies + FT-rapport + FE-rapport + BIA, gelezen via extract. Gepubliceerd na de index-snapshot; eerste PI3Kα-remmer in de sluis; ZIN en ACP verschillen expliciet van mening over het percentage (89 vs. 92).
A7: INT-154 | B7: Lopend | D7: =IF(C7="","",YEAR(C7)) | E7: Herbeoordeling | F7: osimertinib (Tagrisso®) | G7: osimertinib | H7: Tagrisso | I7: lokaal gevorderde niet-kleincellige longkanker | J7: Oncologie (solide tumoren) | L7: Advies - herbeoordeling kosteneffectiviteit osimertinib (Tagrisso®) voor de behandeling van lokaal gevorderde niet-kleincellige longkanker (herbeoordeling) | M7: https://www.zorginstituutnederland.nl/werkagenda/kanker/pakketadvies-sluisgeneesmiddel-osimertinib-tagrisso-bij-lokaal-gevorderde-niet-kleincellige-longkanker-herbeoordeling | N7: Solide tumor (zie Indicatie) | O7: n.v.t. / onbekend | AL7: Index
A8: INT-155 | B8: Lopend | D8: =IF(C8="","",YEAR(C8)) | E8: Initieel | F8: pirtobrutinib (Jaypirca®) | G8: pirtobrutinib | H8: Jaypirca | I8: een bepaalde vorm van bloedkanker | J8: Hemato-oncologie | L8: Advies - wel of niet vergoeden pirtobrutinib (Jaypirca®) voor de behandeling van een bepaalde vorm van bloedkanker | M8: https://www.zorginstituutnederland.nl/werkagenda/kanker/pakketadvies-sluisgeneesmiddel-pirobrutinib-jaypirca-bij-chronische-lymfatische-leukemie-cll | N8: Overig hematologisch | O8: n.v.t. / onbekend | AL8: Index
A9: INT-156 | B9: Lopend | D9: =IF(C9="","",YEAR(C9)) | E9: Initieel | F9: tafasitamab (Minjuvi®) | G9: tafasitamab | H9: Minjuvi | I9: recidiverend of refractair folliculair lymfoom | J9: Hemato-oncologie | L9: Advies - wel of niet vergoeden tafasitamab (Minjuvi®) voor de behandeling van recidiverend of refractair folliculair lymfoom | M9: https://www.zorginstituutnederland.nl/werkagenda/kanker/pakketadvies-sluisgeneesmiddel-tafasitamab-minjuvi-voor-de-behandeling-van-recidiverend-of-refractair-folliculair-lymfoom | N9: Folliculair lymfoom | O9: r/r (lijn niet gespecificeerd) | AL9: Index
A10: INT-157 | B10: Lopend | D10: =IF(C10="","",YEAR(C10)) | E10: Initieel | F10: trastuzumab-deruxtecan (Enhertu®) | G10: trastuzumab-deruxtecan | H10: Enhertu | I10: niet-kleincellige longkanker met HER2-mutatie | J10: Oncologie (solide tumoren) | L10: Advies - wel of niet vergoeden trastuzumab-deruxtecan (Enhertu®) voor de behandeling van niet-kleincellige longkanker met HER2-mutatie | M10: https://www.zorginstituutnederland.nl/werkagenda/kanker/pakketadvies-sluisgeneesmiddel-trastuzumab-deruxtecan-enhertu-voor-de-behandeling-van-niet-kleincellige-longkanker-met-her2-mutatie | N10: Solide tumor (zie Indicatie) | O10: n.v.t. / onbekend | AL10: Index
A11: INT-158 | B11: Lopend | D11: =IF(C11="","",YEAR(C11)) | E11: Initieel | F11: zanubrutinib (Brukinsa®) | G11: zanubrutinib | H11: Brukinsa | I11: lymfeklierkanker | J11: Hemato-oncologie | L11: Advies - wel of niet vergoeden zanubrutinib (Brukinsa®) voor de behandeling van lymfeklierkanker | M11: https://www.zorginstituutnederland.nl/werkagenda/kanker/pakketadvies-sluisgeneesmiddel-zanubrutinib-brukinsa-voor-de-behandeling-van-lymfeklierkanker | N11: Lymfoom (overig / onbepaald) | O11: n.v.t. / onbekend | AL11: Index
A12: INT-159 | B12: Lopend | D12: =IF(C12="","",YEAR(C12)) | E12: Initieel | F12: guselkumab (Tremfya®) | G12: guselkumab | H12: Tremfya | I12: plaque psoriasis | J12: Immunologie / IBD / dermatologie / reumatologie | L12: Advies - wel of niet vergoeden guselkumab (Tremfya®) voor de behandeling van plaque psoriasis | M12: https://www.zorginstituutnederland.nl/werkagenda/zintuigen-huid-en-haar/pakketadvies-sluisgeneesmiddel-guselkumab-tremfya-voor-de-behandeling-van-plaque-psoriasis | N12: Niet-oncologisch (zie Indicatie) | O12: n.v.t. / onbekend | AL12: Index
A13: INT-147 | B13: Afgerond advies | C13: 46260 | D13: =IF(C13="","",YEAR(C13)) -> 2026 | E13: Initieel | F13: lisocabtagene maraleucel (Breyanzi®) | G13: lisocabtagene maraleucel | H13: Breyanzi | I13: recidiverend of refractair folliculair lymfoom | J13: Hemato-oncologie | K13: Alleen vergoeden na prijsdaling | L13: Advies - alleen vergoeden na prijsdaling lisocabtagene maraleucel (Breyanzi®) voor de behandeling van recidiverend of refractair folliculair lymfoom | M13: https://www.zorginstituutnederland.nl/documenten/2026/08/26/pakketadvies-sluisgeneesmiddel-pakketadvies-sluisgeneesmiddel-lisocabtagene-maraleucel-breyanzi-voor-folliculair-lymfoom | N13: Folliculair lymfoom | O13: 3e lijn of later | P13: Bristol Myers Squibb | S13: Meerwaarde | T13: Voldoet | U13: Indirecte vergelijking geaccepteerd (effect groot/consistent) | V13: Positief. Bewijs: enkelarmige fase-2-studie TRANSCEND-FL, met een gepubliceerde indirecte vergelijking tegen een extern controlecohort (patiënten uit eerdere klinische studies én real-world-data behandeld met de standaardbehandeling; IPTW in de base case, propensity-matching als scenario). Geschatte overlevingskans op 30 maanden 88,9% vs. 76,9%; ondanks alle onzekerheden van de indirecte vergelijking lijkt liso-cel een klinisch relevant effect op de overleving te hebben. Bijwerkingen kunnen ernstig zijn maar zijn meestal goed te behandelen en lijken de kwaliteit van leven niet te beïnvloeden. WAR: indirecte vergelijking hier de enige haalbare methode; GRADE zeer laag maar OS-/PFS-curves lopen ver uiteen en de complete-responsrate is hoog; EPAR-data acceptabel; tisa-cel (nog in de sluis voor FL) geen comparator; discussie over 'passend onderzoek' (RCT was in beginsel mogelijk). Conclusie: SWP en meerwaarde t.o.v. de standaardbehandeling; door de korte follow-up onzekerheid over de lange termijn → herbeoordeling op termijn (WAR: zodra 8 jaar follow-up beschikbaar is). Contrast met axi-cel FL (INT-113, 2025): daar werd een vergelijkbare constructie verworpen wegens een niet-valide controlecohort (SCHOLAR-5, kortste OS) en te korte follow-up. | W13: Meerwaarde | X13: Gebruikelijke zorg vanaf 3e lijn (geïndividualiseerd, o.a. anti-CD20-combinaties/rechallenge), via indirecte vergelijking met extern controlecohort (IPTW; EPAR-data). Tisa-cel niet als comparator: zit nog in de sluis voor FL. | Y13: 0,45 (gemiddeld; uit het FE-model – beroepsgroep verwacht hogere ziektelast in de beoogde selecte groep, geen betrouwbare subgroepanalyse mogelijk) | Z13: 50000 | AA13: Basecase fabrikant door ZIN aangepast voor langetermijneffecten | AB13: 105.954 (na conservatieve aanpassingen langetermijneffecten; +ca. 5%-punt korting nodig bij nettoprijs lenalidomide −99%) | AC13: Nee | AD13: 66 (minstens 66% bij referentiewaarde €50.000; ZIN vindt méér dan 66% niet nodig gezien de strenge patiëntselectie door de CAR-T-tumorboard) | AE13: 8,8 macrokosten (jaar 3); 8,0 na substitutie (lijstprijzen) | AF13: 30 in jaar 3; €310.650 per toediening; €292.861 gemiddelde totale kosten per patiënt (incl. conditionering en overbrugging; niet iedereen die start krijgt liso-cel); ca. 700 nieuwe FL-diagnoses per jaar | AG13: Nu niet opnemen; alleen bij prijsdaling van minstens 66% (dan kosteneffectief bij €50.000/QALY). Weging: palliatieve patiënten met mogelijke levensverlenging, maar grote onzekerheid over studieresultaten; comparators mogelijk zelf niet kosteneffectief; liso-cel al vergoed voor andere indicaties met prijsafspraken en meer indicaties verwacht; snel bewegend behandellandschap → kort financieel arrangement. Waardering voor gepast-gebruikafspraken van de beroepsgroep. | AH13: Prijsdaling van (minstens) 66%; strenge patiëntselectie via de landelijke CAR-T-tumorboard en geprotocolleerde inzet (reden waarom ZIN geen hogere korting eist); bij de onderhandeling rekening houden met toekomstige concurrentie van andere CAR-T's bij FL; herbeoordeling op termijn wegens korte follow-up (WAR: 8 jaar); ACP: kort financieel arrangement. | AI13: SWP/meerwaarde via gepubliceerde indirecte vergelijking met extern cohort (30-maands OS 88,9% vs. 76,9%; WAR: enige haalbare methode, GRADE zeer laag maar curves lopen ver uiteen; herbeoordeling na 8 jaar). KEA na ZIN-aanpassingen van de langetermijneffecten (conservatieve, klinisch plausibele aannames; MCM/genezingsaanname en beslisboom verwijderd; utiliteiten uit alternatieve bronnen geaccepteerd) van voldoende kwaliteit: ICER €105.954/QALY bij referentiewaarde €50.000 (ziektelast 0,45 gemiddeld; selecte groep waarschijnlijk hoger, niet te analyseren) → minstens 66% korting; nettoprijs lenalidomide −99% verhoogt de korting met ~5%-punt (beperkt effect). ZIN eist bewust niet méér dan 66% vanwege vertrouwen in de tumorboard-selectie, maar wijst op toekomstige CAR-T-concurrentie. BI 30 patiënten, €8,0 mln. ACP: palliatieve groep met mogelijke levensverlenging maar grote onzekerheid; comparators mogelijk zelf niet kosteneffectief; indicatiestapeling → kort arrangement. | AJ13: Nog geen besluit bekend (stand 09-09-2026) | AL13: Argumenten volledig | AM13: Bron: brief 26-08-2026 + ACP-advies + FT-rapport + FE-rapport + BIA (bundel), aangevuld met WAR-verslagen (16-03 en 06-07-2026) uit batch 1. BMS-dossier. Sluisdatum niet in brief.
A14: INT-148 | B14: Afgerond advies | C14: 46260 | D14: =IF(C14="","",YEAR(C14)) -> 2026 | E14: Initieel | F14: belzutifan (Welireg®) | G14: belzutifan | H14: Welireg | I14: de ziekte van Von Hippel-Lindau | J14: Oncologie (solide tumoren) | K14: Alleen vergoeden na prijsdaling | L14: Advies - alleen vergoeden na prijsdaling belzutifan (Welireg®) voor de behandeling van de ziekte van Von Hippel-Lindau | M14: https://www.zorginstituutnederland.nl/documenten/2026/08/26/pakketadvies-sluisgeneesmiddel-belzutifan-welireg-voor-de-ziekte-van-von-hippel-lindau | N14: Overige solide tumoren | O14: Meerdere lijnen / indicatiebreed | P14: MSD | Q14: Ja | S14: Meerwaarde | T14: Voldoet | U14: Single-arm geaccepteerd (natuurlijk beloop als controle) | V14: Positief, met 'zeer onzekere' effectgrootte; retinaal Hb niet uitgesloten. Bewijs: enkelarmige LS-004 (n=61, primair RCC-VHL, allen ≥1 andere VHL-tumor; ~4 jaar gepubliceerde follow-up): RCC-tumoren krompen ≥30% of verdwenen bij twee derde; bij bijna de helft van de CZS-Hb en 90% van de pNET; slechts 6% CZS-Hb-progressie; effect houdt lang aan. Omdat spontane regressie zeer zelden voorkomt, is de krimp aan belzutifan toe te schrijven; de frequentie van lokale procedures lijkt rigoureus af te nemen (experts: zonder belzutifan onverminderd), maar de omvang van het relatieve effect is door het single-arm design zeer onzeker; een ongepubliceerde MAIC is niet meegenomen. Behandeldoel: uitstellen/voorkomen van lokale procedures (orgaanschade, symptomen), plausibel overlevingswinst. Directe QoL-data ontbreken – 'betreurenswaardig' bij deze aandoening. 'Niet geschikt voor lokale procedure' is subjectief en was geen inclusiecriterium → indicatiecommissie nadrukkelijk nodig. Retinaal Hb (niet aangevraagd bij EMA – onwenselijk) toch niet uitgesloten: hoge respons in kleine subgroep, tumortype-onafhankelijk mechanisme, unmet need; WAR-CG eens. Bijwerkingen bij bijna iedereen, goed behandelbaar → SWP, meerwaarde t.o.v. BSC. | W14: Meerwaarde | X14: Best ondersteunende zorg / actieve surveillance met lokale procedures (natuurlijk beloop; single-arm LS-004) | Y14: Hoog (referentiewaarde €80.000) | Z14: 80000 | AA14: 305903 | AB14: Range 305.903 (fabrikant-basecase, levenslang, ~5 jaar overlevingswinst – te optimistisch, ondergrens) tot 1.001.747 (conservatief scenario met ~6 jaar tijdshorizon en vrijwel geen overlevingswinst – niet realistisch, bovengrens); RCC-subgroep als meest betrouwbare analyse | AC14: Nee | AD14: Minstens 78 (midden van 73–82); ACP: dichter bij 73 (geen effectieve behandeling, kleine groep, beperkte BI) of bij 82 (grote onzekerheden, m.n. ontbrekende QoL-data) | AE14: 6,1 macrokosten (jaar 3); 9,0 in het hoogste scenario (58 patiënten) | AF14: 41 in jaar 3 (~450 VHL-patiënten in NL; ~41/jaar niet meer geschikt voor lokale procedure); 58 in hoog scenario; €160.892 per patiënt per jaar | AG14: ACP: op korte termijn beschikbaar (retinaal Hb niet uitgesloten), maar alleen voor een maatschappelijk aanvaardbare prijs: niet opnemen tenzij 73–82% korting. Richting 73%: aandoening zonder effectieve behandeling, kleine groep, beperkte BI; richting 82%: belangrijke onzekerheden, waarbij het gebrek aan QoL-data zwaar weegt. Verheugd dat de beroepsgroep kritische start-/stopcriteria, gepast gebruik, dosisreductie en 'drug holidays' oppakt; vertrouwen in een landelijke multidisciplinaire indicatiecommissie (behandeling in enkele expertisecentra). | AH14: Korting ≥78% (range 73–82); landelijke multidisciplinaire indicatiecommissie (noodzakelijk, m.n. voor retinaal Hb en de subjectieve 'niet geschikt voor lokale procedure'); start-/stopcriteria (voorstel beroepsgroep ligt er, MDO); monitoring van de inzet in de eerste jaren; onderzoek naar effectiviteit bij lagere dosering en drug holidays; gesprek met veldpartijen over gepast gebruik volgt. | AI14: Single-arm LS-004: tumorkrimp bij ⅔ (RCC), 90% (pNET), afname van lokale procedures – spontane regressie is zeldzaam → SWP/meerwaarde t.o.v. BSC, effectgrootte zeer onzeker; QoL niet gemeten ('betreurenswaardig'); retinaal Hb pragmatisch toegelaten ondanks ontbrekende EMA-registratie. KE: model adequaat maar parameters onvoldoende onderbouwd en model niet transparant; ZIN presenteert een range (fabrikant €305.903 als ondergrens; conservatief kortetermijnscenario €1.001.747 als bovengrens) en concludeert dat ook extra data de onzekerheid nauwelijks zullen verkleinen → 73–82%, advies ≥78%. BI €6,1–9,0 mln. Indicatiecommissie en dosisreductie-onderzoek als voorwaarden. | AJ14: Nog aanvullen (niet in dossier); index: alleen vergoeden na prijsdaling | AL14: Argumenten volledig | AM14: Bron: brief 26-08-2026 (6 p.) + ACP-advies (8 p.) + FT-rapport (96 p.) + FE-rapport + BIA, gelezen via extract. Eerste HIF-2α-remmer; enige advies met een expliciete kortingsrange (73–82%) én een middenwaarde als advies; ZIN laat een niet-geregistreerde subgroep (retinaal Hb) toe op mechanistische gronden.
A15: INT-146 | B15: Afgerond advies | C15: 46232 | D15: =IF(C15="","",YEAR(C15)) -> 2026 | E15: Indicatie-uitbreiding | F15: isatuximab (Sarclisa®) i.c.m. bortezomib, lenalidomide en dexamethason (IsaVRd) | G15: isatuximab | H15: Sarclisa | I15: multipel myeloom | J15: Hemato-oncologie | K15: Alleen vergoeden na prijsdaling | L15: Advies - vergoed isatuximab (Sarclisa®) i.c.m. bortezomib, lenalidomide en dexamethason (IsaVRd) voor de behandeling van multipel myeloom | M15: https://www.zorginstituutnederland.nl/documenten/2026/07/29/pakketadvies-sluisgeneesmiddel-isatuximab-sarclisa-i.c.m.-bortezomib-lenalidomide-en-dexamethason-isavrd-als-inductietherapie-voor-nieuw-gediagnosticeerd-multipel-myeloom-mm | N15: Multipel myeloom | O15: 1e lijn | P15: Sanofi | S15: Gelijke waarde | T15: Voldoet | U15: Niet-inferioriteit / gelijke waarde aangetoond | V15: Positief, als gelijke waarde t.o.v. DaraVRd (voorkeursinductie) en DaraVTd (gelijkwaardig alternatief). Geen directe vergelijking; ZIN maakte een naïeve indirecte vergelijking van drie open-label RCT's: GMMG-HD7 (IsaVRd vs. VRd), PERSEUS (DaraVRd vs. VRd) en CASSIOPEIA (DaraVTd vs. VTd). Effecten op OS en PFS t.o.v. de controlebehandelingen lijken vergelijkbaar; GMMG-HD7 en PERSEUS nog immatuur zonder OS-effect, CASSIOPEIA matuur met klinisch relevante OS-winst; PFS-puntschatter van IsaVRd exact op de PASKWIL-grens (HR 0,70), die van DaraVRd/DaraVTd eronder. ZIN verwacht dat door de vele effectieve vervolgbehandelingen in NDMM-TE geen OS-effect meer aantoonbaar zal zijn en dat het OS-effect van isatuximab en daratumumab in de praktijk gelijk is (zelfde werkingsmechanisme). Studieverschillen (DaraVRd/DaraVTd ook als consolidatie; onderhoud met daratumumab bij alle PERSEUS-patiënten) kunnen IsaVRd onderschatten resp. DaraVRd overschatten. Geen verschillen in QoL, ernstige bijwerkingen, stakers en gebruiksgemak (isatuximab 11 vs. daratumumab 14 toedieningen; subcutane vorm komt). Ondanks zeer immature data en relevante studieverschillen: geen klinisch relevante verschillen → gelijke waarde, mede gesteund door de eerdere vergelijkbare effectiviteit bij NDMM-TIE. | W15: Gelijke waarde | X15: DaraVRd (voorkeursinductie + consolidatie) en DaraVTd (gelijkwaardig alternatief); naïeve indirecte vergelijking GMMG-HD7 / PERSEUS / CASSIOPEIA via VRd/VTd | AC15: Niet beoordeeld | AD15: Nettoprijs niet hoger dan nettoprijs DaraVRd/DaraVTd voor deze indicatie; opname mag niet tot meerkosten leiden | AE15: 2,3 macrokosten (jaar 3); besparing van 2,0 door substitutie op lijstprijzen; met de door ZIN geadviseerde korting van 48,9% op daratumumab (advies DaraRd, januari 2025) nog €0,4 mln besparing | AF15: 47 in jaar 3; €49.391 per inductiebehandeling (DaraVRd €92.290 en DaraVTd €81.703 voor inductie + consolidatie) | AG15: Geen ACP-advies (gelijke waarde). | AH15: Opname mits nettoprijs ≤ nettoprijs DaraVRd/DaraVTd (geen meerkosten). ZIN wil met de beroepsgroep de overwegingen voor de keuze van inductiebehandeling omzetten in gepast-gebruikafspraken. | AI15: Gelijke waarde t.o.v. DaraVRd/DaraVTd via naïeve indirecte vergelijking van drie RCT's (PFS-HR IsaVRd 0,70 op de PASKWIL-grens; OS nog niet aantoonbaar door effectieve vervolglijnen; zelfde werkingsmechanisme; studieverschillen in consolidatie/onderhoud benoemd; gelijke QoL/veiligheid; minder toedieningen) → geen KEA; opname zonder meerkosten. BIA: 47 patiënten, inductie €49.391 vs. €81.703–92.290 → besparing €2,0 mln op lijstprijzen, €0,4 mln met de eerder geadviseerde 48,9% korting op daratumumab; subcutane isatuximab neutraliseert toedieningskostenverschil. | AJ15: Nog aanvullen (niet in dossier) | AL15: Argumenten volledig | AM15: Bron: brief 29-07-2026 + FT-rapport + BIA, gelezen via extract; geen FE, geen ACP/WAR-vermelding. Vervolg op eerder positief advies IsaVRd bij NDMM-TIE en Isa-Kd in het MM-pilotkader (INT-031).
A16: INT-145 | B16: Afgerond advies | C16: 46231 | D16: =IF(C16="","",YEAR(C16)) -> 2026 | E16: Indicatie-uitbreiding | F16: ipilimumab (Yervoy®) i.c.m. nivolumab (Opdivo®) | G16: ipilimumab | H16: Yervoy; Opdivo | I16: peritoneaal mesothelioom | J16: Oncologie (solide tumoren) | K16: Vergoeden | L16: Advies - vergoed ipilimumab (Yervoy®) i.c.m. nivolumab (Opdivo®) voor peritoneaal mesothelioom | M16: https://www.zorginstituutnederland.nl/documenten/2026/07/28/pakketadvies-sluisgeneesmiddel-ipilimumab-yervoy-in-combinatie-met-nivolumab-opdivo-bij-patienten-met-maligne-peritoneaal-mesothelioom | N16: Overige solide tumoren | O16: 1e lijn | P16: Bristol Myers Squibb | Q16: Nee | R16: Ipilimumab 'breed uitgesloten' in de sluis (alle toekomstige indicaties automatisch in de sluis); off-label indicatie op verzoek van de NVMO; formeel VWS-verzoek 25-06-2026 | S16: Meerwaarde | T16: Voldoet | U16: Richtlijn- en consensusgebaseerd (indicatiebrede aanpak / pilot) | V16: Positief, via een verkorte beoordeling van een off-label indicatie. Peritoneaal mesothelioom (~30 patiënten/jaar, 6% van de mesothelioom-gevallen; mediane OS 4–12 maanden) was uitgesloten van CheckMate-743 en zal wegens zeldzaamheid nooit in een RCT of registratie worden onderzocht. ZIN steunt op: (1) de richtlijn Mesothelioom (2022) die ipi + nivo als eerste keus adviseert onafhankelijk van histologie en PD-L1, en peritoneaal mesothelioom gezien de overeenkomsten gelijk behandelt ('data zijn er niet maar het lijkt logisch'); (2) de gangbare praktijk om chemotherapie voor peritoneaal te baseren op pleurale studies, met kleine ongecontroleerde studies die een vergelijkbaar effect suggereren; (3) het eigen advies uit 2021 (INT-042: meerwaarde niet-epitheloïd, gelijke waarde epitheloïd); (4) de SmPC die voorzichtig individueel gebruik bij peritoneaal mesothelioom noemt. Conclusie: SWP voor de gehele populatie, met dezelfde histologische tweedeling als bij pleuraal. | W16: Meerwaarde | X16: Pemetrexed + cis-/carboplatine (extrapolatie van pleuraal mesothelioom, INT-042); meerwaarde niet-epitheloïd, gelijke waarde epitheloïd | AC16: Niet beoordeeld | AD16: Geen nieuwe KEA: aansluiten bij de bestaande financiële afspraken voor ipilimumab + nivolumab bij pleuraal mesothelioom (gebaseerd op de KEA uit 2021) | AE16: 1,15 meerkosten (basecase, 13 patiënten) tot 1,33 (hoog scenario, 15 patiënten) na substitutie van pemetrexed/platina (€7.101 p.p.); macrokosten 1,24–1,43; werkelijk lager door bestaande afspraken | AF16: 13 (10 epitheloïd + 3 niet-epitheloïd) tot 15 per jaar bij 100% marktpenetratie; €95.446 per patiënt (€60.146 nivolumab + €35.300 ipilimumab), behandelduur ~1 jaar | AG16: Geen ACP-advies (verkorte beoordeling; geen nieuwe KEA). | AH16: Opname met gebruik van de bestaande prijsafspraken voor pleuraal mesothelioom; geen relevante gepast-gebruikrisico's verwacht; behandeling conform richtlijn Mesothelioom. | AI16: Eerste verkorte beoordeling van een off-label indicatie op verzoek van de beroepsgroep (NVMO) en VWS: zeldzaamheid (30/jaar) maakt RCT en registratie onhaalbaar; richtlijn, praktijk (chemo ook geëxtrapoleerd van pleuraal), eigen advies 2021 en SmPC dragen SWP. Geen nieuwe KEA 'gezien het lage kostenbeslag én de overlap in indicaties (beide asbestkanker)' → prijs volgt de bestaande pleurale afspraken. BI ~€1,2 mln (13–15 patiënten). Mechanisme 'breed uitgesloten' verklaart waarom een off-label indicatie überhaupt via de sluis loopt. | AJ16: Nog aanvullen (niet in dossier); index: vergoeden | AL16: Argumenten volledig | AM16: Bron: brief 28-07-2026 (4 p., ondertekend M.J. Janssen als voorzitter RvB), geen bijlagen (BIA in brief). BMS-dossier. Vervolg op INT-042 (pleuraal, 2021). Precedent voor off-label indicaties van 'breed uitgesloten' sluismiddelen: verkorte beoordeling, extrapolatie van SWP én van het bestaande arrangement.
A17: INT-144 | B17: Afgerond advies | C17: 46220 | D17: =IF(C17="","",YEAR(C17)) -> 2026 | E17: Indicatie-uitbreiding | F17: darolutamide (Nubeqa®) i.c.m. hormoontherapie (ADT) | G17: darolutamide | H17: Nubeqa | I17: uitgezaaide prostaatkanker | J17: Oncologie (solide tumoren) | K17: Niet vergoeden | L17: Advies - niet vergoeden darolutamide (Nubeqa®) i.c.m. hormoontherapie (ADT) voor de behandeling van uitgezaaide prostaatkanker | M17: https://www.zorginstituutnederland.nl/documenten/2026/07/17/pakketadvies-sluisgeneesmiddel-darolutamide-nubeqa-in-combinatie-met-hormoontherapie-adt-voor-de-behandeling-van-uitgezaaide-prostaatkanker | N17: Prostaatkanker | O17: 1e lijn | P17: Bayer | Q17: Nee | S17: Gelijke waarde | T17: Voldoet niet | U17: Effect te klein of niet klinisch relevant | V17: Negatief. Claim: gelijke waarde met apalutamide + ADT en enzalutamide + ADT; ZIN neemt ook abirateron (NVU-voorkeur op kosten) als comparator; de drie ARPI's gelden als gelijkwaardig, dus vergelijking met één volstaat. De registratiehouder deed – tegen het EMA-advies in – geen vergelijkende studie met een ARPI met OS als primair eindpunt. Een gepubliceerde NMA suggereert dat darolutamide + ADT mogelijk slechter werkt dan de andere ARPI's; de registratiestudies bevestigen dat: ARANOTE toont geen significant of klinisch relevant OS-effect vs. placebo, TITAN (apalutamide) wél, en dat is niet door de kortere studieduur te verklaren; PFS als surrogaat geeft dezelfde conclusie. Mogelijk minder ernstige bijwerkingen en stakers dan apalutamide (naïeve ITC, onzeker) zonder klinisch relevant QoL-voordeel. ZIN beoordeelt op data, niet op een verondersteld klasse-effect ('binnen een klasse kunnen klinisch relevante verschillen bestaan') → geen gelijke waarde → SWP niet voldaan (WAR). NVU wil een extra optie (interacties, heterogeniteit); NVMO, NFK en Prostaatkankerstichting achten de huidige opties toereikend. | W17: Niet te bepalen | X17: Apalutamide, enzalutamide en abirateron (+ ADT), als gelijkwaardige ARPI-klasse; vergelijking via placebo-RCT's (ARANOTE vs. TITAN) en NMA | AC17: Niet beoordeeld | AG17: Niet voorgelegd aan de ACP (advies stopt bij het SWP-criterium). | AH17: n.v.t. (negatief advies). | AI17: Gelijke-waarde-claim afgewezen op inhoud: ARANOTE toont geen OS-effect vs. placebo waar TITAN (apalutamide) dat wél doet; NMA wijst op mogelijk mindere werking; klasse-effect wordt expliciet niet aangenomen; fabrikant negeerde EMA-advies voor een head-to-head met OS → SWP niet voldaan → niet opnemen, geen KEA/BIA/ACP. Eerdere triplet-indicatie (INT-061) positief beoordeeld maar niet vergoed wegens mislukte onderhandeling. Verdeelde veldreacties (NVU vs. NVMO/NFK). | AJ17: Niet opgenomen (negatief advies) | AL17: Argumenten volledig | AM17: Bron: brief 17-07-2026 (4 p.) + FT-rapport (57 p.), gelezen via extract; geen BIA/FE/ACP. Tweede gelijke-waarde-claim die inhoudelijk strandt (na upadacitinib GCA, INT-123): hier omdat de eigen placebo-RCT geen OS-effect toont; expliciete afwijzing van het 'klasse-effect'-argument.
A18: INT-143 | B18: Afgerond advies | C18: 46219 | D18: =IF(C18="","",YEAR(C18)) -> 2026 | E18: Indicatie-uitbreiding | F18: durvalumab (Imfinzi®) | G18: durvalumab | H18: Imfinzi | I18: beperkt stadium kleincellige longkanker | J18: Oncologie (solide tumoren) | K18: Alleen vergoeden na prijsdaling | L18: Advies - vergoed durvalumab (Imfinzi®) voor de behandeling van beperkt stadium kleincellige longkanker | M18: https://www.zorginstituutnederland.nl/documenten/2026/07/16/pakketadvies-durvalumab-imfinzi-voor-de-behandeling-van-beperkt-stadium-kleincellige-longkanker | N18: Longkanker (NSCLC/SCLC) | O18: Onderhoud / consolidatie | P18: AstraZeneca | Q18: Nee | S18: Meerwaarde | T18: Voldoet | U18: Directe RCT met klinisch relevant effect | V18: Positief, beperkt tot WHO PS 0-1 na concurrente chemoradiotherapie (± PCI). Bewijs: dubbelblinde RCT ADRIATIC (durvalumab vs. placebo): geplande interimanalyse toont een klinisch relevant OS-effect, vooral door meer langdurig overlevenden – 8,9% meer in leven na 36 maanden, conform PASKWIL curatief (>5%), 'mogelijk klinisch relevant' (BI's van de overlevingspercentages overlappen; interim). Meer stakers en interventiegerelateerde bijwerkingen, geen QoL-verschil. Niet-fitte patiënten krijgen in NL sequentiële CRT en zaten niet in de studie → geen uitspraak → SWP alleen na concurrente CRT bij WHO 0-1. | W18: Meerwaarde | X18: Actief volgen na concurrente chemoradiotherapie ± PCI (ADRIATIC, placebogecontroleerde RCT) | Y18: Hoog (referentiewaarde €80.000) | Z18: 80000 | AA18: 79994 | AB18: 79.994 – precies op de referentiewaarde; onzeker omdat de finale OS-data ontbreken | AC18: Ja | AD18: Geen percentage; toch onderhandelen: indicatie-uitbreiding (ontwikkelkosten grotendeels terugverdiend → 'forse extra prijsverlaging maatschappelijk noodzakelijk', ACP PD-(L)1 2023), onzekerheid over duurzaamheid; publicatie finale OS voorwaardelijk voor vergoeding; tijdelijk arrangement | AE18: 17,5 macrokosten = BI (jaar 3; geen substitutie); mogelijk lager omdat alleen concurrente CRT-patiënten in aanmerking komen | AF18: 243 in jaar 3 (~1.500 SCLC-diagnoses in 2024); €72.150 per patiënt per behandeling | AG18: Geen apart ACP-document; ZIN verwijst naar het ACP-advies PD-(L)1-remmers (2023): bij indicatie-uitbreiding is een forse extra prijsverlaging maatschappelijk noodzakelijk omdat de ontwikkelkosten vaak al met de eerste indicatie(s) zijn terugverdiend. | AH18: Alleen WHO PS 0-1 na concurrente CRT (± PCI); publicatie van de finale OS-data als voorwaarde voor vergoeding; tijdelijk arrangement zodat de finale OS zo nodig kan worden herbeoordeeld; PD-(L)1-arrangementsbeleid; geen bewijs voor herbehandeling met immunotherapie bij progressie naar ES-SCLC – ZIN wil met de beroepsgroep bespreken wanneer dat te overwegen is. | AI18: ADRIATIC (interim): 36-maands OS +8,9% (PASKWIL curatief >5%), QoL gelijk → meerwaarde t.o.v. actief volgen, beperkt tot WHO 0-1 na concurrente CRT. KE: ICER €79.994 – precies op de grens – kosteneffectief maar onzeker door ontbrekende finale OS. Toch onderhandelen op drie gronden: indicatie-uitbreiding (terugverdiend), PD-(L)1-klassebeleid, en onzekerheid over duurzaamheid → publicatie finale OS als vergoedingsvoorwaarde + tijdelijk arrangement. BI €17,5 mln (243 patiënten). Herbehandeling met I-O na progressie als open gepast-gebruikvraag. | AJ18: Nog aanvullen (niet in dossier); index: vergoeden (na onderhandeling) | AL18: Argumenten volledig | AM18: Bron: brief 16-07-2026 (5 p.) + FT-rapport + FE-rapport + BIA, gelezen via extract; geen ACP-document. Vierde durvalumab-dossier (INT-014 PACIFIC 2019, INT-134, INT-139). Eerste dossier waarin publicatie van finale OS-data expliciet een vergoedingsvoorwaarde is.
A19: INT-142 | B19: Afgerond advies | C19: 46217 | D19: =IF(C19="","",YEAR(C19)) -> 2026 | E19: Initieel | F19: acalabrutinib (Calquence®) | G19: acalabrutinib | H19: Calquence | I19: lymfeklierkanker | J19: Hemato-oncologie | K19: Alleen vergoeden na prijsdaling | L19: Advies - alleen vergoeden na prijsdaling acalabrutinib (Calquence®) voor de behandeling van lymfeklierkanker | M19: https://www.zorginstituutnederland.nl/documenten/2026/07/14/pakketadvies-sluisgeneesmiddel-acalabrutinib-calquence-voor-mantelcellymfoom | N19: Mantelcellymfoom | O19: 2e lijn | P19: AstraZeneca | Q19: Nee | S19: Gelijke waarde | T19: Voldoet | U19: Niet-inferioriteit / gelijke waarde aangetoond | V19: Positief, conform de claim van gelijke waarde t.o.v. ibrutinib. Bewijs: acalabrutinib alleen in een enkelarmige fase-2-studie; ibrutinib in één RCT en enkele single-arm studies; geen directe vergelijking, dus indirecte vergelijking incl. twee gepubliceerde MAIC's: op overleving, uitstel van ziekte en tumorrespons waarschijnlijk ten minste vergelijkbare resultaten; geen klinisch relevante verschillen in ernstige bijwerkingen en stakers. Onzekerheid door onbekende variabelen en populatieverschillen (ibrutinib-studies meer hoogrisicopatiënten → mogelijke bias vóór acalabrutinib), waarvoor de MAIC's corrigeerden met een vergelijkbaar OS-effect. Ondersteunend: vergelijkbaar werkingsmechanisme en eerdere gelijke-waardeconclusies voor beide middelen bij andere indicaties (CLL). Conclusie: voldoende aannemelijk dat acalabrutinib ten minste gelijke waarde heeft → SWP voldaan. | W19: Gelijke waarde | X19: Ibrutinib (eerste keus bij recidief na chemo-immunotherapie; indirecte vergelijking met twee gepubliceerde MAIC's) | AC19: Niet beoordeeld | AD19: Nettoprijs per behandeling niet hoger dan nettoprijs per behandeling met ibrutinib | AE19: 7,4 macrokosten (jaar 3); mogelijke besparing 3,8 na substitutie van ibrutinib (lijstprijzen; werkelijke besparing onbekend) | AF19: 192 in jaar 3; €55.037 per patiënt per jaar; gemiddelde behandelduur 25,3 maanden voor beide middelen | AG19: Geen ACP-advies (gelijke waarde; geen WAR-toets van KE). | AH19: Opname pas als de nettoprijs per behandeling niet hoger is dan die van ibrutinib. | AI19: Gelijke waarde t.o.v. ibrutinib via indirecte vergelijking en twee MAIC's (correctie voor hoger-risico populatie in ibrutinib-studies), gesteund door zelfde werkingsmechanisme en eerdere CLL-conclusies → geen KEA. BIA: 192 patiënten, €55.037 p.p./jaar, behandelduur 25,3 maanden voor beide middelen (groot verschil in follow-up registratiestudies: 38,2 vs. 16 maanden), beroepsgroep akkoord; besparing €3,8 mln op lijstprijzen, werkelijke besparing onbekend. Advies: nettoprijs per behandeling ≤ ibrutinib. Minister bereikte akkoord; vergoed per 29-08-2026. | AJ19: Akkoord met leverancier; vergoed per 29-08-2026 (Stcrt. 2026-30698) | AK19: 46263 | AL19: Argumenten volledig | AM19: Bron: brief 14-07-2026 + FT-rapport + BIA, gelezen via extract; geen FE, geen ACP. Besluit: akkoord met leverancier, vergoed per 29-08-2026 (Stcrt. 2026-30698). Zusterdossiers INT-043 (CLL 2022), INT-046/INT-062 (zanubrutinib).
A20: INT-141 | B20: Afgerond advies | C20: 46212 | D20: =IF(C20="","",YEAR(C20)) -> 2026 | E20: Initieel | F20: amivantamab (Rybrevant®) in combinatie met lazertinib (Lazcluze®) | G20: amivantamab | H20: Rybrevant; Lazcluze | I20: gevorderde niet-kleincellige longkanker | J20: Oncologie (solide tumoren) | K20: Alleen vergoeden na prijsdaling | L20: Advies - alleen vergoeden na prijsdaling amivantamab (Rybrevant®) in combinatie met lazertinib (Lazcluze®) voor de behandeling van gevorderde niet-kleincellige longkanker | M20: https://www.zorginstituutnederland.nl/documenten/2026/07/09/pakketadvies-amivantamab-rybrevant-icm-lazertinib-lazcluze-voor-gevorderde-niet-kleincellige-longkanker | N20: Longkanker (NSCLC/SCLC) | O20: 1e lijn | P20: Janssen | Q20: Nee | S20: Meerwaarde | T20: Voldoet | U20: Niet-inferioriteit / gelijke waarde aangetoond | V20: Positief, als gelijke waarde t.o.v. osimertinib + chemotherapie – de door ZIN (april 2026) tot nieuwe eerste keus verklaarde combinatie die zelf nog niet wordt vergoed (onderhandeling loopt). De claim (meerwaarde t.o.v. osimertinib-monotherapie) is daarmee achterhaald; de beroepsgroep ziet dezelfde plek voor beide combinaties. Bewijs: MARIPOSA (ami + laz vs. osimertinib) en FLAURA2 (osi + chemo vs. osimertinib), geen directe vergelijking: geen klinisch relevante verschillen in overleving en QoL tussen de combinaties; beide meer toxiciteit dan osimertinib-mono, met verschillend type bijwerkingen; amivantamab s.c. of i.v. mogelijk, chemo alleen i.v.; keuze op individuele kenmerken en voorkeuren → SWP, gelijke waarde. | W20: Gelijke waarde | X20: Osimertinib + chemotherapie (nieuwe standaard sinds INT-132; indirecte vergelijking MARIPOSA vs. FLAURA2 via osimertinib-mono) | AC20: Niet beoordeeld | AD20: Netto behandelkosten niet hoger dan netto behandelkosten osimertinib + chemotherapie (waarvoor de onderhandeling nog loopt) | AE20: Scenario 1 (alleen ami + laz beschikbaar): 74,4 macro / 38,9 meerkosten na substitutie van osimertinib-mono; scenario 2 (beide combinaties): 37,2 macro / 16,0 meerkosten na substitutie van osi + chemo (jaar 3, lijstprijzen) | AF20: 743 (scenario 1) of 371 (scenario 2) in jaar 3; €283.133 per patiënt over 3 jaar (€145.067 amivantamab + €138.066 lazertinib) | AG20: Geen ACP-advies (gelijke waarde). | AH20: Netto behandelkosten ≤ osimertinib + chemotherapie; onzekerheid over behandelduur en marktverdeling; prijsafspraken voor osimertinib-mono bestaan al en voor beide combinaties volgen nog. | AI20: Het anker verschuift tijdens het traject: door het osimertinib + chemo-advies (april 2026) is de meerwaarde-claim t.o.v. osimertinib-mono irrelevant en wordt ami + laz via indirecte vergelijking gelijkwaardig aan osi + chemo → geen KEA, nettokosten ≤ osi + chemo (nog niet vergoed, onderhandeling loopt). BIA in twee scenario's (743 vs. 371 patiënten; €38,9 vs. €16,0 mln). Toedieningsvorm (s.c. amivantamab) en bijwerkingenprofiel bepalen de keuze in de spreekkamer, niet het waardeoordeel. | AJ20: Nog aanvullen (niet in dossier); index: alleen vergoeden na prijsdaling | AL20: Argumenten volledig | AM20: Bron: brief 09-07-2026 (4 p.) + FT-rapport + BIA, gelezen via extract; geen FE, geen ACP. Eerste dossier waarin een nog-niet-vergoede combinatie (in onderhandeling) als prijsanker dient; amivantamab + chemo (exon 20) in aparte beoordeling (INT-150).
A21: INT-140 | B21: Afgerond advies | C21: 46203 | D21: =IF(C21="","",YEAR(C21)) -> 2026 | E21: Initieel | F21: belantamab mafodotin (Blenrep®) in combinatie met bortezomib en dexamethason | G21: belantamab mafodotin | H21: Blenrep | I21: multipel myeloom | J21: Hemato-oncologie | K21: Alleen vergoeden na prijsdaling | L21: Advies - alleen vergoeden na prijsdaling belantamab mafodotin (Blenrep®) in combinatie met bortezomib en dexamethason voor de behandeling van multipel myeloom | M21: https://www.zorginstituutnederland.nl/documenten/2026/06/30/pakketadvies-sluisgeneesmiddel-belantamab-mafodotin-blenrep-voor-de-behandeling-van-multipel-myeloom | N21: Multipel myeloom | O21: 2e lijn | P21: GSK | S21: Meerwaarde | T21: Voldoet | U21: Directe RCT met klinisch relevant effect | V21: Positief. Bewijs: RCT DREAMM-7 (BVd vs. DVd) bij r/r MM na ≥1 lijn; 39 maanden follow-up is bij deze relatief lange overleving te kort voor een mediaan-OS-verschil, maar bij de datacut van 07-10-2024 was 28% (BVd) vs. 41% (DVd) overleden. ZIN acht het daarom acceptabel naar het surrogaat PFS te kijken: mediane PFS 36,6 vs. 13,4 maanden (+23,2 maanden; HR 0,41), wat het vertrouwen in een klinisch relevant OS-effect versterkt; een NMA toont een vergelijkbaar effect t.o.v. de vier andere standaardcombinaties. DREAMM-7 includeerde alleen daratumumab-niet-refractaire patiënten; de beroepsgroep wil ook daratumumab-refractaire patiënten behandelen en ZIN verwacht op basis van het verschillende werkingsmechanisme geen invloed op het effect. QoL gelijk aan DVd. Ongunstiger bijwerkingenprofiel (oogtoxiciteit, trombocytopenie; klinisch relevant meer stakers), maar grotendeels reversibel en beheersbaar met monitoring en dosisaanpassing, zonder QoL-verschil. Het overlevingseffect is zo groot dat meerwaarde t.o.v. behandeling naar keuze van de arts wordt geconcludeerd. | W21: Meerwaarde | X21: Behandeling naar keuze van de arts (vijf combinaties); DREAMM-7 direct vs. DVd, NMA voor de overige vier | Z21: 80000 | AA21: 184047 | AB21: 210.862 (met eerder door ZIN geadviseerde kortingen op de comparators toegepast) | AC21: Nee | AD21: Ten minste 61 (t.o.v. bij benadering kosteneffectieve comparators); 49 op lijstprijzen | AE21: 95,3 macrokosten (jaar 3); 70,4 na substitutie (gerectificeerd 30-06-2026 wegens uitstroomcorrectie); ACP: >€120 mln verwacht | AF21: 554 in jaar 3; kosten per patiënt €201.964 (jaar 1), €165.404 (jaar 2), €94.336 (jaar 3) | AG21: ACP: niet opnemen tenzij ≥61% prijsdaling. Weegt zwaar: effectiviteit gebaseerd op immature data met veel onzekerheid over de lange termijn; vergelijking met niet-doelmatige zorg; verwachte budgetimpact >€120 mln; zicht op concurrerende middelen en mogelijke indicatie-uitbreiding → kort financieel arrangement en herbeoordeling zodra OS-data beschikbaar zijn; MM-uitgaven al zeer hoog → maatschappelijk belang van een hogere korting. | AH21: Prijsdaling ≥61%; arrangement met herbeoordeling bij finale(re) OS-data; kort arrangement; doelmatigheidsonderzoek (dosisverlaging met behoud van werkzaamheid lijkt mogelijk); gepast-gebruikmaatregelen van de beroepsgroep tegen oogtoxiciteit en voor juiste inzet bij ouderen. | AI21: DREAMM-7 (RCT vs. DVd): PFS +23,2 mnd (HR 0,41), OS immatuur maar 28% vs. 41% overleden → meerwaarde ondanks oogtoxiciteit; extrapolatie naar dara-refractaire patiënten plausibel (ander werkingsmechanisme). KEA voldoende: ICER €184.047 op lijstprijzen (−49%), maar met de door ZIN eerder geadviseerde kortingen op de comparators €210.862 → ≥61% korting om kosteneffectief te zijn t.o.v. 'bij benadering kosteneffectieve' comparators. Onzekerheden: OS-extrapolatie op interim-data, aanhoudend effect na stoppen zonder scenario (niet geleverd), effect bij dara-refractaire patiënten aangenomen gelijk – acceptabel gezien het grote overlevingsvoordeel; herbeoordeling sterk aanbevolen. BI: 554 patiënten, €70,4 mln (na rectificatie); CAR-T (zelfde BCMA-target) zal inzet verminderen, sequentie onduidelijk; toxiciteit kan tot dosisverlaging leiden. Hoge MM-uitgaven → hogere korting maatschappelijk gewenst. | AJ21: Nog aanvullen (niet in dossier) | AL21: Argumenten volledig | AM21: Bron: gerectificeerde brief 30-06-2026 (oorspronkelijk 13-05-2026; behandelkosten binnen de BIA-horizon gecorrigeerd voor uitstroom) + ACP-advies + FT + FE + BIA, gelezen via extract. Eerste dossier waarin ZIN de ICER standaard herberekent met eerder geadviseerde comparatorkortingen (49% → 61%).
A22: INT-137 | B22: Afgerond advies | C22: 46169 | D22: =IF(C22="","",YEAR(C22)) -> 2026 | E22: Herbeoordeling | F22: brexucabtagene autoleucel (Tecartus®) | G22: brexucabtagene autoleucel | H22: Tecartus | I22: acute lymfatische leukemie (ALL) | J22: Hemato-oncologie | K22: Alleen vergoeden na prijsdaling | L22: Advies - alleen vergoeden na prijsdaling brexucabtagene autoleucel (Tecartus®) voor de behandeling van acute lymfatische leukemie (ALL) (herbeoordeling) | M22: https://www.zorginstituutnederland.nl/documenten/2026/05/27/pakketadvies-sluisgeneesmiddel-brexucabtagene-autoleucel-tecartus-voor-de-behandeling-van-acute-lymfatische-leukemie-all | N22: B-ALL | O22: r/r (lijn niet gespecificeerd) | P22: Kite / Gilead | Q22: Ja | R22: Sluis; eerder advies 15-01-2025 (INT-096: niet opnemen wegens onbruikbare KEA); herindiening KEA | S22: Meerwaarde | T22: Voldoet | U22: Indirecte vergelijking geaccepteerd (effect groot/consistent) | V22: Positief, bevestiging van 2025 (INT-096). ZUMA-3 (single-arm) indirect vergeleken met SCHOLAR-3: OS-verlenging 19,2 maanden, klinisch relevante QoL-verbetering na 3 maanden; onzekerheden door indirecte vergelijking, lage aantallen en verschillen met de Nederlandse praktijk. Nieuwe data met 45 maanden follow-up: 38,6% in leven na 54 maanden, wat het langetermijneffect bevestigt en het SWP-oordeel (getrokken op 21 maanden follow-up) onderschrijft. Voldoende vertrouwen in klinisch relevante overlevingswinst zonder verlies van kwaliteit van leven. | W22: Meerwaarde | X22: Blinatumomab, inotuzumab ozogamicine of chemotherapie (± alloSCT); extern cohort SCHOLAR-3 | Z22: 80000 | AA22: Basecase herindiening; door ZIN aangepast op de genezingsaanname | AB22: 126029 | AC22: Nee | AD22: Meer dan 44 (minstens 44% om kosteneffectief te zijn; meer wegens onzekerheid en ondoelmatige comparator) | AE22: 6,4 macrokosten (jaar 3); 4,6 na substitutie (BIA 2025 ongewijzigd); in werkelijkheid hoger door verzekeraarsafspraken over blinatumomab/inotuzumab | AF22: 23 in jaar 3 (beroepsgroep verwacht mogelijk minder door nieuwe eerstelijnsopties); €360.000 per toediening; €277.818 per patiënt per jaar | AG22: ACP: beschikbaarheid belangrijk, maar alleen tegen een maatschappelijk aanvaardbare prijs; niet opnemen tenzij ≥44% prijsdaling (ICER onder €80.000). Weegt mee: ernstig zieke maar zeer kleine groep, beperkte budgetimpact en klinisch relevant langere overleving voor een aanzienlijk deel van de patiënten. Daartegenover: de comparators zijn hoogstwaarschijnlijk ondoelmatig, zodat 44% de ondoelmatigheid in stand houdt – de ACP mist instrumenten voor betere prijsadvisering. Dynamisch landschap → kort financieel arrangement. Waardering voor de verantwoordelijkheid van de beroepsgroep bij patiëntselectie en gepast gebruik. | AH22: Prijsdaling >44%; kort financieel arrangement; landelijke CAR-T-tumorboard en geprotocolleerde inzet. | AI22: SWP/meerwaarde bevestigd met 45 maanden follow-up (38,6% in leven na 54 mnd). Herindiening KEA met langere follow-up en op verzoek gewijzigde aannames; ZIN paste de genezingsaanname aan, waarna de analyse bruikbaar was: ICER €126.029/QALY → minstens 44% korting; ZIN adviseert méér dan 44% wegens (kosten)effectiviteitsonzekerheid en de onbekende doelmatigheid van de standaardbehandeling. BIA 2025 gehandhaafd (23 patiënten, €4,6 mln netto). ACP: ≥44%, kort arrangement, erkent dat 44% ondoelmatigheid in stand houdt. | AJ22: Nog aanvullen (niet in dossier) | AL22: Argumenten volledig | AM22: Bron: gebundelde PDF (brief 27-05-2026; ACP-advies; FT-rapport; herbeoordeling FE-rapport; BIA), gelezen via extract. Vervolg op INT-096. Brexu-cel voor MCL wordt niet vergoed omdat prijsonderhandelingen mislukten (vermeld in brief).
A23: INT-138 | B23: Afgerond advies | C23: 46169 | D23: =IF(C23="","",YEAR(C23)) -> 2026 | E23: Herbeoordeling | F23: ciltacabtagene autoleucel (Carvykti®) | G23: ciltacabtagene autoleucel | H23: Carvykti | I23: multipel myeloom | J23: Hemato-oncologie | K23: Alleen vergoeden na prijsdaling | L23: Advies - alleen vergoeden na prijsdaling ciltacabtagene autoleucel (Carvykti®) voor de behandeling van multipel myeloom (herbeoordeling) | M23: https://www.zorginstituutnederland.nl/documenten/2026/05/27/pakketadvies-sluisgeneesmiddel-cilta-cel-carvykti-bij-multipel-myeloom-herbeoordeling | N23: Multipel myeloom | O23: 3e lijn of later | P23: Janssen | Q23: Ja | R23: Sluis; adviezen 20-10-2022 (INT-052, KEA onbruikbaar) en 18-02-2025 (INT-099, ≥35%); onderhandeling mislukt → november 2025 niet opgenomen; herbeoordeling FE op verzoek fabrikant (dec. 2025) met steun HOVON, NVvH en Hematon | S23: Meerwaarde | T23: Voldoet | U23: Indirecte vergelijking geaccepteerd (effect groot/consistent) | V23: Ongewijzigd (SWP en meerwaarde t.o.v. de standaardbehandeling vanaf de vierde lijn, zie INT-099). De update betreft de KE op basis van bijna tweemaal zo lange follow-up van de registratiestudie (61,3 vs. 34,5 maanden), verwerkt in het FE-model met klinische validatie van de langetermijnschattingen voor (progressievrije) overleving. Onzeker blijft het effect op post-progressie-overleving (beroepsgroep: klinisch aannemelijk maar grootte onzeker; sterk afhankelijk van vervolgbehandelingen) en de kosten/effecten van vervolgbehandeling in een veranderend landschap. | W23: Meerwaarde | X23: Standaardbehandeling 4L+ (indirecte vergelijking; zie INT-099) | Z23: 80000 | AB23: 71.267 op lijstprijzen (geüpdatete en aangepaste FE-analyse); scenario's blijven onder 80.000; kosteneffectief maar afhankelijk van nettoprijzen van standaard- en vervolgbehandelingen → ~5% korting | AC23: Ja | AD23: Meer dan 5 (5 volgens KEA, afhankelijk van nettoprijzen van comparator/vervolgbehandelingen; méér wegens resterende onzekerheid en zeer hoge BI) | AE23: 37,9–46,2 (jaar 3, op vraagprijs); stijgt verder bij de 2L-indicatie (beoordeling start 2026, INT-151) | AF23: Zie BIA (4L+; ~1.400 MM-diagnoses/jaar) | AG23: Geen nieuw ACP-advies (update FE; WAR). | AH23: Korting >5%; rekening houden met de onderhandelde nettoprijzen van standaard- en vervolgbehandelingen; onzekerheid over post-progressie-overleving en vervolgbehandelingen; komende 2L-indicatie. | AI23: Langere follow-up (61 mnd) verandert het beeld radicaal: van ≥35% (2025) naar ~5% (ICER €71.267, kosteneffectief bij €80.000). ZIN accepteert nu de langetermijn-PFS/OS-extrapolaties na klinische validatie, houdt onzekerheid over post-progressie-overleving en vervolgbehandelingen, en vraagt 'meer dan 5%' vanwege die onzekerheid en een BI van €38–46 mln (plus komende 2L-uitbreiding). Derde geval (na Libmeldy, sacituzumab) waarin follow-updata een mislukte onderhandeling heropenen en de kortingseis fors verlagen. | AJ23: Heronderhandeling geadviseerd; index: alleen vergoeden na prijsdaling | AL23: Argumenten volledig | AM23: Bron: brief 27-05-2026 (4 p.) + FE-herbeoordelingsrapport (19-05-2026) + FT + BIA, gelezen via extract (EPAR-bijlage niet meegenomen). Vervolg op INT-052 en INT-099. Grootste kortingsdaling in de database door langetermijndata (35% → 5%).
A24: INT-139 | B24: Afgerond advies | C24: 46169 | D24: =IF(C24="","",YEAR(C24)) -> 2026 | E24: Indicatie-uitbreiding | F24: durvalumab (Imfinzi®) in combinatie met tremelimumab (Imjudo®) | G24: durvalumab | H24: Imfinzi; Imjudo | I24: leverkanker | J24: Oncologie (solide tumoren) | K24: Alleen vergoeden na prijsdaling | L24: Advies - alleen vergoeden na prijsdaling durvalumab (Imfinzi®) in combinatie met tremelimumab (Imjudo®) voor de behandeling van leverkanker | M24: https://www.zorginstituutnederland.nl/documenten/2026/05/27/pakketadvies-sluisgeneesmiddel-durvalumab-imfinzi-in-combinatie-met-tremelimumab-imjudo-voor-de-behandeling-van-leverkanker | N24: Lever-/galwegkanker | O24: 1e lijn | P24: AstraZeneca | Q24: Nee | S24: Gelijke waarde | T24: Voldoet | U24: Niet-inferioriteit / gelijke waarde aangetoond | V24: Positief, als gelijke waarde t.o.v. atezolizumab + bevacizumab (eerste keus; claim van meerwaarde t.o.v. sorafenib niet getoetst). Bewijs: geen directe vergelijking; NMA van HIMALAYA (durva + treme vs. sorafenib) en IMbrave150 (atezo + bev vs. sorafenib): geen klinisch relevante verschillen in overleving; beide combinaties klinisch relevant beter dan sorafenib (HIMALAYA: 4-jaars OS 21,1% vs. 11,6%); naïeve ITC: geen relevante verschillen in QoL of bijwerkingen; beroepsgroep verwacht vergelijkbare effectiviteit. Verschillen in contra-indicaties (atezo + bev bij bloedingsrisico/cardiovasculaire comorbiditeit) maken durva + treme een relevante toevoeging voor die patiënten → SWP, gelijke waarde. | W24: Gelijke waarde | X24: Atezolizumab + bevacizumab (NMA via sorafenib-arm; HIMALAYA vs. IMbrave150); sorafenib bij contra-indicatie | AC24: Niet beoordeeld | AD24: Netto behandelkosten durvalumab + tremelimumab niet hoger dan netto behandelkosten atezolizumab + bevacizumab (bevacizumab en sorafenib generiek → nettoprijzen aanzienlijk lager) | AE24: 1,9 macrokosten (jaar 3); 0,29 meerkosten na substitutie op lijstprijzen – werkelijk hoger door generieke bevacizumab/sorafenib | AF24: 47 in jaar 3 (28 starters + 19 continuerend); €77.226 per behandeling (durvalumab 10,1 maanden + eenmalig tremelimumab) | AG24: Geen ACP-advies (gelijke waarde). | AH24: Netto behandelkosten ≤ atezolizumab + bevacizumab; keuze per patiënt door de behandelaar (contra-indicaties); meer indicatie-uitbreidingen van durvalumab en tremelimumab verwacht. | AI24: Gelijke waarde met atezo + bev via NMA (gemeenschappelijke sorafenib-arm) → geen KEA; de meerwaarde-claim t.o.v. sorafenib wordt niet getoetst omdat sorafenib geen eerste keus meer is. Anker: nettokosten van de combinatie atezo + bev, waarvan bevacizumab generiek is → laag anker. BI klein (47 patiënten). Klinische niche: patiënten met contra-indicatie voor bevacizumab. | AJ24: Nog aanvullen (niet in dossier); index: alleen vergoeden na prijsdaling | AL24: Argumenten volledig | AM24: Bron: brief 27-05-2026 (4 p.) + FT-rapport + BIA, gelezen via extract; geen FE, geen ACP. Eerste HCC-dossier in de database; eerste dubbele sluisplaatsing (durvalumab én tremelimumab) in één beoordeling.
A25: INT-135 | B25: Afgerond advies | C25: 46155 | D25: =IF(C25="","",YEAR(C25)) -> 2026 | E25: Indicatie-uitbreiding | F25: trastuzumab-deruxtecan (Enhertu®) | G25: trastuzumab-deruxtecan | H25: Enhertu | I25: gevorderde of uitgezaaide maagkanker | J25: Oncologie (solide tumoren) | K25: Alleen vergoeden na prijsdaling | L25: Advies - alleen vergoeden na prijsdaling trastuzumab-deruxtecan (Enhertu®) voor de behandeling van gevorderde of uitgezaaide maagkanker | M25: https://www.zorginstituutnederland.nl/documenten/2026/05/13/pakketadvies-sluisgeneesmiddel-trastuzumab-deruxtecan-enhertu-voor-de-behandeling-van-gevorderde-of-uitgezaaide-maagkanker | N25: Maag-/slokdarmkanker | O25: 3e lijn of later | P25: Daiichi Sankyo / AstraZeneca | Q25: Nee | S25: Meerwaarde | T25: Voldoet | U25: Directe RCT met klinisch relevant effect | V25: Positief, voor de derde lijn en later (claim smaller dan de registratie vanaf de tweede lijn; CieBOM adviseerde negatief voor 2L en positief vanaf 3L). Bewijs: RCT DESTINY-Gastric01 (T-DXd vs. irinotecan/paclitaxel na ≥2 lijnen): mediane OS 12,5 vs. 8,4 maanden (ruim 17 weken winst), klinisch relevant; ondanks onzekerheden voldoende representatief voor NL. Meer ernstige bijwerkingen en meer stakers; QoL-data te beperkt voor conclusies. Conclusie (met WAR): SWP, meerwaarde t.o.v. chemotherapie (TAS-102/irinotecan). | W25: Meerwaarde | X25: Chemotherapie (irinotecan of paclitaxel in de studie; TAS-102/irinotecan in NL) – DESTINY-Gastric01, directe RCT | Y25: Hoog (referentiewaarde €80.000; 5-jaarsoverleving 2%) | Z25: 80000 | AA25: Aangepast door ZIN | AB25: 239.946 (na aanpassing door ZIN; voldoende kwaliteit) | AC25: Nee | AD25: Meer dan 62 (62 volgens ICER; méér wegens de al hoge uitgaven aan T-DXd in NL en verwachte verdere indicatie-uitbreidingen) | AE25: 0,87 macrokosten; 0,77 meerkosten (jaar 3, lijstprijzen) | AF25: 12 in jaar 3; €72.159 per patiënt bij 6,68 maanden behandeling | AG25: Geen apart ACP-document in de bundel; kern in brief: >62% wegens bestaande hoge T-DXd-uitgaven en komende uitbreidingen. | AH25: Korting >62%; alleen vanaf de derde lijn (conform CieBOM); in de spreekkamer aandacht voor ernstige bijwerkingen en staken zodat patiënt en arts samen beslissen of levensverlenging opweegt tegen de toxiciteit. | AI25: DESTINY-Gastric01: OS 12,5 vs. 8,4 mnd → meerwaarde; QoL onbekend, meer toxiciteit. KE: ICER €239.946 na ZIN-aanpassing → 62%, maar 'meer dan 62%' vanwege de al hoge landelijke T-DXd-uitgaven (product-brede opslag) en komende indicaties. Zeer kleine BI (12 patiënten, €0,8 mln) – het percentage wordt dus niet door de BI van deze indicatie gedreven maar door het product als geheel. Samen-beslissen als passende-zorgvoorwaarde. | AJ25: Nog aanvullen (niet in dossier); index: alleen vergoeden na prijsdaling | AL25: Argumenten volledig | AM25: Bron: brief 13-05-2026 (4 p.) + FT-rapport + FE-rapport + BIA, gelezen via extract; geen ACP-document. Derde T-DXd-dossier (INT-054, INT-112). Eerste keer dat de totale landelijke uitgaven aan een product expliciet als opslagargument voor een kleine nieuwe indicatie dienen.
A26: INT-136 | B26: Afgerond advies | C26: 46155 | D26: =IF(C26="","",YEAR(C26)) -> 2026 | E26: Indicatie-uitbreiding | F26: isatuximab (Sarclisa®) | G26: isatuximab | H26: Sarclisa | I26: multipel myeloom | J26: Hemato-oncologie | K26: Alleen vergoeden na prijsdaling | L26: Advies - vergoed isatuximab (Sarclisa®) voor de behandeling van multipel myeloom | M26: https://www.zorginstituutnederland.nl/documenten/2026/05/13/pakketadvies-sluisgeneesmiddel-isatuximab-sarclisa-bij-multipel-myeloom | N26: Multipel myeloom | O26: 1e lijn | P26: Sanofi | Q26: Nee | S26: Gelijke waarde | T26: Voldoet | U26: Niet-inferioriteit / gelijke waarde aangetoond | V26: Positief, als gelijke waarde t.o.v. DaraRd (eerste keus bij NDMM niet-transplantabel). Bewijs: naïeve indirecte vergelijking van IMROZ (IsaVRd vs. VRd) en MAIA (DaraRd vs. Rd); bewijskwaliteit vergelijkbaar. Door de lange overleving bij NDMM accepteert ZIN PFS als basis voor de gelijke-waarde-claim: mediane PFS IsaVRd niet bereikt bij ~60 maanden follow-up vs. 61,9 maanden voor DaraRd (64,5 maanden follow-up) → vergelijkbaar. Meer zekerheid over OS is wenselijk maar zal er niet komen (controle-armen krijgen alsnog anti-CD38). Meer neuropathie door bortezomib, beheersbaar via monitoring/dosisreductie; bortezomib alleen de eerste 4 cycli, blijft beschikbaar voor latere lijnen. ZIN is 'nog niet overtuigd' van een klinisch relevante meerwaarde van de toevoeging van bortezomib, maar gelijke waarde is voldoende aannemelijk → SWP. | W26: Gelijke waarde | X26: DaraRd (MAIA) via naïeve indirecte vergelijking met IMROZ; beide anti-CD38 | AC26: Niet beoordeeld | AD26: Nettoprijs per behandeling IsaVRd niet hoger dan nettoprijs DaraRd voor deze indicatie; vergelijking op gemiddelde prijs per patiënt per jaar over de eerste 3 jaar | AE26: 8 macrokosten (jaar 3); −1,7 (besparing) na substitutie van DaraRd op lijstprijzen; +1,9 meerkosten als DaraRd 48% korting heeft (conform MM-pilotadvies 2025) | AF26: 38 in jaar 3; €63.328 (jaar 1), €90.437 (jaar 2), €58.615 (jaar 3) per patiënt; DaraRd met 48% korting €50.011 / €55.940 / €56.099 | AG26: Geen ACP-advies (gelijke waarde). | AH26: Nettoprijs ≤ DaraRd (gemiddelde over 3 jaar omdat de jaarkosten per jaar verschillen); inzet bij niet-transplantabele patiënten die fit genoeg zijn voor bortezomib (beroepsgroep); hogere niet-geneesmiddelkosten (dagbehandeling); sommige patiënten alsnog naar autologe SCT bij goede respons (kosteneffect onduidelijk); HOVON HO174-doelmatigheidsstudie en s.c.-isatuximab maken gebruik en marktpenetratie onzeker. | AI26: Gelijke waarde met DaraRd op PFS via naïeve ITC (IMROZ vs. MAIA); OS-vergelijking komt nooit door crossover naar anti-CD38 → geen KEA. Anker: nettoprijs DaraRd, waarbij ZIN rekent met de 48% korting uit het MM-pilotadvies (2025) → IsaVRd zou dan €1,9 mln meerkosten geven i.p.v. €1,7 mln besparing. Nieuwe methodiek: prijzen gelijkstellen op het 3-jaarsgemiddelde per patiënt omdat de kostenprofielen per jaar verschillen. Gecorrigeerde brief (behandelduur/kosten). | AJ26: Nog aanvullen (niet in dossier); index: vergoed | AL26: Argumenten volledig | AM26: Bron: gecorrigeerde brief 13-05-2026 (oorspronkelijk 20-11-2025; 5 p.) + FT-rapport + BIA, gelezen via extract; geen FE, geen ACP. Zusterdossier van DaraVRd (INT-161) en IsaVRd-TE (INT-146); eerste toepassing van het 48%-DaraRd-anker uit de MM-pilot.
A27: INT-134 | B27: Afgerond advies | C27: 46154 | D27: =IF(C27="","",YEAR(C27)) -> 2026 | E27: Indicatie-uitbreiding | F27: durvalumab (Imfinzi®) in combinatie met carboplatine of cisplatine en etoposide | G27: durvalumab | H27: Imfinzi | I27: kleincellige longkanker | J27: Oncologie (solide tumoren) | K27: Alleen vergoeden na prijsdaling | L27: Advies - alleen vergoeden na prijsdaling durvalumab (Imfinzi®) in combinatie met carboplatine of cisplatine en etoposide voor de behandeling van kleincellige longkanker | M27: https://www.zorginstituutnederland.nl/documenten/2026/05/12/pakketadvies-sluisgeneesmiddel-durvalumab-imfinzi-in-combinatie-met-carboplatine-of-cisplatine-en-etoposide-voor-kleincellige-longkanker | N27: Longkanker (NSCLC/SCLC) | O27: 1e lijn | P27: AstraZeneca | Q27: Nee | S27: Meerwaarde | T27: Voldoet | U27: Directe RCT met klinisch relevant effect | V27: Positief, voor ECOG PS 0-1. Bewijs: RCT CASPIAN (durvalumab + chemotherapie vs. chemotherapie): na 27 maanden nog 20,7% vs. 9,3% in leven → klinisch relevant OS-effect; geen klinisch relevante toename van ernstige bijwerkingen of stakers; geen QoL-verlies; immuungerelateerde bijwerkingen acceptabel volgens de beroepsgroep. Conclusie (met WAR): SWP, meerwaarde t.o.v. chemotherapie. | W27: Meerwaarde | X27: Carboplatine/cisplatine + etoposide (CASPIAN, directe RCT); serplulimab + chemo gelijktijdig beoordeeld (INT-133), beroepsgroep verwacht geen klinisch relevante verschillen | Y27: Hoog (referentiewaarde €80.000) | Z27: 80000 | AA27: 144603 | AB27: 144.603 (analyse van voldoende kwaliteit) | AC27: Nee | AD27: Ten minste 60 | AE27: 20 macrokosten = BI (jaar 3; add-on, geen substitutie); lager bij marktverdeling met serplulimab | AF27: 394 in jaar 3; €50.644 per patiënt bij 7,5 maanden behandeling | AG27: Geen apart ACP-document in de bundel; advies conform ZIN (≥60%), met PD-(L)1-klassebeleid en concurrentie serplulimab als context. | AH27: Korting ≥60%; PD-(L)1-arrangementsbeleid (2023) toepassen; concurrentie met serplulimab (gelijkwaardig geacht door beroepsgroep) meewegen; alleen ECOG PS 0-1; meer durvalumab-indicaties in beoordeling (LS-SCLC, HCC). | AI27: CASPIAN: 27-maands OS 20,7% vs. 9,3%, geen extra toxiciteit, QoL behouden → meerwaarde t.o.v. chemo. KE: ICER €144.603 → 60% (vs. 33% voor serplulimab in dezelfde indicatie: hogere prijs/langere OS-extrapolatie). ZIN beoordeelde beide middelen apart t.o.v. chemo omdat de trajecten gelijktijdig liepen, maar verwacht onderlinge concurrentie in de praktijk. BI €20 mln (394 patiënten). PD-(L)1-klassebeleid. | AJ27: Nog aanvullen (niet in dossier); index: alleen vergoeden na prijsdaling | AL27: Argumenten volledig | AM27: Bron: brief 12-05-2026 (4 p.) + FT-rapport + FE-rapport + BIA, gelezen via extract; geen ACP-document. Zusterdossier INT-133; ZIN's eerste expliciete 'parallelle beoordeling' van twee concurrenten met een aankondiging dat ze in de praktijk zullen concurreren.
A28: INT-133 | B28: Afgerond advies | C28: 46140 | D28: =IF(C28="","",YEAR(C28)) -> 2026 | E28: Initieel | F28: serplulimab (Hetronifly®) | G28: serplulimab | H28: Hetronifly | I28: bepaalde patiënten met kleincellige longkanker | J28: Oncologie (solide tumoren) | K28: Alleen vergoeden na prijsdaling | L28: Advies - alleen vergoeden na prijsdaling serplulimab (Hetronifly®) voor de behandeling van bepaalde patiënten met kleincellige longkanker | M28: https://www.zorginstituutnederland.nl/documenten/2026/04/28/pakketadvies-sluisgeneesmiddel-serplulimab-hetronifly-voor-de-behandeling-van-bepaalde-patienten-met-kleincellige-longkanker | N28: Longkanker (NSCLC/SCLC) | O28: 1e lijn | P28: Henlius / Accord | Q28: Nee | S28: Meerwaarde | T28: Voldoet | U28: Directe RCT met klinisch relevant effect | V28: Positief, voor de geclaimde subgroep ECOG PS 0-1 (smaller dan de registratie). Bewijs: RCT ASTRUM-005 (serplulimab + chemotherapie vs. chemotherapie): klinisch relevante mediane OS-winst van 4,7 maanden; geen klinisch relevante toename van ernstige bijwerkingen of stakers; geen aanwijzingen voor QoL-verlies; immuungerelateerde bijwerkingen door de beroepsgroep acceptabel geacht. Conclusie (met WAR): SWP, meerwaarde t.o.v. chemotherapie. | W28: Meerwaarde | X28: Carboplatine + etoposide (ASTRUM-005, directe RCT); durvalumab + chemo gelijktijdig beoordeeld (INT-134) | Y28: Hoog (referentiewaarde €80.000; mediane OS <1 jaar) | Z28: 80000 | AA28: 102213 | AB28: 102.213 (analyse van voldoende kwaliteit); ook na 33% korting nog 50% kans niet kosteneffectief (ACP) | AC28: Nee | AD28: Ten minste 33 | AE28: 25,5 macrokosten = BI (jaar 3; add-on, geen substitutie); lager als ook durvalumab beschikbaar komt | AF28: 394 in jaar 3 (ca. 1.125 ES-SCLC-diagnoses/jaar); €64.803 per patiënt bij 8,6 maanden behandeling | AG28: ACP: snel beschikbaar gezien het uitblijven van vooruitgang voor deze groep, maar alleen tegen een maatschappelijk aanvaardbare prijs; tijdelijke betaling van de maximale referentiewaarde (€80.000/QALY) is verdedigbaar omdat het een goed onderzocht nieuw middel met aangetoonde klinisch relevante overlevingswinst voor ernstig zieke patiënten betreft en de comparator (goedkope chemotherapie) hoogstwaarschijnlijk kosteneffectief is → niet opnemen tenzij ≥33% korting, met de kanttekening dat er dan nog 50% kans is dat het niet kosteneffectief is; arrangementsduur afstemmen op komende concurrentie (durvalumab) en indicatie-uitbreidingen. | AH28: Korting ≥33%; PD-(L)1-arrangementsbeleid (2023) toepassen; concurrentie van durvalumab (gelijktijdig beoordeeld) meewegen; alleen ECOG PS 0-1. | AI28: ASTRUM-005: OS +4,7 mnd, geen extra toxiciteit/stakers, QoL behouden → meerwaarde t.o.v. chemo (eerste I-O in ES-SCLC in de sluis). KE: ICER €102.213 → 33%. ACP motiveert waarom hier de volle referentiewaarde tijdelijk mag worden betaald: nieuw, goed onderzocht middel, relevante OS-winst, kosteneffectieve comparator – geen 'terugverdiend'-argument. BI €25,5 mln (394 patiënten, add-on). Concurrentie met durvalumab en het PD-(L)1-klassebeleid bepalen de arrangementsduur. | AJ28: Nog aanvullen (niet in dossier); index: alleen vergoeden na prijsdaling | AL28: Argumenten volledig | AM28: Bron: brief 28-04-2026 (4 p.) + ACP-advies + FT-rapport + FE-rapport + BIA, gelezen via extract. Parallel beoordeeld met durvalumab ES-SCLC (INT-134): zelfde populatie, beide vs. chemo, 33% vs. 60%.
A29: INT-131 | B29: Afgerond advies | C29: 46127 | D29: =IF(C29="","",YEAR(C29)) -> 2026 | E29: Herbeoordeling | F29: venetoclax (Venclyxto®) met obinutuzumab | G29: venetoclax | H29: Venclyxto | I29: niet eerder behandelde chronische lymfatische leukemie | J29: Hemato-oncologie | K29: Alleen vergoeden na prijsdaling | L29: Advies - alleen vergoeden na prijsdaling venetoclax (Venclyxto®) met obinutuzumab voor de behandeling van niet eerder behandelde chronische lymfatische leukemie | M29: https://www.zorginstituutnederland.nl/documenten/2026/04/15/pakketadvies-sluisgeneesmiddel-venetoclax-venclyxto-voor-de-behandeling-van-niet-eerder-behandelde-chronische-lymfatische-leukemie | N29: CLL | O29: 1e lijn | P29: AbbVie | Q29: Nee | R29: Sluis; eerste advies 14-07-2025 (INT-163; drie CLL-subgroepen: deels positief, voor deze subgroep KEA onbruikbaar → niet opnemen); herbeoordeling FE | S29: Meerwaarde | T29: Voldoet | U29: Directe RCT met klinisch relevant effect | V29: Ongewijzigd t.o.v. juli 2025: GAIA-CLL13 (open-label RCT, vooraf gespecificeerde subgroepanalyse) bij fitte, therapienaïeve CLL-patiënten met ongemuteerd IGHV zonder del(17p)/TP53: mogelijk klinisch relevante verbetering van (via PFS gemeten) overleving t.o.v. chemo-immunotherapie, geen klinisch relevante verschillen in bijwerkingen of staken; QoL niet beschikbaar → SWP, meerwaarde. | W29: Meerwaarde | X29: Chemo-immunotherapie (FCR / BR) – GAIA-CLL13 | Z29: 50000 | AA29: Te optimistisch (ingediende analyse) | AB29: 108.975 na twee noodzakelijke aanpassingen: tweedelijnsbehandelingen niet meenemen en kortere duur van de overlevingswinst | AC29: Nee | AD29: Ten minste 51 op venetoclax (prijs obinutuzumab constant) | AE29: 1,7 macrokosten; 1,3 meerkosten (jaar 3) na substitutie van FCR/BR (BIA juli 2025 nog van toepassing) | AF29: 46 in jaar 3; €72.455 per patiënt vs. FCR €14.911 / BR €15.131 | AG29: Geen nieuw ACP-advies (herbeoordeling FE; alleen WAR). | AH29: Korting ≥51% op venetoclax voor deze subgroep (fit, therapienaïef, IGHV-ongemuteerd, zonder del(17p)/TP53); overige subgroepen conform het advies van juli 2025. | AI29: Herindiening na 'KEA onbruikbaar' (juli 2025): analyse nu voldoende, maar ZIN corrigeert twee optimistische aannames (2L-behandelingen weglaten; duur van de overlevingswinst) → ICER €108.975 bij €50.000 → ≥51% op venetoclax. Kleine BI (46 patiënten, €1,3 mln) omdat de comparator goedkope chemo-immunotherapie is. | AJ29: Nog aanvullen (niet in dossier); index: alleen vergoeden na prijsdaling | AL29: Argumenten volledig | AM29: Bron: brief 15-04-2026 (4 p.) + FE-herbeoordelingsrapport + BIA, gelezen via extract; geen FT/ACP. Het moederadvies van 14-07-2025 (drie subgroepen) ontbrak in de index en is toegevoegd als INT-163 (PDF nog aan te leveren).
A30: INT-132 | B30: Afgerond advies | C30: 46127 | D30: =IF(C30="","",YEAR(C30)) -> 2026 | E30: Indicatie-uitbreiding | F30: osimertinib (Tagrisso®) in combinatie met pemetrexed en chemotherapie | G30: osimertinib | H30: Tagrisso | I30: gevorderd niet-kleincellige longkanker | J30: Oncologie (solide tumoren) | K30: Alleen vergoeden na prijsdaling | L30: Advies - alleen vergoeden na prijsdaling osimertinib (Tagrisso®) in combinatie met pemetrexed en chemotherapie voor de behandeling van gevorderd niet-kleincellige longkanker | M30: https://www.zorginstituutnederland.nl/documenten/2026/04/15/pakketadvies-sluisgeneesmiddel-osimertinib-tagrisso-met-pemetrexed-en-chemotherapie-voor-de-behandeling-van-gevorderd-niet-kleincellige-longkanker | N30: Longkanker (NSCLC/SCLC) | O30: 1e lijn | P30: AstraZeneca | Q30: Nee | S30: Meerwaarde | T30: Voldoet | U30: Directe RCT met klinisch relevant effect | V30: Positief. Bewijs: RCT FLAURA2 (osimertinib + chemotherapie vs. osimertinib-monotherapie, de huidige standaard): klinisch relevant OS-effect – de HR van 0,77 ligt boven de relevantiegrens van 0,70, maar de mediane OS-winst van 9,9 maanden ligt ruimschoots boven de grens van 16 weken, en het verschil in langdurige overleving is aanzienlijk (12% na 24 en 36 maanden, 8% na 48 maanden). Meer bijwerkingen en stakers door de chemotherapie, zonder klinisch relevante impact op de gemiddelde QoL, mede omdat de platinumchemotherapie slechts 4 cycli duurt. Conclusie (met WAR): SWP, meerwaarde t.o.v. osimertinib-monotherapie. | W30: Meerwaarde | X30: Osimertinib-monotherapie (FLAURA2, directe RCT; osimertinib onder bestaand arrangement) | Y30: Hoog (referentiewaarde €80.000) | Z30: 80000 | AA30: 110108 | AB30: 110.108 op lijstprijzen (→ 9% korting); 204.526 bij 35% korting op de comparator osimertinib-monotherapie (zoals ZIN in 2018 adviseerde) → 39% korting | AC30: Nee | AD30: Ten minste 39 op osimertinib (uitgaande van 35% korting op osimertinib-monotherapie; 9 op lijstprijzen) | AE30: 28,8 macrokosten (jaar 3); 4,6 meerkosten na substitutie van osimertinib-monotherapie (€173.148 p.p., lijstprijzen); werkelijk afhankelijk van het osimertinib-arrangement | AF30: 187 in jaar 3; €239.924 per patiënt (€212.815 osimertinib + €27.109 chemo); hogere osimertinib-kosten door langere behandelduur in combinatie | AG30: ACP betrokken (appraisal); geen apart ACP-document in de bundel. | AH30: Korting ≥39% op osimertinib; met dit advies wordt osimertinib + chemotherapie de nieuwe eerstekeusbehandeling (zie amivantamab + lazertinib, INT-141). | AI30: FLAURA2: OS-HR 0,77 (boven de 0,70-grens) maar mediaan +9,9 mnd en 8–12% meer langdurig overlevenden → toch klinisch relevant → meerwaarde; 4 cycli chemo → toxiciteit zonder QoL-verlies. KE: ICER €110.108 op lijstprijzen zou 9% vragen, maar ZIN herrekent met zijn eigen 35%-kortingsadvies op de comparator (osimertinib mono, 2018) → ICER €204.526 → 39% korting. BI €4,6 mln netto (187 patiënten); de meerkost zit vooral in de langere osimertinib-duur, niet in de chemo. | AJ30: Nog aanvullen (niet in dossier); index: alleen vergoeden na prijsdaling; onderhandeling loopt (juli 2026) | AL30: Argumenten volledig | AM30: Bron: brief 15-04-2026 (4 p.) + FT-rapport + FE-rapport + BIA, gelezen via extract; geen ACP-document. Vierde osimertinib-dossier (INT-009, INT-040, INT-125). Voorbeeld van 'absolute winst overrulet HR-grens' en van comparator-herwaardering met een eigen eerder kortingsadvies (9% → 39%).
A31: INT-130 | B31: Afgerond advies | C31: 46093 | D31: =IF(C31="","",YEAR(C31)) -> 2026 | E31: Indicatie-uitbreiding | F31: ipilimumab (Yervoy®) in combinatie met nivolumab (Opdivo®) | G31: ipilimumab | H31: Yervoy; Opdivo | I31: darmkanker | J31: Oncologie (solide tumoren) | K31: Alleen vergoeden na prijsdaling | L31: Advies - vergoed ipilimumab (Yervoy®) in combinatie met nivolumab (Opdivo®) voor de behandeling van darmkanker | M31: https://www.zorginstituutnederland.nl/documenten/2026/03/12/pakketadvies-sluisgeneesmiddel-ipilimumab-yervoy-met-nivolumab-opdivo-voor-de-behandeling-van-darmkanker | N31: Darmkanker | O31: 1e lijn | P31: Bristol Myers Squibb | Q31: Nee | S31: Meerwaarde | T31: Voldoet | U31: Directe RCT met klinisch relevant effect | V31: Positief, meerwaarde t.o.v. pembrolizumab (NL-standaard). Bewijs: RCT CheckMate 8HW (ipilimumab + nivolumab vs. nivolumab-monotherapie): gepubliceerde PFS-verlenging; recentere, nog ongepubliceerde data laten zien dat het PFS-effect zich lijkt te vertalen in langere OS – de OS-HR lijkt aan de klinische relevantiegrens te voldoen, met onzekerheid door immature data. Nivolumab-monotherapie geldt als proxy voor pembrolizumab: een indirecte vergelijking toont vergelijkbare effecten (beide PD-1-remmers). Meer bijwerkingen en stakers, maar geen aanwijzingen voor relevante QoL-verschillen, mede omdat slechts 4 cycli ipilimumab worden toegevoegd aan een PD-1-remmer die tot 2 jaar wordt gegeven. Conclusie (met WAR): SWP, meerwaarde. ZIN hanteert 'irresectabel' i.p.v. 'inoperabel'; de tweedelijnsregistratie (na fluoropyrimidine) is niet aangevraagd omdat die chemo in NL geen 1L-standaard is. | W31: Meerwaarde | X31: Pembrolizumab (NL-standaard 1L dMMR/MSI-H mCRC), via nivolumab-monotherapie als proxy (CheckMate 8HW, directe RCT; ITC nivolumab ≈ pembrolizumab) | Y31: Laag (referentiewaarde €20.000 – opmerkelijk voor mCRC; ziektelast berekend t.o.v. de al effectief behandelde dMMR/MSI-H-populatie) | Z31: 20000 | AA31: Dominant op lijstprijzen (pembrolizumab-behandeling €135.068 duurder dan nivolumab €82.625) | AB31: Dominantie op lijstprijzen niet realistisch; scenario's: 32% korting op beide → 13.795 (kosteneffectief); nivolumab-kosten i.p.v. pembrolizumab → ~35.000 (60% korting op ipilimumab nodig); nivolumab −32% én gelijke kosten → 36.255 (~75% korting op ipilimumab nodig) | AC31: Onzeker | AD31: Niet te berekenen door vertrouwelijke arrangementen van nivolumab én pembrolizumab; scenario's geven richting: 0% (dominant op lijstprijzen) tot ~60–75% op ipilimumab als de nettoprijzen van nivolumab en pembrolizumab lager en vergelijkbaar zijn | AE31: 12,9 macrokosten (jaar 3); op lijstprijzen besparing 3,4 na substitutie van pembrolizumab; ca. 2,4 meerkosten (uitsluitend ipilimumab) bij 32% korting op nivolumab en gelijke nettokosten nivolumab/pembrolizumab | AF31: 120 in jaar 3 (ca. 15% van mCRC is dMMR/MSI-H); €106.158 per behandeling (€23.533 ipilimumab + €82.625 nivolumab) vs. pembrolizumab €135.068 | AG31: Geen ACP-advies in de bundel (WAR; KE-oordeel afhankelijk van vertrouwelijke prijzen). | AH31: Alleen opnemen als een kosteneffectieve prijs kan worden onderhandeld; als de combinatie op basis van de werkelijke (onderhandelde) prijzen niet kosteneffectief is, moet over de prijs van ipilimumab worden onderhandeld. Diagnostiek: dMMR/MSI-H-testen al ingebed (pembrolizumab) met kwaliteitsnormen en onafhankelijke laboratoriumtoetsing; aandacht voor de drempel om bij twijfel over de IHC-uitslag een bevestigende moleculaire test aan te vragen (risico op inzet zonder dMMR/MSI-H). | AI31: CheckMate 8HW: PFS-winst, OS-HR lijkt relevant (ongepubliceerd, immatuur); nivolumab als proxy voor pembrolizumab; 4 cycli ipilimumab op een 2-jaars PD-1-backbone → toxiciteit zonder QoL-verlies → meerwaarde. KE: referentiewaarde slechts €20.000; op lijstprijzen dominant (pembrolizumab duurder dan nivolumab) maar 'niet realistisch' omdat beide een arrangement hebben; ZIN rekent scenario's (−32% op beide: €13.795, kosteneffectief; gelijke nettokosten: 60–75% korting op ipilimumab nodig) zonder een percentage te kunnen noemen. BI: 120 patiënten, nominaal besparing €3,4 mln, realistisch ~€2,4 mln meerkosten voor ipilimumab. Advies: opnemen mits kosteneffectieve prijs; anders onderhandelen over ipilimumab. | AJ31: Nog aanvullen (niet in dossier); index: vergoed | AL31: Argumenten volledig | AM31: Bron: brief 12-03-2026 (4 p.) + FT-rapport (16-02-2026) + FE-rapport + BIA, gelezen via extract; geen ACP. BMS-dossier. Uniek: (1) OS-oordeel mede op ongepubliceerde data; (2) ZIN kan geen percentage noemen omdat zowel de eigen backbone (nivolumab) als de comparator (pembrolizumab) een vertrouwelijk arrangement heeft en presenteert een scenario-range van 0 tot ~75%; (3) referentiewaarde €20.000 bij een gemetastaseerde tumor.
A32: INT-129 | B32: Afgerond advies | C32: 46078 | D32: =IF(C32="","",YEAR(C32)) -> 2026 | E32: Indicatie-uitbreiding | F32: exagamglogene autotemcel (Casgevy®) | G32: exagamglogene autotemcel | H32: Casgevy | I32: ernstige sikkelcelziekte | J32: Hematologie (benigne) | K32: Alleen vergoeden na prijsdaling | L32: Advies - vergoed exagamglogene autotemcel (Casgevy®) voor de behandeling van ernstige sikkelcelziekte | M32: https://www.zorginstituutnederland.nl/documenten/2026/02/25/pakketadvies-exagamglogene-autotemcel-casgevy-voor-de-behandeling-van-ernstige-sikkelcelziekte | N32: Sikkelcelziekte / thalassemie | O32: n.v.t. / onbekend | P32: Vertex | Q32: Ja | S32: Meerwaarde | T32: Voldoet | U32: Single-arm geaccepteerd (natuurlijk beloop als controle) | V32: Positief voor de geregistreerde indicatie (geen geschikte donor). Bewijs: enkelarmige CLIMB-SCD-121 (≥2 VOC's/jaar, geen donor): 71% van alle gestarte patiënten ≥12 maanden vrij van ernstige VOC's en 73% zonder VOC-opname; van de daadwerkelijk behandelde patiënten 96% resp. 100%; QoL verbeterd; levenslange werkzaamheid onbekend; traject intensief maar vergelijkbaar met autologe SCT. De claim was breder (ook patiënten mét donor maar te hoog SCT-risico): die groep zat niet in de studie, valt buiten de registratie en de beroepsgroep ziet alleen een plek zonder geschikte donor → SWP, meerwaarde t.o.v. hydroxycarbamide, transfusies en symptomatische VOC-behandeling (met WAR). | W32: Meerwaarde | X32: Standaardbehandeling: hydroxycarbamide, bloedtransfusies, symptomatische behandeling van vaso-occlusieve crises (allogene SCT alleen bij donor) | Z32: 80000 | AA32: 112068 | AB32: 112.068 (analyse van voldoende kwaliteit); scenario's met afnemend effect hebben grote impact | AC32: Nee | AD32: Minstens 24; meer dan 24 wegens het zeer hoge macrokostenbeslag (164 mln) als alle 85 patiënten worden behandeld | AE32: 13,5 (jaar 3, 7 patiënten door capaciteit; geen substitutie van betekenis, transfusiekosten ~€10.000 p.p./jaar niet meegenomen); 164 als alle 85 patiënten worden behandeld | AF32: 7 in jaar 3 (enkele per jaar, capaciteit gedeeld met TDT); 85 in aanmerking (ca. 2.000 SCZ-patiënten); €1,9 mln per patiënt | AG32: Maatschappelijke weging: op korte termijn beschikbaar, maar alleen voor een maatschappelijk aanvaardbare prijs; bij succesvolle onderhandeling moet exa-cel voor beide indicaties (SCZ en TDT) gelijktijdig beschikbaar komen, zodat op medisch-inhoudelijke gronden wordt gekozen wie eerst wordt behandeld; gepast-gebruikafspraken (expertisecentra, landelijke multidisciplinaire indicatiecommissie). | AH32: Korting >24%; onderhandeling afstemmen met de lopende TDT-onderhandeling zodat beide indicaties tegelijk beschikbaar komen; herbeoordeling vóór heronderhandeling bij langetermijndata; indicatiecommissie en expertisecentra (traject al gestart n.a.v. TDT-advies); alleen patiënten zonder geschikte donor. | AI32: Single-arm CLIMB-SCD-121 (96% VOC-vrij bij behandelde patiënten) → meerwaarde, SWP, maar beperkt tot de registratie (geen donor) – bredere claim afgewezen. KEA voldoende: ICER €112.068 bij €80.000 → ≥24%, meer wegens €164 mln macro bij volledige behandeling; effectverlies-scenario's zeer bepalend. Capaciteit: enkele patiënten/jaar, te delen met TDT → gezamenlijke beschikbaarheid en indicatiecommissie. Herbeoordeling vóór heronderhandeling. | AJ32: Nog aanvullen (niet in dossier); index: vergoed | AL32: Argumenten volledig | AM32: Bron: brief 25-02-2026 (5 p.) + ACP-advies + FT-rapport + FE-rapport + BIA, gelezen via extract. Zusterdossier INT-116 (TDT: 43% bij €50.000); hier lagere korting (24%) door hogere referentiewaarde (€80.000) en lagere ICER. Enige dossier dat gelijktijdige beschikbaarheid van twee indicaties als voorwaarde stelt.
A33: INT-128 | B33: Afgerond advies | C33: 46066 | D33: =IF(C33="","",YEAR(C33)) -> 2026 | E33: Initieel | F33: lecanemab (Leqembi ®) | G33: lecanemab | H33: Leqembi | I33: Alzheimer | J33: Neurologie | K33: Niet vergoeden | L33: Advies - niet vergoeden lecanemab (Leqembi ®) voor de behandeling van Alzheimer | M33: https://www.zorginstituutnederland.nl/documenten/2026/02/13/pakketadvies-lecanemab-leqembi--voor-de-behandeling-van-alzheimer | N33: Niet-oncologisch (zie Indicatie) | O33: 1e lijn | P33: Eisai / BioArctic (BioArctic; Eisai) | Q33: Nee | S33: Meerwaarde | T33: Voldoet niet | U33: Effect te klein of niet klinisch relevant | V33: Negatief. Bewijs: RCT Clarity AD (n=1.795; 18 maanden lecanemab vs. placebo bovenop BSC, gevolgd door 18 maanden eenarmige extensie); de geregistreerde indicatie/claim berust op de subgroep ApoE ε4-niet-dragers/heterozygoten (84,7%, n=1.466). Op cognitief functioneren en dagelijks functioneren een klein, statistisch significant maar niet klinisch relevant effect (relevantiegrenzen o.b.v. literatuur, richtlijnen en beroepsgroep); de eenarmige extensie vs. een historisch cohort toont ook na 36 maanden geen klinisch relevant effect; QoL: onvoldoende bewijs (subgroepdata niet gepubliceerd). Amyloïdklaring correleert slecht met klinische uitkomsten. Mogelijk meer ernstige bijwerkingen (alleen voor de totale populatie gepubliceerd); meer ARIA (meestal asymptomatisch, zelden ernstig/dodelijk). Conclusie (met WAR): geen aangetoonde klinisch relevante vertraging van progressie, onvoldoende QoL-bewijs, groter risico op ernstige bijwerkingen → SWP niet voldaan. | W33: Niet te bepalen | X33: Best ondersteunende zorg (Clarity AD, placebogecontroleerd) | AC33: Niet beoordeeld | AG33: Niet voorgelegd aan de ACP (advies stopt bij het SWP-criterium). | AH33: n.v.t. (negatief advies). | AI33: Statistisch significant maar niet klinisch relevant effect op cognitie/dagelijks functioneren (18 mnd), geen relevant effect na 36 mnd (extensie vs. historisch cohort); QoL-subgroepdata niet gepubliceerd; surrogaat (amyloïdklaring) slecht gecorreleerd met klinische uitkomsten; meer (soms dodelijke) ARIA en mogelijk meer SAE's → SWP niet voldaan → niet opnemen, geen KEA/BIA/ACP. | AJ33: Niet opgenomen (negatief advies) | AL33: Argumenten volledig | AM33: Bron: brief 13-02-2026 (4 p.) + FT-rapport, gelezen via extract; geen BIA/FE/ACP. Eerste anti-amyloïd-antilichaam in de sluis; klinische relevantiegrenzen (MCID) op cognitieve schalen als doorslaggevend instrument.
A34: INT-127 | B34: Afgerond advies | C34: 46065 | D34: =IF(C34="","",YEAR(C34)) -> 2026 | E34: Initieel | F34: glofitamab (Columvi®) in combinatie met gemcitabine en oxaliplatine (GemOx) | G34: glofitamab | H34: Columvi | I34: lymfeklierkanker | J34: Hemato-oncologie | K34: Alleen vergoeden na prijsdaling | L34: Advies - vergoed glofitamab (Columvi®) in combinatie met gemcitabine en oxaliplatine (GemOx) voor de behandeling van lymfeklierkanker | M34: https://www.zorginstituutnederland.nl/documenten/2026/02/12/pakketadvies-sluisgeneesmiddel-glofitamab-columvi-voor-lymfeklierkanker | N34: DLBCL / LBCL | O34: 2e lijn | P34: Roche | S34: Meerwaarde | T34: Voldoet | U34: Directe RCT met klinisch relevant effect | V34: Positief. Bewijs: gerandomiseerde open-label fase-III-studie STARGLO (Glofit-GemOx vs. R-GemOx) bij r/r DLBCL na ≥1 lijn, niet geschikt voor auto-SCT. R-GemOx is wereldwijd de meest gebruikte CIT; in Nederland ook R-PECC, volgens de beroepsgroep therapeutisch gelijkwaardig → STARGLO geaccepteerd als passend bewijs. Klinisch relevant OS-effect: mediaan 25,5 vs. 12,9 maanden; bewijskwaliteit zeer laag door onzekere vergelijkbaarheid van de studiepopulatie met Nederlandse patiënten, maar het verschil is zo groot dat ook bij overschatting een klinisch relevant effect voldoende aannemelijk is; ondersteund door de Europese NIVEAU-studie (OS op R-GemOx vergelijkbaar met de STARGLO-controlearm). QoL niet beoordeeld (alleen ongepubliceerd aangeleverd). Veiligheid beheersbaar; CRS-risico vereist eenmalige voorbehandeling met obinutuzumab. Conclusie: SWP en meerwaarde t.o.v. CIT. Keerpunt na het negatieve monotherapie-advies van 2024 (INT-077). | W34: Meerwaarde | X34: Chemo-immunotherapie: R-GemOx (STARGLO), in NL gelijkwaardig aan R-PECC; substitutiemix R-PECC 40%, R-lenalidomide 25%, R-GemOx 25%, BR 10% | Z34: 80000 | AA34: Analyse fabrikant te optimistisch / onvoldoende kwaliteit; niet gerapporteerd als basis | AB34: 94.584 (door ZIN op vijf punten aangepaste base case; winst 2,19 LY en 1,58 QALY; incl. kosten obinutuzumab-voorbehandeling) | AC34: Nee | AD34: 28 | AE34: 12,0 macrokosten (jaar 3); 10,7 na substitutie van CIT (gewogen €10.356 per patiënt); lijstprijzen – werkelijk hoger door lage nettoprijs lenalidomide | AF34: 131 in jaar 3; €91.977 per patiënt incl. obinutuzumab-voorbehandeling | AG34: ACP: effectieve behandeling bij hoge ziektelast, maar veel onzekerheid over effectiviteit en kosteneffectiviteit; niet opnemen tenzij prijsdaling van ten minste 28% (ICER onder €80.000/QALY); herbeoordeling overwegen na 3–4 jaar gezien onzekerheden, dynamisch veld en verwachte indicatie-uitbreiding; complimenten aan de beroepsgroep voor voorgenomen gepast-gebruikafspraken. | AH34: Prijsdaling ≥28%; ook de eenmalige obinutuzumab-voorbehandeling (zelfde registratiehouder) moet voor vergoeding in aanmerking komen; herbeoordeling na 3–4 jaar als bewijs over duurzaamheid van het effect beschikbaar is; landelijke gepast-gebruikafspraken en registratie van met bispecifieke antilichamen behandelde patiënten in het bestaande landelijke register. | AI34: STARGLO (RCT vs. R-GemOx ≈ R-PECC): OS 25,5 vs. 12,9 mnd, effect zo groot dat het ondanks zeer lage bewijskwaliteit (generaliseerbaarheid) klinisch relevant blijft; NIVEAU-studie bevestigt comparator-OS; QoL alleen ongepubliceerd → niet beoordeeld. KEA fabrikant te optimistisch → ZIN paste de base case zelf op vijf punten aan (cohort- i.p.v. trialmortaliteit; cohortleeftijd 73 jaar; generalized gamma PFS / log-logistic OS; ziektegerelateerde kosten 5 jaar voor progressievrije patiënten; gelijke frequentie curatieve vervolgbehandeling in beide armen) → ICER €94.584 → korting ≥28%; herbeoordeling na 3–4 jaar. Kosten obinutuzumab-voorbehandeling meegenomen en moeten mee vergoed worden. BI 131 patiënten, €10,7 mln; onzekerheid door CAR-T in het algoritme en lage nettoprijs lenalidomide. VWS vroeg op 19-03-2026 de resultaten van de aangepaste base case op; ZIN leverde op 22-04-2026 de PSA-resultaten (geen scenario's haalbaar). | AJ34: Nog aanvullen; VWS-verzoek om aangepaste base-case-resultaten (19-03-2026) beantwoord op 22-04-2026 | AL34: Argumenten volledig | AM34: Bron: gebundelde PDF (brief 12-02-2026; ACP-advies; FT-rapport; FE-rapport; BIA) + brief 'Reactie op verzoek aanlevering ontbrekende resultaten' (22-04-2026), gelezen via extract. Vervolg op INT-077 (glofitamab mono, niet vergoeden 2024). Index-uitkomst 'Vergoeden' vervangen door 'Alleen vergoeden na prijsdaling'.
A35: INT-126 | B35: Afgerond advies | C35: 46057 | D35: =IF(C35="","",YEAR(C35)) -> 2026 | E35: Initieel | F35: tislelizumab (Tevimbra®) | G35: tislelizumab | H35: Tevimbra | I35: niet-kleincellige longkanker | J35: Oncologie (solide tumoren) | K35: Alleen vergoeden na prijsdaling | L35: Advies - vergoed tislelizumab (Tevimbra®) voor de behandeling van niet-kleincellige longkanker | M35: https://www.zorginstituutnederland.nl/documenten/2026/02/04/pakketadvies-sluisgeneesmiddel-tislelizumab-tevimbra-voor-nietkleincellige-longkanker-nsclc | N35: Longkanker (NSCLC/SCLC) | O35: 2e lijn | P35: BeiGene / Novartis | Q35: Nee | S35: Gelijke waarde | T35: Voldoet | U35: Niet-inferioriteit / gelijke waarde aangetoond | V35: Positief, als gelijke waarde t.o.v. nivolumab en atezolizumab. Bewijs: RATIONALE-303 (tislelizumab vs. docetaxel na platinumchemotherapie), indirect vergeleken met de RCT's van nivolumab en atezolizumab: vergelijkbaar OS-effect, geen relevante verschillen in QoL of bijwerkingen → SWP, gelijke waarde. | W35: Gelijke waarde | X35: Nivolumab en atezolizumab (indirecte vergelijking via docetaxel-arm); pembrolizumab ook standaard | AC35: Niet beoordeeld | AD35: Nettoprijs niet hoger dan nettoprijs van de andere PD-(L)1-remmers voor deze indicatie | AE35: 1,7 macrokosten (jaar 3); op lijstprijzen besparing 0,30 na substitutie van andere PD-(L)1-remmers – werkelijk hoger door de arrangementen op alle PD-(L)1-remmers | AF35: 31 in jaar 3; €66.305 per patiënt per jaar | AG35: Geen ACP-advies (gelijke waarde). | AH35: Opname mits nettoprijs ≤ andere PD-(L)1-remmers (allen onder arrangement); 2L-monotherapie is in NL een kleine niche omdat I-O meestal al 1L wordt gegeven. | AI35: Vierde PD-(L)1-remmer in 2L NSCLC (na atezolizumab 2018): gelijke waarde via indirecte vergelijking met de docetaxel-gecontroleerde RCT's → geen KEA; anker = nettoprijs van de klasse. Zeer kleine BI (31 patiënten) omdat 2L-I-O grotendeels is verdrongen door 1L-gebruik. Brief ondertekend door plaatsvervangend voorzitter RvB. | AJ35: Nog aanvullen (niet in dossier); index: vergoed | AL35: Argumenten volledig | AM35: Bron: brief 04-02-2026 (3 p.) + FT-conclusie + BIA, gelezen via extract; geen FE, geen ACP. Vergelijk INT-007 (atezolizumab, 2018): zelfde positie, acht jaar later een routinematige gelijke-waarde-toets.
A36: INT-125 | B36: Afgerond advies | C36: 46051 | D36: =IF(C36="","",YEAR(C36)) -> 2026 | E36: Indicatie-uitbreiding | F36: osimertinib (Tagrisso®) | G36: osimertinib | H36: Tagrisso | I36: lokaal gevorderde niet-kleincellige longkanker | J36: Oncologie (solide tumoren) | K36: Niet vergoeden | L36: Advies - niet vergoeden osimertinib (Tagrisso®) voor de behandeling van lokaal gevorderde niet-kleincellige longkanker | M36: https://www.zorginstituutnederland.nl/documenten/2026/01/29/pakketadvies-sluisgeneesmiddel-osimertinib-tagrisso-voor-de-behandeling-van-lokaal-gevorderde-niet-kleincellige-longkanker | N36: Longkanker (NSCLC/SCLC) | O36: Onderhoud / consolidatie | P36: AstraZeneca | Q36: Nee | S36: Meerwaarde | T36: Voldoet | U36: Directe RCT met klinisch relevant effect | V36: Positief (het negatieve pakketadvies berust op de onbruikbare KEA). Bewijs: RCT LAURA (osimertinib vs. placebo na platinabevattende chemoradiotherapie, EGFR ex19del/L858R): aanzienlijk PFS-effect; analyses tonen een mogelijk klinisch relevant OS-effect, nog onzeker door immature data; meer bijwerkingen en stakers zonder aangetoonde negatieve impact op QoL. ZIN heeft voldoende vertrouwen in een overlevingsvoordeel, waardoor het mogelijk negatievere bijwerkingenprofiel acceptabel is → SWP, meerwaarde t.o.v. actief volgen (met WAR). | W36: Meerwaarde | X36: Actief volgen na chemoradiotherapie (LAURA, placebogecontroleerde RCT) | AC36: Onzeker | AD36: Niet te bepalen: KEA van onvoldoende kwaliteit, ook na herstelmogelijkheid; geen onderhandelingsadvies mogelijk | AE36: 8,4 macrokosten (jaar 3); werkelijk lager door het naar voren schuiven van osimertinib (van gemetastaseerde naar lokaal gevorderde setting) | AF36: 153 in jaar 3; €68.650 per patiënt per jaar | AG36: Niet aan de ACP voorgelegd (KEA van onvoldoende kwaliteit). | AH36: n.v.t. (negatief advies). ZIN verzoekt de registratiehouder de FE-analyse spoedig aan te passen (gemodelleerde effecten in lijn met de klinische studie) en opnieuw in te dienen. | AI36: LAURA: groot PFS-effect, OS mogelijk relevant maar immatuur → meerwaarde, SWP. KEA onbruikbaar, ook na herstelronde: te optimistische, klinisch niet plausibele langetermijn-OS-aannames die niet door de recentste studiedata (niet in het model verwerkt) worden gesteund, en kosten/duur van vervolgbehandelingen niet goed meegenomen → geen betrouwbare KE-schatting, geen onderhandelingsadvies → niet opnemen. ZIN benadrukt dat vergoeding tegen de vraagprijs een 'maatschappelijk niet te verantwoorden' BI en verdringing zou geven, en dat de vertraging voor patiënten aan de fabrikant te wijten is. Osimertinib heeft al een arrangement (stadium IV). | AJ36: Niet opgenomen (negatief advies); herindiening KEA verzocht | AL36: Argumenten volledig | AM36: Bron: brief 29-01-2026 (4 p.) + FT-rapport + FE-rapport + BIA, gelezen via extract; geen ACP. Derde 'niet opnemen wegens onbruikbare KEA' (na ripretinib en brexu-cel ALL), nu na een expliciete herstelmogelijkheid; zusterdossiers osimertinib INT-009 (2018) en INT-040 (adjuvant 2021).
A37: INT-124 | B37: Afgerond advies | C37: 46010 | D37: =IF(C37="","",YEAR(C37)) -> 2025 | E37: Initieel | F37: nemolizumab (Nemluvio®) | G37: nemolizumab | H37: Nemluvio | I37: matig tot ernstige huidaandoeningen | J37: Immunologie / IBD / dermatologie / reumatologie | K37: Alleen vergoeden na prijsdaling | L37: Advies - vergoed nemolizumab (Nemluvio®) voor de behandeling van matig tot ernstige huidaandoeningen | M37: https://www.zorginstituutnederland.nl/documenten/2025/12/19/pakketadvies-sluisgeneesmiddel-nemolizumab-nemluvio-voor-de-behandeling-van-matig-tot-ernstige-huidaandoeningen | N37: Niet-oncologisch (zie Indicatie) | O37: 3e lijn of later | P37: Galderma | Q37: Nee | S37: Gelijke waarde | T37: Voldoet | U37: Niet-inferioriteit / gelijke waarde aangetoond | V37: Positief voor beide indicaties, als gelijke waarde. AD: fase-3 RCT's ARCADIA 1/2 vs. placebo; naïeve indirecte vergelijking met de andere AD-biologicals (dupilumab, lebrikizumab, tralokinumab – gekozen op werkingsmechanisme en toedieningsweg): geen klinisch relevante verschillen op jeuk (PP-NRS), ernst (EASI, IGA) en QoL (DLQI); bijwerkingenprofielen verschillen maar zonder eenduidig relevant voordeel → gelijke waarde. PN: fase-3 RCT's OLYMPIA 1/2 vs. placebo; naïeve ITC met dupilumab: geen relevante verschillen op dezelfde maten → gelijke waarde met dupilumab → SWP. | W37: Gelijke waarde | X37: AD: dupilumab, lebrikizumab, tralokinumab (naïeve ITC); PN: dupilumab (naïeve ITC) | AC37: Niet beoordeeld | AD37: Geen meerkosten (beide indicaties); KE comparators onbekend | AE37: AD: 17,5 macrokosten, besparing 1,0 na substitutie (jaar 3; marktaandeelverschuivingen kunnen dit in meerkosten doen omslaan); PN: 5,3 macrokosten, 2,7 meerkosten na substitutie van dupilumab | AF37: AD: 1.216 in jaar 3 (€18.508 jaar 1 / €12.030 vervolg); PN: 171 in jaar 3 (€33.055 / €29.353); PN-prevalentie onzeker (5.886–29.980), scenario met lagere groei | AG37: Geen ACP-advies (gelijke waarde). | AH37: Opname voor AD (≥12 jaar, systemische behandeling) en PN (volwassenen) mits geen meerkosten; PN-positie conform dupilumab-criteria (na intensieve lokale therapie ± lichttherapie en ≥1 off-label systemische therapie, ≥4 maanden). | AI37: Anti-IL-31RA met twee indicaties in één advies: gelijke waarde met de AD-biologicals en met dupilumab bij PN via naïeve ITC's (PP-NRS, EASI, IGA, DLQI) → geen KEA. BI AD nominaal besparend (€1 mln) maar marktverschuiving kan dat omkeren; PN €2,7 mln meerkosten door hogere prijs dan dupilumab (PN-dosering) → gelijke prijs vereist. Onzekere PN-populatie (scenario's). | AJ37: Nog aanvullen (niet in dossier); index: vergoed | AL37: Argumenten volledig | AM37: Bron: brief 19-12-2025 (4 p.) + FT-rapport (72 p.) + BIA, gelezen via extract; geen FE, geen ACP. Eerste dubbele-indicatie-advies met dupilumab als anker voor beide.
A38: INT-123 | B38: Afgerond advies | C38: 46003 | D38: =IF(C38="","",YEAR(C38)) -> 2025 | E38: Indicatie-uitbreiding | F38: upadacitinib (Rinvoq®) | G38: upadacitinib | H38: Rinvoq | I38: ontstoken bloedvaten | J38: Immunologie / IBD / dermatologie / reumatologie | K38: Niet vergoeden | L38: Advies - niet vergoeden upadacitinib (Rinvoq®) voor de behandeling van ontstoken bloedvaten | M38: https://www.zorginstituutnederland.nl/documenten/2025/12/12/pakketadvies-sluisgeneesmiddel-upadacitinib-rinvoq-voor-de-behandeling-van-ontstoken-bloedvaten | N38: Niet-oncologisch (zie Indicatie) | O38: 2e lijn | P38: AbbVie | Q38: Nee | S38: Gelijke waarde | T38: Voldoet niet | U38: Indirecte vergelijking niet valide / te onzeker | V38: Negatief. Claim: gelijke waarde met tocilizumab (NL-standaard) bij RCA na methotrexaat-falen/-contra-indicatie. Bewijs: geen directe vergelijking; upadacitinib en tocilizumab zijn elk in aparte placebogecontroleerde dubbelblinde RCT's (≥50 jaar, met glucocorticoïd-afbouw) onderzocht, zonder specifieke aandacht voor eerdere MTX-behandeling. De studies verschillen te veel in opzet en patiënten om betrouwbaar indirect te vergelijken; ze kunnen alleen per middel de meerwaarde t.o.v. placebo toetsen. Ook op de afzonderlijke resultaten (behoud van remissie – klinisch en voor de eindbeoordeling het meest relevant gezien de langdurige behandeling –, cumulatieve glucocorticoïddosis, QoL, bijwerkingen) kan gelijkwaardigheid met tocilizumab niet betrouwbaar worden vastgesteld → SWP niet voldaan (WAR eens). Bijzonderheid: fabrikant vroeg GVS-opname; VWS besliste (13-10-2025) dat upadacitinib medisch-specialistische zorg is en intramuraal wordt bekostigd. | W38: Niet te bepalen | X38: Tocilizumab (NL-standaard na MTX); alleen placebo-RCT's per middel, indirecte vergelijking niet valide | AC38: Niet beoordeeld | AG38: Niet voorgelegd aan de ACP (advies stopt bij het SWP-criterium). | AH38: n.v.t. (negatief advies). | AI38: Gelijke-waarde-claim strandt: placebo-RCT's van upadacitinib en tocilizumab te heterogeen voor een valide indirecte vergelijking; op de cruciale maat 'behoud van remissie' geen betrouwbare gelijkwaardigheid vast te stellen → SWP niet voldaan → niet opnemen, geen KEA/BIA/ACP. Procedureel: GVS-verzoek afgewezen door VWS (intramurale bekostiging), waarna sluisbeoordeling. | AJ38: Niet opgenomen (negatief advies) | AL38: Argumenten volledig | AM38: Bron: brief 12-12-2025 (3 p.) + FT-rapport, gelezen via extract; geen BIA/FE/ACP. Eerste 'gelijke waarde'-claim die op de indirecte vergelijking zelf afketst (vgl. bimekizumab axSpA, waar een matige NMA wél werd geaccepteerd); illustreert dat de gelijke-waarde-route niet automatisch is.
A39: INT-122 | B39: Afgerond advies | C39: 45999 | D39: =IF(C39="","",YEAR(C39)) -> 2025 | E39: Herbeoordeling | F39: ravulizumab (Ultomiris®) | G39: ravulizumab | H39: Ultomiris | I39: de bloedziekte aHUS | J39: Hematologie (benigne) | K39: Alleen vergoeden na prijsdaling | L39: Advies - vergoed ravulizumab (Ultomiris®) voor de behandeling van de bloedziekte aHUS | M39: https://www.zorginstituutnederland.nl/documenten/2025/12/08/pakketadvies-sluisgeneesmiddel-ravulizumab-ultomiris-bij-ahus | N39: Overig hematologisch | O39: 2e lijn | P39: Alexion (AstraZeneca) | Q39: Ja | R39: Sluis; aHUS in 2021 negatief beoordeeld (INT-041: studiedesign, afwijkend van NL-praktijk); nu herbeoordeeld voor een smallere 'chronische behandelindicatie' met nieuwe RWD | S39: Gelijke waarde | T39: Voldoet | U39: Niet-inferioriteit / gelijke waarde aangetoond | V39: Positief, als gelijke waarde t.o.v. eculizumab, voor aHUS-patiënten (≥10 kg) die al ≥12 maanden continu met eculizumab worden behandeld en langdurige behandeling nodig hebben. In 2021 negatief voor de registratie-indicatie (≥3 maanden eculizumab; studiedesign en afwijking van de NL-praktijk waar alleen hoog-risicopatiënten langdurig worden behandeld). Nieuw bewijs: drie enkelarmige cross-over real-world studies (≥12 maanden eculizumab → switch naar ravulizumab, intra-patiënt vergelijking): geen relevante verschillen in nierfunctie (stabiel), dialyse/niertransplantaties (geen nieuwe), mortaliteit en ernstige bijwerkingen, bij volwassenen en kinderen; QoL niet onderzocht. Zelfde werkingsmechanisme, langere halfwaardetijd (8 weken, beroepsgroep verwacht 12 via TDM; eculizumab in NL elke 4 i.p.v. 2 weken). ZIN acht enkelarmig onderzoek hier acceptabel vanuit het kader passend onderzoek (lage prevalentie, ernst, nieuw gerandomiseerd bewijs lastig) → SWP, gelijke waarde. | W39: Gelijke waarde | X39: Eculizumab (langdurige behandeling; intra-patiënt switch-RWD); eculizumab bij aHUS in 2016 door ZIN als zeer ongunstig kosteneffectief beoordeeld (€80.000) | AC39: Niet beoordeeld | AD39: Niet meer kosten per patiënt per jaar dan de goedkoopste eculizumab-formulering zoals in de NL-praktijk gebruikt (4-wekelijks); biosimilars eculizumab doorvertalen; eerder onderhandelde ravulizumab-prijs als vertrekpunt | AE39: 6,2 macrokosten (jaar 3); 1,9 meerkosten na substitutie van eculizumab (4-wekelijks interval); −0,1 (besparing) als het ravulizumab-interval via TDM naar 12 weken kan | AF39: 24 in jaar 3 (ca. 100 aHUS-patiënten, ~20 langdurig op eculizumab, 5–7 nieuwe/jaar waarvan 2 langdurig); €289.214 (jaar 1) / €265.966 (vervolg) | AG39: Geen ACP-advies (gelijke waarde). | AH39: Alleen de chronische behandelindicatie (≥12 maanden continu eculizumab, langdurige behandeling aangewezen); geen meerkosten t.o.v. goedkoopste eculizumab-formulering in de praktijk; doseringsintervalverlenging (12 weken) nog aan te tonen bij aHUS (wel bij PNH); biosimilars en eerdere ravulizumab-prijs meewegen. | AI39: Heropening van de in 2021 afgewezen aHUS-indicatie via een smallere claim (chronisch, na ≥12 mnd eculizumab) en intra-patiënt switch-RWD (nierfunctie stabiel, geen dialyse/transplantatie, geen extra SAE's) → gelijke waarde, SWP; single-arm acceptabel bij weesindicatie ('passend onderzoek'). Geen KEA, maar eculizumab zelf in 2016 als zeer ongunstig beoordeeld → dilemma niet-kosteneffectieve standaard. BI €1,9 mln (24 patiënten), mogelijk besparing bij 12-weeks interval. Prijs ≤ goedkoopste eculizumab-formulering in praktijkdosering; biosimilar-doorwerking; eigen eerdere prijs als vertrekpunt. | AJ39: Nog aanvullen (niet in dossier); index: vergoed | AL39: Argumenten volledig | AM39: Bron: brief 08-12-2025 (5 p.) + FT-rapport + BIA, gelezen via extract; geen FE, geen ACP. Voorbeeld van een geslaagde herindiening na negatief SWP-oordeel door indicatieversmalling + RWD; ZIN rekent de eculizumab-kosten op praktijkdosering (4 weken), niet op SmPC (2 weken).
A40: INT-121 | B40: Afgerond advies | C40: 45960 | D40: =IF(C40="","",YEAR(C40)) -> 2025 | E40: Indicatie-uitbreiding | F40: ravulizumab (Ultomiris®) | G40: ravulizumab | H40: Ultomiris | I40: een zeldzame ziekte van het zenuwstelsel (NMOSD) | J40: Neurologie | K40: Alleen vergoeden na prijsdaling | L40: Advies - vergoed ravulizumab (Ultomiris®) voor de behandeling van een zeldzame ziekte van het zenuwstelsel (NMOSD) | M40: https://www.zorginstituutnederland.nl/documenten/2025/10/30/pakketadvies-sluisgeneesmiddel-ravulizumab-ultomiris-bij-nmosd | N40: Niet-oncologisch (zie Indicatie) | O40: 2e lijn | P40: Alexion (AstraZeneca) | Q40: Ja | S40: Gelijke waarde | T40: Voldoet | U40: Niet-inferioriteit / gelijke waarde aangetoond | V40: Positief, als gelijke waarde t.o.v. eculizumab, satralizumab en inebilizumab bij AQP4+ NMOSD na rituximab (NL-standaard eerste lijn). Bewijs: geen directe vergelijkingen; naïeve vergelijkingen en een NMA: alle vier middelen geven klinisch relevante effecten op terugval (risico, ARR, tijd tot eerste terugval vs. placebo), een klein positief effect op QoL en invaliditeit, zonder duidelijke verschillen in ernstige bijwerkingen; rituximab-voorbehandelde patiënten halen vergelijkbare uitkomsten. Ravulizumab is een langwerkende eculizumab-variant (lagere toedieningsfrequentie, mogelijk gebruiksvriendelijker) → SWP, gelijke waarde. | W40: Gelijke waarde | X40: Eculizumab, inebilizumab, satralizumab (naïeve vergelijkingen + NMA vs. placebo); rituximab als NL-eerstelijn | AC40: Niet beoordeeld | AD40: Geen meerkosten t.o.v. de werkelijke kosten van eculizumab (ZIN 2017: 90% korting geadviseerd) c.q. goedkoopste eculizumab-formulering; eculizumab-biosimilars moeten doorwerken in de ravulizumab-prijs; eerder onderhandelde ravulizumab-prijs als vertrekpunt (indicatie-uitbreiding ≠ prijsstijging) | AE40: 2,9 macrokosten (jaar 3); 0,52 meerkosten na substitutie (lijstprijzen) | AF40: 12 in jaar 3 (ca. 200 NMOSD-patiënten, 17 nieuwe/jaar, 80% AQP4+, ~5/jaar falen op rituximab); €267.768 per patiënt per jaar | AG40: Geen ACP-advies (gelijke waarde). | AH40: Alleen AQP4+ patiënten die niet langer met rituximab behandeld kunnen worden; geen meerkosten t.o.v. de werkelijke kosten van eculizumab/inebilizumab/satralizumab; toevoegen aan het weesgeneesmiddelenarrangement NMOSD van de gezamenlijke zorgverzekeraars (2020: eculizumab, satralizumab, tocilizumab, inebilizumab); eculizumab-biosimilars doorvertalen; eerdere ravulizumab-prijs als vertrekpunt. | AI40: Vierde ravulizumab-indicatie: gelijke waarde met drie vergoede NMOSD-middelen via NMA/naïeve vergelijking → geen KEA (ook comparators nooit op KE getoetst). BI klein (12 patiënten, €0,5 mln nominaal). Prijsformule: geen meerkosten t.o.v. werkelijke eculizumab-kosten (verwijzing naar 90%-advies 2017), biosimilar-doorwerking, eigen eerdere prijs als vertrekpunt ('indicatie-uitbreiding = meer volume ≠ prijsstijging'); aansluiting bij het verzekeraarsarrangement NMOSD. | AJ40: Nog aanvullen (niet in dossier); index: vergoed | AL40: Argumenten volledig | AM40: Bron: brief 30-10-2025 (4 p.) + FT-rapport + BIA, gelezen via extract; geen FE, geen ACP. Ravulizumab-serie: PNH/aHUS (INT-041), gMG (INT-065), NMOSD, aHUS chronisch (INT-122).
A41: INT-120 | B41: Afgerond advies | C41: 45947 | D41: =IF(C41="","",YEAR(C41)) -> 2025 | E41: Herbeoordeling | F41: ripretinib (Qinlock®) | G41: ripretinib | H41: Qinlock | I41: zeldzame kanker in maag of darmen | J41: Oncologie (solide tumoren) | K41: Alleen vergoeden na prijsdaling | L41: Advies - vergoed ripretinib (Qinlock®) voor de behandeling van zeldzame kanker in maag of darmen (herbeoordeling) | M41: https://www.zorginstituutnederland.nl/documenten/2025/10/17/pakketadvies-sluisgeneesmiddel-ripretinib-qinlock-voor-gist | N41: Sarcoom / GIST | O41: 3e lijn of later | P41: Deciphera | Q41: Nee | R41: Sluis 07-12-2021; negatief advies 16-01-2025 (INT-098, KEA onbruikbaar); herbeoordeling na verbeterde KEA van de registratiehouder | S41: Meerwaarde | T41: Voldoet | U41: Directe RCT met klinisch relevant effect | V41: Ongewijzigd t.o.v. januari 2025: INVICTUS (n=129) OS 15,1 vs. 6,6 maanden (follow-up 18,2 vs. 6,3), klinisch relevant ondanks 67% crossover; QoL mogelijk beter; toxiciteit mogelijk hoger maar goed behandelbaar → SWP, meerwaarde t.o.v. BSC (gemiddeld 8,5 maanden langer leven). | W41: Meerwaarde | X41: Placebo / best ondersteunende zorg (INVICTUS) | Y41: Hoog (referentiewaarde €80.000) | Z41: 80000 | AA41: 272992 | AB41: 272.992 (verbeterde analyse, nu voldoende kwaliteit; basecase met doorbehandelen na progressie conform INVICTUS); alternatief scenario 'stoppen bij progressie' → 48% korting | AC41: Nee | AD41: Ten minste 75 (ZIN + ACP-meerderheid; basecase met doorbehandelen na progressie); ACP-minderheid: ten minste 48 (stoppen bij progressie, zoals de beroepsgroep na januari 2025 aangaf) | AE41: 4,5 (basecase, jaar 3); 5,5 met dosisverhoging na progressie; ACP: 4,5–7,2 afhankelijk van doorbehandelscenario – onder de sluisdrempel | AF41: 25 starters in jaar 3; €164.660 per patiënt (stoppen bij progressie), +€84.684 / +€212.329 bij doorbehandelen 1×/2× daags; maatschappelijke kosten levenslang €382.017 vs. €9.326 BSC | AG41: ACP unaniem: op korte termijn beschikbaar, maar alleen voor een maatschappelijk aanvaardbare prijs onder €80.000/QALY. Verdeeld over het percentage (ook na lange discussie): meerderheid ≥75% (basecase met doorbehandelen na progressie – de onderzochte behandeling waarop SWP is geconcludeerd); minderheid ≥48% omdat de beroepsgroep het middel uit kostenoverwegingen alleen tot progressie wil inzetten, wat tot lagere kosten leidt dan in de basecase (met de kanttekening dat maar twee scenario's voorlagen). | AH41: Korting ≥75% in de context van doorbehandelen na progressie (SWP-conforme strategie); ZIN merkt op dat het effect en de SWP-status van 'stoppen bij progressie' niet zijn vastgesteld; dosisverhoging na progressie is off-label en niet in de ESMO-richtlijn. | AI41: Na het niet-aanleveren in januari 2025 leverde de fabrikant de ontbrekende informatie alsnog; de KEA is nu bruikbaar: ICER €272.992 → 75%. ZIN gaat uit van doorbehandelen na progressie (zoals in INVICTUS en SWP-getoetst), hoewel de beroepsgroep na het negatieve advies aangaf uit kostenoverwegingen tot progressie te willen behandelen (effect en SWP daarvan onbekend). BI €4,5–7,2 mln – lager dan de sluisdrempel – maar de prijs per patiënt blijft 'uitzonderlijk hoog'. ACP verdeeld: 75% (meerderheid) vs. 48% (minderheid). Maatschappelijk belang van snelle beschikbaarheid (8,5 maanden langer leven) expliciet benoemd. | AJ41: Nog aanvullen (niet in dossier); index: vergoed | AL41: Argumenten volledig | AM41: Bron: brief 17-10-2025 (5 p., ondertekend door K.C. Timm-van Ruitenburg) + ACP-advies (26 p.) + FT-rapport + BIA, gelezen via extract. Vervolg op INT-098. Eerste ACP-advies met een expliciet minderheidsstandpunt over het kortingspercentage.
A42: INT-119 | B42: Afgerond advies | C42: 45936 | D42: =IF(C42="","",YEAR(C42)) -> 2025 | E42: Indicatie-uitbreiding | F42: alectinib (Alecensa®) | G42: alectinib | H42: Alecensa | I42: niet-kleincellige longkanker (NSCLC) | J42: Oncologie (solide tumoren) | K42: Vergoeden | L42: Advies - vergoed alectinib (Alecensa®) voor de behandeling van niet-kleincellige longkanker (NSCLC) | M42: https://www.zorginstituutnederland.nl/documenten/2025/10/06/pakketadvies-alectinib-alecensa-voor-niet-kleincellige-longkanker | N42: Longkanker (NSCLC/SCLC) | O42: Onderhoud / consolidatie | P42: Roche | Q42: Nee | S42: Meerwaarde | T42: Voldoet | U42: Directe RCT met klinisch relevant effect | V42: Positief. Bewijs: open-label RCT ALINA (alectinib vs. platinumchemotherapie, stadium IB-IIIA ALK+ NSCLC na resectie), vooraf gespecificeerde interimanalyse bij 28 maanden mediane follow-up, immature data: geen uitspraak over OS mogelijk; bij gebrek daaraan beoordeelt ZIN het surrogaat DFS – ondanks onduidelijkheid over de correlatie DFS–OS concludeert ZIN op grond van de grootte van het effect (recidief 11,5% vs. 39,4%) dat alectinib mogelijk een positief effect op overleving heeft, al kan (nog) niet worden uitgesloten dat er geen OS-effect is. Waarschijnlijk geen QoL-effect; minder bijwerkingen en stakers dan chemotherapie. CieBOM (november 2024): DFS voldoet aan PASKWIL, advies 'voorlopig' wegens immaturiteit; mature analyses verwacht in 2027. Conclusie (met WAR): SWP, meerwaarde t.o.v. platinumchemotherapie. | W42: Meerwaarde | X42: Adjuvante platinumbevattende chemotherapie (ALINA, directe RCT) | Y42: Middelste categorie (referentiewaarde €50.000) | Z42: 50000 | AA42: 16639 | AB42: 16.639 (extrapolatie DFS, geaccepteerd); conservatief scenario zonder OS-effect 52.916 | AC42: Ja | AD42: Geen (kosteneffectief); heroverweging bij finale OS-analyse (2027) | AE42: 2,4 macrokosten / 2,3 meerkosten (jaar 3) | AF42: 55 in jaar 3; €65.700 per patiënt per jaar (tot 2 jaar behandeling); chemo €5.814 | AG42: Geen ACP-advies (kosteneffectief; alleen WAR). | AH42: Opname zonder prijsvoorwaarde; ZIN adviseert de opname te heroverwegen zodra de finale OS-analyse beschikbaar is (publicatie verwacht 2027) en daarmee rekening te houden bij de duur van toelating; herbeoordeling indien nodig. | AI42: ALINA: DFS-recidief 11,5% vs. 39,4% (PASKWIL, BOM 'voorlopig'), OS immatuur → meerwaarde op het surrogaat, met expliciete onzekerheid. KEA voldoende: ICER €16.639 (DFS-extrapolatie) en zelfs zonder OS-effect €52.916 → gunstig bij €50.000 → opnemen zonder korting, maar met een 'houdbaarheidsdatum': heroverweging bij finale OS (2027). BI €2,3 mln (55 patiënten). Tweede positieve advies zonder prijsvoorwaarde in de database (na NTRK). | AJ42: Nog aanvullen (niet in dossier); index: vergoed | AL42: Argumenten volledig | AM42: Bron: brief 06-10-2025 (4 p.) + FT-rapport + FE-rapport (100 p.) + BIA, gelezen via extract; geen ACP. Contrast met abemaciclib adjuvant: hier volstond DFS omdat OS 'redelijkerwijs nog niet te verwachten' was en het effect zeer groot; conservatief scenario blijft onder de referentiewaarde.
A43: INT-118 | B43: Afgerond advies | C43: 45910 | D43: =IF(C43="","",YEAR(C43)) -> 2025 | E43: Indicatie-uitbreiding | F43: enfortumab vedotin (Padcev®) | G43: enfortumab vedotin | H43: Padcev | I43: blaaskanker | J43: Oncologie (solide tumoren) | K43: Alleen vergoeden na prijsdaling | L43: Advies - vergoed enfortumab vedotin (Padcev®) voor de behandeling van blaaskanker | M43: https://www.zorginstituutnederland.nl/documenten/2025/09/10/pakketadvies-sluisgeneesmiddel-enfortumab-vedotin-padcev-bij-blaaskanker | N43: Blaas-/urotheelkanker | O43: 1e lijn | P43: Astellas (enfortumab vedotin) / MSD (pembrolizumab) | Q43: Nee | S43: Meerwaarde | T43: Voldoet | U43: Directe RCT met klinisch relevant effect | V43: Positief. Bewijs: RCT EV-302 (enfortumab vedotin + pembrolizumab vs. platinumbevattende chemotherapie): aanzienlijk klinisch relevant overlevingsvoordeel van ruim 15 maanden; meer stakers wegens bijwerkingen (ander bijwerkingenprofiel: neuropathie, huiduitslag, diarree vs. hematologische toxiciteit bij chemo); QoL vergelijkbaar; optimale behandelduur onduidelijk. Conclusie (met WAR): SWP, meerwaarde t.o.v. platinumchemotherapie (± avelumab-onderhoud). | W43: Meerwaarde | X43: Platinumbevattende chemotherapie, eventueel gevolgd door avelumab-onderhoud (EV-302, directe RCT) | Y43: Hoog (referentiewaarde €80.000; 5-jaarsoverleving ~10%) | Z43: 80000 | AA43: 111120 | AB43: 111.120 op lijstprijzen (analyse van voldoende kwaliteit); daalt bij aannames over onderhandelde prijzen van pembrolizumab en avelumab | AC43: Nee | AD43: 70 op lijstprijzen; werkelijk benodigde korting afhankelijk van de nettoprijzen van pembrolizumab (vertrouwelijk) en avelumab (ACP: rekenen met de eerder geadviseerde 30% op avelumab); 'minimaal kosteneffectief' wegens hoge BI | AE43: 111 macrokosten (jaar 3); 91 meerkosten na substitutie van chemotherapie, avelumab en pembrolizumab (lijstprijzen) | AF43: 683 in jaar 3; €168.860 per patiënt per jaar (€80.873 enfortumab vedotin + €87.987 pembrolizumab) | AG43: ACP: op korte termijn beschikbaar maar alleen voor een maatschappelijk aanvaardbare prijs; niet opnemen tenzij de KE onder €80.000/QALY komt. Geen exact percentage mogelijk omdat de pembrolizumab-prijs vertrouwelijk is; rekenen met de behaalde pembrolizumab-korting en met de eerder geadviseerde 30% op avelumab (de kosteneffectieve avelumab-prijs voor deze indicatie). Zo mogelijk samen optrekken met ZN, die onderhandelt over EV-monotherapie in de derde lijn. Kort lopend arrangement (dynamisch landschap: indicatie-uitbreidingen, nieuwe middelen). Start-/stopcriteria en een internationale behandelduurstudie waaraan alle behandelende Nederlandse ziekenhuizen zouden moeten deelnemen; partijen moeten hun verantwoordelijkheid nemen. | AH43: Prijs die 'minimaal' kosteneffectief is (extra ruimte wegens hoge BI); korting gekoppeld aan nettoprijzen van pembrolizumab en avelumab (30%); afstemming met ZN-onderhandeling over EV 3L; kort arrangement; start-/stopcriteria; deelname aan een internationale studie naar de optimale behandelduur (hoge prijs, zware patiëntbelasting). | AI43: EV-302: OS +15 maanden → meerwaarde t.o.v. platinumchemo (± avelumab); meer stakers, QoL gelijk; behandelduur onbekend. KEA voldoende: ICER €111.120 op lijstprijzen → 70%, maar de benodigde korting hangt af van de nettoprijzen van pembrolizumab (vertrouwelijk) en avelumab (ZIN adviseerde in 2021 30%); ZIN zegt 'minimaal kosteneffectief' vanwege een BI van €91 mln (683 patiënten à €168.860, waarvan pembrolizumab €87.987). ACP: koppel aan de gerealiseerde kortingen op beide partnermiddelen, trek samen op met ZN (EV 3L-onderhandeling), kort arrangement, behandelduurstudie verplicht voor alle centra. | AJ43: Nog aanvullen (niet in dossier); index: vergoed | AL43: Argumenten volledig | AM43: Bron: brief 10-09-2025 (4 p., gericht aan staatssecretaris Bruijn) + ACP-advies + FT-rapport + FE-rapport (96 p.) + BIA, gelezen via extract. Vervolg op avelumab-onderhoud (INT-035, 2021); EV-monotherapie 3L was al vergoed via verzekeraarsafspraken. Grootste BI van 2025 in de database (€91 mln), vóór Pluvicto (€70 mln) en T-DXd HER2-low (€40,6 mln).
A44: INT-117 | B44: Afgerond advies | C44: 45889 | D44: =IF(C44="","",YEAR(C44)) -> 2025 | E44: Indicatie-uitbreiding | F44: guselkumab (Tremfya®) | G44: guselkumab | H44: Tremfya | I44: de ziekte van Crohn | J44: Immunologie / IBD / dermatologie / reumatologie | K44: Alleen vergoeden na prijsdaling | L44: Advies - vergoed guselkumab (Tremfya®) voor de behandeling van de ziekte van Crohn | M44: https://www.zorginstituutnederland.nl/documenten/2025/08/20/pakketadvies-sluisgeneesmiddel-guselkumab-bij-crohn | N44: Niet-oncologisch (zie Indicatie) | O44: 3e lijn of later | P44: Janssen | Q44: Nee | S44: Gelijke waarde | T44: Voldoet | U44: Niet-inferioriteit / gelijke waarde aangetoond | V44: Positief, als gelijke waarde t.o.v. ustekinumab, vedolizumab, upadacitinib, risankizumab en mirikizumab. Bewijs: twee identieke RCT's GALAXI-2 en -3 met directe vergelijking guselkumab vs. ustekinumab en placebo: in de i.v.-inductiefase (week 12) geen klinisch relevante verschillen in endoscopische respons en klinische remissie; in de s.c.-onderhoudsfase (week 48) vergelijkbaar tot numeriek beter dan ustekinumab op endoscopische respons/remissie en klinische remissie; resultaten bij biological-ervaren patiënten vergelijkbaar met naïeve; vergelijkbaar bijwerkingenprofiel → gelijke waarde met ustekinumab en via de eerdere conclusies met de andere post-TNF-middelen → SWP. Kanttekening: GALAXI includeerde ook conventioneel-therapie-falers; het advies betreft de door de beroepsgroep aangewezen positie na een biological (meestal TNF-alfa). | W44: Gelijke waarde | X44: Ustekinumab (GALAXI-2/3, directe RCT's); vedolizumab, upadacitinib, risankizumab, mirikizumab via eerdere conclusies | AC44: Niet beoordeeld | AD44: Gelijke prijs als uitgangspunt; introductie mag niet tot meerkosten leiden; biosimilars ustekinumab (en vedolizumab 2026) verlagen het anker | AE44: Geen uitgebreide BIA (pragmatisch: al 5 vergoede middelen); budgetneutraal verwacht bij vergelijkbare prijsafspraken | AF44: Bijna 7.500 Crohn-patiënten op post-TNF-middelen (groei 22%/jaar 2020–2024, stabiliserend); €18.203 (startjaar) / €16.171 (onderhoud) vs. ustekinumab €16.441 / €14.559 (lijstprijzen); non-responders hogere dosering (bijna 2× mirikizumab) | AG44: Geen ACP-advies (gelijke waarde). | AH44: Opname na falen van/intolerantie voor een biological (meestal TNF-alfa), mits gelijke prijs; ZIN signaleert dat biosimilars van ustekinumab (uit patent) en vedolizumab (Q1/2 2026) de ruimte voor nieuwere middelen beperken; de voorkeur voor TNF-alfa als eerste biological kan volgens de beroepsgroep veranderen als de ustekinumab-prijs daalt. | AI44: Head-to-head RCT's vs. ustekinumab (GALAXI-2/3, numeriek beter in onderhoud) → toch 'gelijke waarde' (geen klinisch relevant verschil) → geen KEA. Geen uitgebreide BIA (zesde middel in de klasse); budgetneutraal bij vergelijkbare veldafspraken. ZIN benoemt expliciet dat biosimilars (ustekinumab nu, vedolizumab 2026) de markt voor nieuwe middelen verkleinen en het anker verlagen; dosisverhoging bij non-responders als kostenrisico. | AJ44: Nog aanvullen (niet in dossier); index: vergoed | AL44: Argumenten volledig | AM44: Bron: brief 20-08-2025 (7 p. incl. bijlagen), geen aparte rapporten; gelezen via extract. Zusterdossier INT-114 (CU). Numeriek betere onderhoudsresultaten dan ustekinumab leverden geen meerwaarde op.
A45: INT-116 | B45: Afgerond advies | C45: 45869 | D45: =IF(C45="","",YEAR(C45)) -> 2025 | E45: Initieel | F45: exagamglogene autotemcel (Casgevy®) | G45: exagamglogene autotemcel | H45: Casgevy | I45: transfusieafhankelijke β-thalassemie (TDT) | J45: Hematologie (benigne) | K45: Alleen vergoeden na prijsdaling | L45: Advies - vergoed exagamglogene autotemcel (Casgevy®) voor de behandeling van transfusieafhankelijke β-thalassemie (TDT) | M45: https://www.zorginstituutnederland.nl/documenten/2025/07/31/pakketadvies-sluisgeneesmiddel-exagamglogene-autotemcel-casgevy-voor-de-behandeling-van-transfusieafhankelijke-thalassemie-tdt | N45: Sikkelcelziekte / thalassemie | O45: n.v.t. / onbekend | P45: Vertex | Q45: Ja | S45: Meerwaarde | T45: Voldoet | U45: Single-arm geaccepteerd (natuurlijk beloop als controle) | V45: Positief. Bewijs: enkelarmige CLIMB-THAL-111: 93% van de behandelde patiënten werd ≥12 maanden transfusieonafhankelijk; onbekend of dit levenslang aanhoudt, maar vooralsnog geen signalen van terugval; QoL verbeterd; behandeltraject van maanden en intensief, maar vergelijkbaar met allogene SCT. Conclusie (met WAR): meerwaarde t.o.v. levenslange transfusies + ijzerchelatie ± luspatercept → SWP. Eenmalige autologe CRISPR/Cas9-gentherapie. | W45: Meerwaarde | X45: Levenslange bloedtransfusies + ijzerchelatietherapie ± luspatercept (BMS; beperkt ingezet wegens beperkte effectiviteit/botpijn) | Z45: 50000 | AA45: Basecase niet realistisch (leeftijd, ijzernormalisatie, utiliteiten, productiviteits- en mantelzorgkosten) | AB45: 168.103 (gewogen; modelstructuur voldoende, aannames door ZIN aangepast) | AC45: Nee | AD45: Minstens 43; meer dan 43 wegens het zeer hoge macrokostenbeslag als alle 69 patiënten worden behandeld en de komende sikkelcel-uitbreiding | AE45: 23 macrokosten / 22,5 meerkosten (jaar 3, 12 patiënten door capaciteitsbeperking); 131 als alle 69 patiënten worden behandeld; transfusiekosten (€9.876–16.840 p.p./jaar) niet meegenomen (geen geneesmiddelkosten) | AF45: 6 (jaar 1) en 12 per jaar daarna door ziekenhuiscapaciteit; 69 in aanmerking; €1.909.500 per patiënt; ca. 350 bèta-thalassemiepatiënten in NL | AG45: Maatschappelijke weging: op korte termijn beschikbaar, maar alleen voor een maatschappelijk aanvaardbare prijs; prijsonderhandeling cruciaal; gepast-gebruikafspraken over de rol van expertisecentra en een landelijke multidisciplinaire indicatiecommissie. | AH45: Korting >43%; centralisatie in expertisecentra; landelijke multidisciplinaire indicatiecommissie die bij beperkte capaciteit bepaalt wie start (ZIN neemt hiertoe contact op met beroepsgroep, patiëntenvereniging en verzekeraars); capaciteit te verdelen met sikkelcelziekte zodra die indicatie beschikbaar komt; herbeoordeling vóór heronderhandeling zodra meer langetermijndata beschikbaar zijn (onzekerheid over aanhoudend effect). | AI45: Single-arm CLIMB-THAL-111 (93% transfusieonafhankelijk) → meerwaarde, SWP (natuurlijk beloop als controle). KEA: modelstructuur akkoord maar basecase onrealistisch → ZIN-aannames (leeftijd, ijzernormalisatie, utiliteiten, productiviteit/mantelzorg) → ICER €168.103 bij €50.000 → ≥43%; méér wegens €131 mln macrokosten bij volledige behandeling van de 69 patiënten en de sikkelcel-uitbreiding. Uitvoerbaarheid: ziekenhuiscapaciteit slechts 6–12 patiënten/jaar → indicatiecommissie voor selectie. Herbeoordeling vóór heronderhandeling bij langetermijndata. | AJ45: Nog aanvullen (niet in dossier); index: vergoed | AL45: Argumenten volledig | AM45: Bron: brief 31-07-2025 (4 p.) + ACP-advies + FT-rapport + FE-rapport + BIA, gelezen via extract. Vergelijk beti-cel/Zynteglo (INT-034, 2021: 35% + P4P); luspatercept (BMS) als beperkt ingezette comparator-component. Eerste dossier waarin behandelcapaciteit de BI bepaalt en een indicatiecommissie als capaciteitsverdeler wordt voorgesteld.
A46: INT-115 | B46: Afgerond advies | C46: 45854 | D46: =IF(C46="","",YEAR(C46)) -> 2025 | E46: Initieel | F46: elranatamab (Elrexfio®) en talquetamab (Talvey®) | G46: elranatamab | H46: Elrexfio; Talvey | I46: multipel myeloom | J46: Hemato-oncologie | K46: Alleen vergoeden na prijsdaling | L46: Advies - vergoed elranatamab (Elrexfio®) en talquetamab (Talvey®) voor de behandeling van multipel myeloom | M46: https://www.zorginstituutnederland.nl/documenten/2025/07/02/pakketadvies-sluisgeneesmiddel-elranatamab-elrexfio-en-talquetamab-talvey-voor-de-behandeling-van-multipel-myeloom | N46: Multipel myeloom | O46: 3e lijn of later | P46: Pfizer (elranatamab); Janssen (talquetamab) | S46: Meerwaarde | T46: Voldoet | U46: Indirecte vergelijking geaccepteerd (effect groot/consistent) | V46: Positief voor beide middelen (gecombineerd advies). Bewijs: enkelarmige fase-(1-)2-studies MagnetisMM-3 en MonumenTal-1 met vergelijkbare opzet, via verschillende analysemethoden indirect vergeleken met het externe cohort LocoMMotion/MoMMent (behandeling naar keuze van de arts, overeenkomend met de Nederlandse regimes). Elranatamab: klinisch relevante OS-verbetering; talquetamab: puntschatter klinisch relevant, absoluut effect nog niet te bepalen (mediaan niet bereikt); beide klinisch relevante PFS-winst; bewijs zeer laag door niet-gerandomiseerde opzet, indirecte vergelijking en observationele comparator. Geen gepubliceerde relatieve QoL-data. Indirect vergeleken met teclistamab (gepubliceerde MAIC voor elranatamab): alleen 'vergelijkbaar effect op overleving' te concluderen, versterkt door vergelijkbare PFS. Bijwerkingen ongunstiger dan BKA (CRS, neurotoxiciteit, infecties) maar vergelijkbaar met teclistamab en goed behandelbaar volgens de beroepsgroep. Conclusie: SWP, meerwaarde t.o.v. BKA en gelijke waarde t.o.v. teclistamab. | W46: Gelijke waarde | X46: Behandeling naar keuze van de arts (LocoMMotion/MoMMent) → meerwaarde; teclistamab (MAIC) → gelijke waarde; prijsanker: onderhandelde (of theoretische) nettoprijs teclistamab | AC46: Niet beoordeeld | AD46: Geen meerkosten t.o.v. teclistamab; onderhandelde prijs teclistamab leidend, anders de theoretische prijs na de door ZIN geadviseerde minimale korting (>40%, INT-108) | AE46: Macrokosten jaar 3 (met voorgenomen prijsverlagingen): elranatamab 7,3 (5,6 4e lijn + 1,6 5e lijn); talquetamab 9,6 (7,4 + 2,2); BI t.o.v. teclistamab: elranatamab −0,5 tot +0,2; talquetamab +1,8 tot +2,5 | AF46: 147 in jaar 3, gelijk verdeeld over de drie bispecifieke antilichamen; kosten per patiënt €151.510 (elranatamab), €200.372 (talquetamab), €147.581–162.196 (teclistamab) | AG46: Geen apart ACP-advies (gelijke waarde t.o.v. teclistamab). | AH46: Opname mits geen meerkosten t.o.v. teclistamab. Gepast-gebruikafspraken; behandeling bespreken in een indicatiecommissie (zoals voor teclistamab), die de onzekerheid over effectiviteit bij sequentieel gebruik en na CAR-T meeweegt; evaluatie van sequentiële inzet; doelmatigheidsonderzoek door de beroepsgroep. | AI46: Twee bispecifieke antilichamen in één advies. SWP/meerwaarde t.o.v. BKA via extern cohort (zeer laag bewijs); gelijke waarde t.o.v. teclistamab via MAIC → geen KEA, prijsanker teclistamab. Vier nieuwe 4L-middelen (drie bispecifics + cilta-cel) gaan concurreren zonder bewijs voor effectief sequentieel gebruik; cilta-cel voor fitte, bispecifics voor minder fitte patiënten (effect van die selectie onbekend). BI: 147 patiënten gelijk verdeeld; BI hoger als teclistamab of cilta-cel niet worden opgenomen; risico op sequentieel gebruik en op inzet na cilta-cel (buiten 3-jaarshorizon) → hogere kosten later. Verwijzing naar MM-pakketadvies 2025: stapeling van dure middelen in MM is voor de meeste behandelvolgorden niet kosteneffectief. Correctie 16-07-2025 betrof cijfers in BIA en brief. | AJ46: Nog aanvullen (niet in dossier) | AL46: Argumenten volledig | AM46: Bron: gecorrigeerde brief 16-07-2025 (oorspronkelijk 02-07-2025) + FT-rapport + BIA, gelezen via extract; geen FE-rapport. Index-veld 'geneesmiddel' toont beide middelen; registratiehouders verschillen.
A47: INT-114 | B47: Afgerond advies | C47: 45845 | D47: =IF(C47="","",YEAR(C47)) -> 2025 | E47: Indicatie-uitbreiding | F47: guselkumab (Tremfya®) | G47: guselkumab | H47: Tremfya | I47: colitis ulcerosa | J47: Immunologie / IBD / dermatologie / reumatologie | K47: Alleen vergoeden na prijsdaling | L47: Advies - vergoed guselkumab (Tremfya®) voor de behandeling van colitis ulcerosa | M47: https://www.zorginstituutnederland.nl/documenten/2025/07/07/pakketadvies-sluisgeneesmiddel-guselkumab-tremfya-voor-colitis-ulcerosa | N47: Niet-oncologisch (zie Indicatie) | O47: 3e lijn of later | P47: Janssen | Q47: Nee | S47: Gelijke waarde | T47: Voldoet | U47: Niet-inferioriteit / gelijke waarde aangetoond | V47: Positief, als gelijke waarde t.o.v. risankizumab en mirikizumab (IL-23-klassegenoten met recent positief advies), en daarmee ook t.o.v. vedolizumab en ustekinumab (eerder gelijkwaardig aan risankizumab bevonden). Bewijs: placebogecontroleerde RCT's van guselkumab en risankizumab met vergelijkbare gunstige en ongunstige effecten → SWP. | W47: Gelijke waarde | X47: Risankizumab (placebo-RCT's; IL-23-klassegenoot); mirikizumab, vedolizumab, ustekinumab via eerdere conclusies | AC47: Niet beoordeeld | AD47: Gelijke prijs als uitgangspunt; introductie mag niet tot meerkosten leiden; biosimilars ustekinumab (en vedolizumab 2026) verlagen het anker | AE47: ruim 8 macrokosten (jaar 3); 0,58 meerkosten na substitutie van risankizumab en mirikizumab (lijstprijzen) | AF47: 466 in jaar 3; €17.622 (startjaar) / €13.476 (vervolg) bij standaarddosering, tot €26.952 bij hogere dosering voor non-responders; comparators €20.089 / €14.887 | AG47: Geen ACP-advies (gelijke waarde). | AH47: Opname na falen van/intolerantie voor een TNF-alfa-remmer, mits gelijke prijs; let op de hogere dosering voor initiële non-responders (op lijstprijs bijna tweemaal de kosten van mirikizumab); ustekinumab-biosimilars kunnen prijzen en landschap verschuiven. | AI47: Derde IL-23-remmer bij CU: gelijke waarde met risankizumab (placebo-RCT's) en via ketting met mirikizumab/vedolizumab/ustekinumab → geen KEA (KE comparators onbekend). BI €0,58 mln meerkosten (466 patiënten); de dosisverhoging bij non-responders (tot €26.952) is het opwaartse risico. Gelijke prijs als voorwaarde; biosimilars ustekinumab als drukfactor. | AJ47: Nog aanvullen (niet in dossier); index: vergoed | AL47: Argumenten volledig | AM47: Bron: brief 07-07-2025 (3 p.) + FT-conclusie + BIA, gelezen via extract; geen FE, geen ACP. Guselkumab was al vergoed voor psoriasis en PsA (niet in sluis).
A48: INT-113 | B48: Afgerond advies | C48: 45833 | D48: =IF(C48="","",YEAR(C48)) -> 2025 | E48: Indicatie-uitbreiding | F48: axi-cel (Yescarta®) | G48: axicabtagene ciloleucel | H48: Yescarta | I48: recidiverend of refractair folliculair lymfoom | J48: Hemato-oncologie | K48: Niet vergoeden | L48: Advies - niet vergoeden axi-cel (Yescarta®) voor de behandeling van recidiverend of refractair folliculair lymfoom | M48: https://www.zorginstituutnederland.nl/documenten/2025/06/25/pakketadvies-sluisgeneesmiddel-axi-cel-yescarta-voor-de-behandeling-van-bloedkanker | N48: Folliculair lymfoom | O48: 3e lijn of later | P48: Kite / Gilead | Q48: Ja | S48: Meerwaarde | T48: Voldoet niet | U48: Indirecte vergelijking niet valide / te onzeker | V48: Negatief. Bewijs: subgroep (≥3 lijnen) van de enkelarmige fase-2-studie ZUMA-5, met een gepubliceerde gewogen indirecte vergelijking tegen het retrospectieve cohort SCHOLAR-5. Waarom verworpen: hoewel de resultaten numeriek overtuigend lijken, is zeer onzeker of axi-cel daadwerkelijk overleving verlengt: te korte follow-up in zowel ZUMA-5 als SCHOLAR-5, en veel onzekerheid over de validiteit van het controlecohort – SCHOLAR-5 heeft van alle beschikbare cohorten de kortste mediane OS, mogelijk door korte follow-up, en volgens de beroepsgroep sluit geen enkel cohort goed aan bij de Nederlandse praktijk. Kwaliteit van leven is niet gemeten; behandeling gaat wel gepaard met ernstige bijwerkingen. Onduidelijke levensverlenging + onbekende QoL + zekere ernstige toxiciteit → SWP niet voldaan. ZIN nodigt de fabrikant uit tot herindiening zodra later in 2025 langeretermijndata van ZUMA-5 zijn gepubliceerd. | W48: Niet te bepalen | X48: Rituximab-gebaseerde behandelingen en alloSCT (retrospectief cohort SCHOLAR-5; gepubliceerde gewogen indirecte vergelijking) | AC48: Niet beoordeeld | AG48: Niet voorgelegd aan de ACP (advies stopt bij het SWP-criterium). | AH48: n.v.t. (negatief advies). Herbeoordeling mogelijk op basis van langeretermijndata ZUMA-5 (publicatie verwacht eind 2025). | AI48: ZUMA-5-subgroep vs. SCHOLAR-5: numeriek overtuigend maar zeer onzeker – korte follow-up beide studies, SCHOLAR-5 met de kortste OS van alle cohorten (validiteit), geen cohort past bij NL (beroepsgroep); QoL niet gemeten; ernstige bijwerkingen zeker → SWP niet voldaan; uitnodiging tot herindiening met langere follow-up. | AJ48: Niet opgenomen (negatief advies) | AL48: Argumenten volledig | AM48: Bron: brief 25-06-2025 + FT-rapport, gelezen via extract. Contrast met INT-147 (liso-cel FL, 2026): daar werd de indirecte vergelijking met een extern cohort wél geaccepteerd (langere follow-up, best passend cohort, consistente methoden).
A49: INT-112 | B49: Afgerond advies | C49: 45805 | D49: =IF(C49="","",YEAR(C49)) -> 2025 | E49: Indicatie-uitbreiding | F49: trastuzumab-deruxtecan (Enhertu®) | G49: trastuzumab-deruxtecan | H49: Enhertu | I49: borstkanker | J49: Oncologie (solide tumoren) | K49: Alleen vergoeden na prijsdaling | L49: Advies - vergoed trastuzumab-deruxtecan (Enhertu®) voor de behandeling van borstkanker | M49: https://www.zorginstituutnederland.nl/documenten/2025/05/28/pakketadvies-trastuzumab-deruxtecan-enhertu-voor-de-behandeling-van-borstkanker | N49: Borstkanker | O49: 2e lijn | P49: Daiichi Sankyo / AstraZeneca | Q49: Nee | S49: Meerwaarde | T49: Voldoet | U49: Directe RCT met klinisch relevant effect | V49: Positief. Bewijs: fase-3 DESTINY-Breast04 (n=557) vs. chemotherapie naar keuze bij gemetastaseerde HER2-low borstkanker (HER2-low bepaald met de Ventana/Ultraview-test; populatie representatief voor NL): klinisch relevante OS-winst van 6,6 maanden, conform PASKWIL 2023. QoL is gemeten (>92% vulde vragenlijsten in) maar niet gepubliceerd – ook bij de eerdere HER2+-indicatie. Ernstige interventiegerelateerde bijwerkingen vergelijkbaar; klinisch relevant (2×) meer stakers. Conclusie: SWP, meerwaarde op OS t.o.v. chemotherapie. | W49: Meerwaarde | X49: Chemotherapie naar keuze van de behandelaar (DESTINY-Breast04, directe RCT) | Y49: Hoog (referentiewaarde €80.000) | Z49: 80000 | AA49: 190476 | AB49: ten minste 219.803 (te optimistisch langetermijn-OS-effect fabrikant; onzekerheid door ontbrekende QoL-data en HER2-low-teststandaardisatie) | AC49: Nee | AD49: Fors meer dan 68 (68 volgens ICER; ACP: 'nog veel meer' wegens indicatie-uitbreidingen, hoge wereldwijde omzet en niet-gepubliceerde QoL-data) | AE49: 40,6 (jaar 3); extra HER2-low-testkosten 0,24 | AF49: 475 in jaar 3; €95.203 per patiënt vs. €3.411 voor chemotherapie; snelle, volledige substitutie van chemotherapie verwacht | AG49: ACP: opnemen alleen voor een maatschappelijk aanvaardbare prijs; omdat het een indicatie-uitbreiding is, op afzienbare termijn meer uitbreidingen volgen en de wereldwijde omzet al hoog is, moet de prijs met 'nog veel meer dan 68%' dalen. Dat QoL wel is gemeten maar niet gepubliceerd is een belangrijke overweging: juist in de laatste levensfase weegt QoL zwaar bij de keuze voor nóg een behandeling met ernstige bijwerkingen. Gezien de hoge BI en het veranderende behandellandschap een arrangement van maximaal twee jaar. | AH49: Korting fors >68%; nadrukkelijk rekening houden met waarschijnlijke indicatie-uitbreidingen en met het niet-publiceren van gemeten QoL-data; arrangement maximaal twee jaar; landelijke standaardisatie/betrouwbaarheid van HER2-low-diagnostiek (andere testen dan Ventana kunnen andere patiënten classificeren – gevolgen voor KE en aantallen; zie ZIN-rapport 'Verkennende analyse HER2-low diagnostiek', 25-03-2025). | AI49: DESTINY-Breast04: OS +6,6 mnd (PASKWIL 2023) → meerwaarde; QoL gemeten maar niet gepubliceerd (ZIN én ACP rekenen dit de fabrikant aan). KEA voldoende maar onzeker (QoL, langetermijn-OS, HER2-low-testen): fabrikant-ICER €190.476 → ZIN ≥€219.803 → ≥68%, ACP 'nog veel meer' (indicatie-uitbreiding, hoge omzet, QoL-data achtergehouden). BI €40,6 mln (475 patiënten à €95.203 vs. €3.411 chemo, volledige substitutie) + €0,24 mln testkosten. Diagnostiek (Ventana vs. andere testen) als KE- en BI-onzekerheid. Arrangement max. twee jaar. | AJ49: Nog aanvullen (niet in dossier); index: vergoed | AL49: Argumenten volledig | AM49: Bron: brief 28-05-2025 (5 p.) + ACP-advies + FT-rapport + FE-rapport + BIA, gelezen via extract. Vervolg op INT-054 (HER2+, 2023). Eerste dossier waarin het niet-publiceren van gemeten QoL-data expliciet als prijsargument wordt gebruikt en waarin diagnostiek (HER2-low-classificatie) als KE-onzekerheid wordt benoemd.
A50: INT-111 | B50: Afgerond advies | C50: 45804 | D50: =IF(C50="","",YEAR(C50)) -> 2025 | E50: Initieel | F50: epcoritamab (Tepkinly®) | G50: epcoritamab | H50: Tepkinly | I50: lymfeklierkanker | J50: Hemato-oncologie | K50: Niet vergoeden | L50: Advies - niet vergoeden epcoritamab (Tepkinly®) voor de behandeling van lymfeklierkanker | M50: https://www.zorginstituutnederland.nl/documenten/2025/05/27/pakketadvies-epcoritamab-tepkinly-voor-de-behandeling-van-lymfeklierkanker | N50: DLBCL / LBCL | O50: 3e lijn of later | P50: AbbVie / Genmab | S50: Meerwaarde | T50: Voldoet niet | U50: Indirecte vergelijking niet valide / te onzeker | V50: Negatief. Bewijs: voorwaardelijk geregistreerd op de enkelarmige fase-I/II-studie EPCORE NHL-1 (n=157); geen directe vergelijking met chemo-immunotherapie, dus ZIN maakte een naïeve indirecte vergelijking met SCHOLAR-1 (populaties aanzienlijk verschillend; ~39% van EPCORE eerder CAR-T). Na harmonisatie bleven slechts 29 van de 157 epcoritamab-patiënten vergelijkbaar: mediane OS 18,5 (11,7–27,7) vs. 6,3 maanden (5,9–7,0) – een verschil van 12,2 maanden, numeriek hoog en klinisch relevant, maar door de zeer lage bewijskwaliteit zeer onzeker en niet van toepassing op de overige 128 patiënten. Aanvullende toets (module SWP voor single-arm oncologica, 2023: hoe lager de bewijskwaliteit, hoe overtuigender de overige argumenten moeten zijn): mediane PFS 4,4 maanden – het laagste van alle sinds 2020 beoordeelde middelen voor r/r DLBCL (lonca/glofitamab 4,9; TAFA-LEN 11,6/7,6; Pola-BR 9,5; bij 3L+ Pola-BR 6,1); QoL niet interpreteerbaar. De beroepsgroep meldde dat Pola-BR in de praktijk aanzienlijk slechter presteert dan in de single-arm registratiestudie en amper meer wordt gebruikt, wat ZIN's twijfel over de reproduceerbaarheid van single-arm OS-resultaten vergrootte. Bovendien loopt een directe fase-III-studie (GCT3013-05). Conclusie: onvoldoende aannemelijk dat epcoritamab van voldoende meerwaarde is → SWP niet voldaan. | W50: Niet te bepalen | X50: Chemo-immunotherapie (SCHOLAR-1; naïeve indirecte vergelijking door ZIN, 29 vergelijkbare patiënten); PFS kwalitatief afgezet tegen lonca, glofitamab, TAFA-LEN en Pola-BR | AC50: Niet beoordeeld | AG50: Niet voorgelegd aan de ACP (advies stopt bij het SWP-criterium). | AH50: n.v.t. (negatief advies); bewijs van hogere kwaliteit verwacht uit de lopende fase-III-studie GCT3013-05 (epcoritamab vs. CIT). | AI50: Single-arm + naïeve ITC met SCHOLAR-1: slechts 29/157 patiënten vergelijkbaar; OS-verschil 12,2 mnd numeriek relevant maar zeer onzeker en niet generaliseerbaar; PFS 4,4 mnd = slechtste in klasse (cross-dossier-vergelijking); QoL niet te duiden; real-world Pola-BR-ervaring ondermijnt vertrouwen in single-arm OS; fase III loopt → SWP niet voldaan; geen KE/BIA/ACP. | AJ50: Niet opgenomen (negatief advies) | AL50: Argumenten volledig | AM50: Bron: brief 27-05-2025 + FT-rapport, gelezen via extract. FL-indicatie buiten scope. Vergelijk INT-077/078 (glofitamab/loncastuximab 2024) en INT-055 (TAFA-LEN 2023).
A51: INT-110 | B51: Afgerond advies | C51: 45796 | D51: =IF(C51="","",YEAR(C51)) -> 2025 | E51: Initieel | F51: idecabtagene vicleucel (Abecma®) | G51: idecabtagene vicleucel | H51: Abecma | I51: multipel myeloom | J51: Hemato-oncologie | K51: Niet vergoeden | L51: Advies - niet vergoeden idecabtagene vicleucel (Abecma®) voor de behandeling van multipel myeloom | M51: https://www.zorginstituutnederland.nl/documenten/2025/05/19/pakketadvies-idecabtagene-vicleucel-abecma-voor-de-behandeling-van-multipel-myeloom | N51: Multipel myeloom | O51: 3e lijn of later | P51: Bristol Myers Squibb | Q51: Ja | S51: Meerwaarde | T51: Voldoet niet | U51: Effect te klein of niet klinisch relevant | V51: Negatief, ondanks een gerandomiseerde fase-3-studie. KarMMa-3 vergeleek ide-cel met vijf standaardregimes (DPd, DVd, IRd, Kd, EPd) bij RRMM na 2–4 lijnen (66% triple-refractair; populatie representatief voor Nederland). Waarom verworpen: geen klinisch relevant effect op overleving – mediane OS 41,4 vs. 37,9 maanden (3,5 maanden), HR 1,01 (0,73–1,40); ook analyses die corrigeren voor de aanzienlijke crossover (56% van de controlearm kreeg later ide-cel) tonen geen klinisch relevant OS-voordeel. De PFS-winst (13,8 vs. 4,4 maanden, 9,4 maanden; door de beroepsgroep als beoordelingsbasis geaccepteerd) is klinisch relevant maar vertaalt zich niet in overleving en is volgens ZIN 'niet substantieel' vergeleken met cilta-cel (PFS 33,4 maanden), de andere CAR-T in de 4e lijn waarover ZIN recent positief adviseerde. QoL ten minste behouden (klinische relevantie onduidelijk); meer ernstige bijwerkingen en meer vroege overlijdens. Conclusie: voldoet niet aan SWP; geen KE, BIA of ACP. | W51: Niet te bepalen | X51: Standaardbehandeling in KarMMa-3 (DPd, DVd, IRd, Kd, EPd), representatief voor Nederland; benchmark cilta-cel (INT-099) voor de effectgrootte | AC51: Niet beoordeeld | AG51: Niet voorgelegd aan de ACP (advies stopt bij het SWP-criterium). | AH51: n.v.t. (negatief advies). | AI51: RCT KarMMa-3: PFS +9,4 mnd maar OS HR 1,01 (41,4 vs. 37,9 mnd), ook na crossover-correctie geen klinisch relevant OS-effect; PFS-winst 'niet substantieel' t.o.v. cilta-cel (33,4 mnd); QoL behouden, relevantie onduidelijk; meer ernstige bijwerkingen en vroege sterfte → SWP niet voldaan → niet opnemen. Beroepsgroep positioneert smaller (triple-refractair na 2 lijnen). | AJ51: Niet opgenomen (negatief advies) | AL51: Argumenten volledig | AM51: Bron: brief 19-05-2025 + FT-rapport (06-05-2025), gelezen via extract; geen FE/BIA/ACP. BMS-dossier. Zeldzaam voorbeeld van een negatief SWP-oordeel op basis van een RCT met significante PFS-winst.
A52: INT-109 | B52: Afgerond advies | C52: 45762 | D52: =IF(C52="","",YEAR(C52)) -> 2025 | E52: Herbeoordeling | F52: abemaciclib (Verzenios®) | G52: abemaciclib | H52: Verzenios | I52: borstkanker | J52: Oncologie (solide tumoren) | K52: Niet vergoeden | L52: Advies - niet vergoeden abemaciclib (Verzenios®) voor de behandeling van borstkanker (herbeoordeling) | M52: https://www.zorginstituutnederland.nl/documenten/2025/04/11/pakketadvies-sluisgeneesmiddel-abemaciclib-verzenios-voor-de-behandeling-van-borstkanker-herbeoordeling | N52: Borstkanker | O52: Onderhoud / consolidatie | P52: Eli Lilly | Q52: Nee | R52: Sluis; eerder negatief advies 13-12-2023 (INT-067); herbeoordeling na kort geding van de registratiehouder, met nieuw beoordelingsteam en nieuwe studieresultaten | S52: Meerwaarde | T52: Voldoet niet | U52: Effect te klein of niet klinisch relevant | V52: Negatief (bevestiging van 2023 na volledige herbeoordeling). Bewijs: monarchE bij ~54 maanden mediane follow-up: 197/2.555 (7,7%) overleden met abemaciclib vs. 223/2.565 (8,7%) zonder; OS-HR 0,89 (0,74–1,08), niet significant en niet conform de CieBOM-relevantiegrenzen voor adjuvante behandeling (≥5% absoluut verschil, of ≥3% én HR <0,70 bij ≥3 jaar follow-up). Omdat de OS-data immatuur zijn (finale analyse na 650 events of 10 jaar) en mature data redelijkerwijs nog niet te verwachten zijn, keek ZIN ditmaal wél naar iDFS als surrogaat: ook dat effect haalt de CieBOM-grens voor een voorlopig positief advies niet. QoL op lange termijn (12 maanden na behandeling) behouden; toxiciteit, ernstige bijwerkingen en stakers tijdens behandeling klinisch relevant hoger → zonder winst op gunstige effecten onacceptabel. WAR tweemaal: voldoet niet. | W52: Niet te bepalen | X52: Adjuvante endocriene therapie alleen (monarchE, directe RCT) | AC52: Niet beoordeeld | AG52: Niet voorgelegd aan de ACP (advies stopt bij het SWP-criterium). | AH52: n.v.t. (negatief advies). | AI52: Herbeoordeling na kort geding: initiële beoordeling terzijde gelegd, nieuw team, startbijeenkomst met beroepsgroep/richtlijncommissie/patiëntenverenigingen/ZN, nieuwe data, consultatie, WAR tweemaal. Uitkomst ongewijzigd: OS-HR 0,89 (54 mnd) niet relevant volgens CieBOM-adjuvantgrenzen (5% of 3% + HR <0,70); iDFS (nu wél beoordeeld als surrogaat wegens immature OS) haalt de grens voor een voorlopig positief advies evenmin; meer toxiciteit en stakers → SWP niet voldaan. | AJ52: Niet opgenomen (negatief advies, bevestigd) | AL52: Argumenten volledig | AM52: Bron: brief 11-04-2025 (gedateerd 15-04 in index; 4 p.) + FT-herbeoordelingsrapport, gelezen via extract; geen BIA/FE/ACP. Eerste herbeoordeling afgedwongen via een kort geding; de expliciete CieBOM-adjuvantgrenzen (5% / 3% + HR <0,70) worden hier voor het eerst in een brief genoemd.
A53: INT-108 | B53: Afgerond advies | C53: 45761 | D53: =IF(C53="","",YEAR(C53)) -> 2025 | E53: Herbeoordeling | F53: teclistamab (Tecvayli®) | G53: teclistamab | H53: Tecvayli | I53: multipel myeloom | J53: Hemato-oncologie | K53: Alleen vergoeden na prijsdaling | L53: Advies - vergoed teclistamab (Tecvayli®) voor de behandeling van multipel myeloom (herbeoordeling) | M53: https://www.zorginstituutnederland.nl/documenten/2025/04/14/pakketadvies-teclistamab-tecvayli-voor-de-behandeling-van-multipel-myeloom-herbeoordeling | N53: Multipel myeloom | O53: 3e lijn of later | P53: Janssen | R53: Sluis; eerder advies 10-07-2024 (INT-081: niet opnemen wegens onbruikbare KEA); herindiening KEA met 30% lagere lijstprijs | S53: Meerwaarde | T53: Voldoet | U53: Indirecte vergelijking geaccepteerd (effect groot/consistent) | V53: Positief, bevestiging van 2024 (INT-081). MajesTEC-1 (single-arm) indirect vergeleken met het prospectieve externe cohort LocoMMotion: mediane OS 21,9 maanden vs. 11,76 maanden (na correctie voor prognostische factoren) → overlevingswinst 10,1 maanden, HR 0,64 (klinisch relevant); PFS als surrogaat HR 0,48; bewijs zeer lage kwaliteit door de indirecte vergelijking. QoL mogelijk positief (pijn) in de single-arm studie; klinisch relevant meer ernstige bijwerkingen. Beter bewijs voor monotherapie in de 4e lijn wordt niet verwacht. | W53: Meerwaarde | X53: Behandeling naar keuze van de arts, 4e lijn (Pom-Cy-Dex, Kd, Elo-Pom-Dex); prospectief extern cohort LocoMMotion | Z53: 80000 | AA53: Basecase na 30% prijsverlaging; door ZIN vervangen door conservatieve range | AB53: Range 113.041–157.780 (conservatieve benadering wegens indirecte vergelijking en onzekere langetermijnoverleving; met 30% lagere lijstprijs) | AC53: Nee | AD53: Meer dan 40 (range 25–40 op de al met 30% verlaagde prijs); addendum: 35–60% en 'meer dan 60%' afhankelijk van nettoprijzen comparators; ACP: 'veel meer dan 40%' | AE53: Macrokosten 35,2–38,6 (jaar 3, met 30% prijsverlaging); 15,2–18,6 na substitutie | AF53: 367 (4e lijn) + 108 (5e lijn) in jaar 3; €162.196 per patiënt (€147.581 bij tweewekelijkse dosering) | AG53: ACP: beschikbaarheid belangrijk, maar alleen tegen een maatschappelijk aanvaardbare prijs → niet vergoeden tenzij een forse prijsdaling, 'veel meer dan de 40%' uit het conservatieve scenario, vanwege de grote onzekerheden; kan de benodigde daling niet kwantificeren omdat zij de onderhandelde prijzen niet kent en er geen scenario is met een kosteneffectieve comparator. Toelaten van een niet-doelmatige behandeling werkt ook in de toekomst negatief door. Arrangementsduur afstemmen op verwachte concurrenten en indicatie-uitbreidingen naar eerdere lijnen. ZIN: extra prijsdaling boven de 40% omdat de comparator waarschijnlijk zelf niet kosteneffectief is en op lijstprijzen is gewaardeerd. | AH53: Prijsdaling >40% (op de al 30% verlaagde lijstprijs), met extra daling wegens niet-kosteneffectieve comparator op lijstprijzen (addendum: 35–60%, mogelijk >60%); rekening houden met langetermijndata, uitbreiding naar eerdere lijnen en nieuwe behandelingen; korte arrangementsduur; gepast-gebruikafspraken door de beroepsgroep (indicatiecommissie). | AI53: SWP/meerwaarde bevestigd (OS +10,1 mnd, HR 0,64; PFS HR 0,48). Herbeoordeling KEA (met 30% vrijwillige prijsverlaging) nu van voldoende kwaliteit; onzekerheid over indirecte vergelijking en langetermijnoverleving → conservatieve ICER-range €113.041–157.780 → korting 25–40%, advies >40%. Kern: de comparator (4e-lijnsmix op lijstprijzen) is waarschijnlijk zelf niet kosteneffectief en in werkelijkheid goedkoper → extra korting nodig; addendum op verzoek VWS rekent nettoprijzen door (lenalidomide −99%, pomalidomide −41%/−99%, carfilzomib −32%): benodigde korting 35–60%, mogelijk >60%. ACP: 'veel meer dan 40%', niet te kwantificeren; korte arrangementsduur. BI 475 patiënten, €15–19 mln netto. | AJ53: Nog aanvullen (niet in dossier) | AL53: Argumenten volledig | AM53: Bron: gebundelde PDF (brief 14-04-2025; addendum nettoprijzen comparators; ACP-verslag; FT; BIA 2024; FE herbeoordeling), gelezen via extract. Vervolg op INT-081. Prijsanker voor elranatamab/talquetamab (INT-115).
A54: INT-106 | B54: Afgerond advies | C54: 45750 | D54: =IF(C54="","",YEAR(C54)) -> 2025 | E54: Indicatie-uitbreiding | F54: mirikizumab (Omvoh®) | G54: mirikizumab | H54: Omvoh | I54: de ziekte van Crohn | J54: Immunologie / IBD / dermatologie / reumatologie | K54: Alleen vergoeden na prijsdaling | L54: Advies - vergoed mirikizumab (Omvoh®) voor de behandeling van de ziekte van Crohn | M54: https://www.zorginstituutnederland.nl/documenten/2025/04/03/pakketadvies-sluisgeneesmiddel-mirikizumab-omvoh-voor-de-ziekte-van-crohn | N54: Niet-oncologisch (zie Indicatie) | O54: 3e lijn of later | P54: Eli Lilly | Q54: Nee | S54: Gelijke waarde | T54: Voldoet | U54: Niet-inferioriteit / gelijke waarde aangetoond | V54: Positief, als gelijke waarde t.o.v. ustekinumab, vedolizumab, upadacitinib en risankizumab. Bewijs: RCT VIVID-1 met directe vergelijking mirikizumab vs. ustekinumab: geen klinisch relevante verschillen in klinische respons en behoud van remissie, vergelijkbare QoL-verbetering, vergelijkbaar bijwerkingenprofiel; resultaten bij biological-ervaren patiënten vergelijkbaar met biological-naïeve. Omdat ZIN eerder via NMA gelijke waarde tussen ustekinumab en de andere post-TNF-middelen vaststelde, geldt mirikizumab ook als gelijkwaardig aan vedolizumab, upadacitinib en risankizumab → SWP. | W54: Gelijke waarde | X54: Ustekinumab (VIVID-1, directe RCT); vedolizumab, upadacitinib, risankizumab via eerdere NMA-conclusie | AC54: Niet beoordeeld | AD54: Gelijke prijs als uitgangspunt; introductie mag niet tot meerkosten leiden; biosimilars ustekinumab (en vedolizumab 2026) verlagen het anker | AE54: Geen uitgebreide BIA (pragmatisch: al 4 vergoede middelen); verwacht budgetneutraal bij vergelijkbare prijsafspraken | AF54: Enkele honderden (van 6.000–7.000 Crohn-patiënten op post-TNF-middelen); €17.175 (jaar 1) / €16.276 (vervolg) vs. standaard €16.661–20.808 / €13.422–16.276 (lijstprijzen) | AG54: Geen ACP-advies (gelijke waarde). | AH54: Opname mits geen meerkosten (gelijke prijs); het aandeel ustekinumab zal door meerdere biosimilars verder toenemen. | AI54: Head-to-head RCT vs. ustekinumab (VIVID-1) → gelijke waarde; via eerdere NMA ook met vedolizumab/upadacitinib/risankizumab → geen KEA. Eerste sluisdossier zonder uitgebreide BIA ('pragmatische overwegingen': vijfde middel in een klasse met prijsafspraken in het veld); budgetneutraal verwacht bij vergelijkbare afspraken. | AJ54: Nog aanvullen (niet in dossier); index: vergoed | AL54: Argumenten volledig | AM54: Bron: brief 03-04-2025 (3 p.) + FT-conclusie, gelezen via extract; geen BIA/FE/ACP. Tweede mirikizumab-dossier (na CU, INT-085).
A55: INT-107 | B55: Afgerond advies | C55: 45750 | D55: =IF(C55="","",YEAR(C55)) -> 2025 | E55: Initieel | F55: etrasimod (Velsipity®) | G55: etrasimod | H55: Velsipity | I55: colitis ulcerosa | J55: Immunologie / IBD / dermatologie / reumatologie | K55: Alleen vergoeden na prijsdaling | L55: Advies - vergoed etrasimod (Velsipity®) voor de behandeling van colitis ulcerosa | M55: https://www.zorginstituutnederland.nl/documenten/2025/04/03/pakketadvies-sluisgeneesmiddel-etrasimod-velsipity-voor-de-behandeling-van-colitis-ulcerosa | N55: Niet-oncologisch (zie Indicatie) | O55: 3e lijn of later | P55: Pfizer | Q55: Nee | S55: Gelijke waarde | T55: Voldoet | U55: Niet-inferioriteit / gelijke waarde aangetoond | V55: Positief, als gelijke waarde t.o.v. vedolizumab en ozanimod (en via NMA ustekinumab) bij CU ≥16 jaar na TNF-alfa-remmer. Bewijs: vergelijkbare gunstige en ongunstige effecten t.o.v. vedolizumab en ozanimod (S1P-modulator, dezelfde klasse); vedolizumab ≈ ustekinumab in gepubliceerde NMA's. Beroepsgroep: geen voorkeur na TNF-alfa, prijs bepalend → SWP. | W55: Gelijke waarde | X55: Vedolizumab en ozanimod (S1P-klassegenoot); ustekinumab via NMA | AC55: Niet beoordeeld | AD55: Geen meerkosten t.o.v. ustekinumab/vedolizumab; ustekinumab-biosimilars (geregistreerd) verlagen het anker | AE55: 0,79 macrokosten (jaar 3); besparing 0,39 na substitutie van ozanimod (lijstprijzen) | AF55: 101 in jaar 3; €10.128,75 per patiënt per jaar | AG55: Geen ACP-advies (gelijke waarde). | AH55: Opname alleen na falen van/intolerantie voor een TNF-alfa-remmer, mits geen meerkosten t.o.v. ustekinumab en vedolizumab; prijsdaling door ustekinumab-biosimilars en onderhandelde prijzen meewegen. | AI55: Tweede orale S1P-modulator bij CU: gelijke waarde met vedolizumab en ozanimod, via NMA met ustekinumab → geen KEA (KE comparators onbekend). Kleine BI (101 patiënten; nominaal €0,39 mln besparing door substitutie van ozanimod), maar anker = ustekinumab/vedolizumab incl. biosimilarkortingen. | AJ55: Nog aanvullen (niet in dossier); index: vergoed | AL55: Argumenten volledig | AM55: Bron: brief 03-04-2025 (3 p.) + FT-conclusie + BIA, gelezen via extract; geen FE, geen ACP. Zesde CU/Crohn-dossier met identieke gelijke-waarde-route.
A56: INT-105 | B56: Afgerond advies | C56: 45735 | D56: =IF(C56="","",YEAR(C56)) -> 2025 | E56: Initieel | F56: marstacimab (Hympavzi®) | G56: marstacimab | H56: Hympavzi | I56: hemofilie A of B | J56: Hematologie (benigne) | K56: Alleen vergoeden na prijsdaling | L56: Advies - vergoed marstacimab (Hympavzi®) voor de behandeling van hemofilie A of B | M56: https://www.zorginstituutnederland.nl/documenten/2025/03/19/pakketadvies-marstacimab-hympavzi-voor-de-behandeling-van-hemofilie-a-of-b | N56: Hemofilie | O56: Meerdere lijnen / indicatiebreed | P56: Pfizer | Q56: Nee | S56: Gelijke waarde | T56: Voldoet | U56: Niet-inferioriteit / gelijke waarde aangetoond | V56: Positief, als gelijke waarde t.o.v. factor VIII-/IX-producten en (bij hemofilie A) emicizumab. Bewijs: niet-gerandomiseerde open-label fase-3 studie B7841005 (≥12 jaar, ernstige hemofilie A en B zonder remmers): even effectief in het voorkomen van bloedingen als factor VIII/IX; geen klinisch relevante verschillen in bijwerkingen; mogelijk gebruiksgemakvoordeel (wekelijkse subcutane injectie vs. intraveneuze factorproducten). Via de eerdere conclusie emicizumab = factor VIII ook gelijkwaardig aan emicizumab-profylaxe → SWP. | W56: Gelijke waarde | X56: Factor VIII- (hemofilie A) en factor IX-producten (hemofilie B), en emicizumab (hemofilie A, via transitiviteit) | AC56: Niet beoordeeld | AD56: Nettoprijs niet hoger dan nettoprijs factor VIII- en IX-producten | AE56: 25,9 macrokosten (jaar 3); op lijstprijzen besparing van 0,21 na substitutie van factor VIII/IX en emicizumab – werkelijk hoger door onderhandelde comparatorprijzen | AF56: 55 in jaar 3 (ca. 1.400 hemofilie A- en 200 hemofilie B-patiënten in NL); €477.340 (jaar 1) / €468.333 (vervolgjaren) per patiënt | AG56: Geen ACP-advies (gelijke waarde). | AH56: Opname voor de geregistreerde indicatie (ernstige hemofilie A en B zonder remmers, ≥12 jaar, ≥35 kg) mits nettoprijs ≤ factor VIII-/IX-producten; onzekerheid over marktpenetratie. | AI56: Eerste anti-TFPI in de sluis: single-arm fase 3 → even effectief als factor VIII/IX, vergelijkbare veiligheid, wekelijks s.c. als gebruiksgemakvoordeel (geen meerwaarde) → gelijke waarde, ook met emicizumab via transitiviteit → geen KEA; anker = nettoprijs factorproducten, consistent met emicizumab (2020/2023) en efanesoctocog (jan 2025). Nominale besparing (€0,2 mln) op lijstprijzen gerelativeerd; 55 patiënten à ~€470.000. | AJ56: Nog aanvullen (niet in dossier); index: vergoed | AL56: Argumenten volledig | AM56: Bron: brief 19-03-2025 (3 p.) + FT-rapport + BIA, gelezen via extract; geen FE, geen ACP. Brief verwijst voor het eerst naar 'Rapport kosteneffectiviteit van zorg (2024)' i.p.v. het rapport uit 2015.
A57: INT-102 | B57: Afgerond advies | C57: 45728 | D57: =IF(C57="","",YEAR(C57)) -> 2025 | E57: Initieel | F57: injectie Pluvicto® | G57: lutetium (177Lu) vipivotide tetraxetan | H57: Pluvicto | I57: prostaatkanker | J57: Oncologie (solide tumoren) | K57: Alleen vergoeden na prijsdaling | L57: Advies - vergoed injectie Pluvicto® voor de behandeling van prostaatkanker | M57: https://www.zorginstituutnederland.nl/documenten/2025/03/12/pakketadvies-injectie-pluvicto-voor-de-behandeling-van-prostaatkanker | N57: Prostaatkanker | O57: 3e lijn of later | P57: Novartis (Advanced Accelerator Applications) | Q57: Nee | S57: Meerwaarde | T57: Voldoet | U57: Alleen subgroep onderbouwd (deels) | V57: Positief voor de hele indicatie, met een gesplitst waardeoordeel over drie met de beroepsgroepen gedefinieerde groepen. Groep 1 (na ARPI + één taxaan, geschikt voor cabazitaxel): open-label fase-II RCT TheraP vs. cabazitaxel – bij 35,7 maanden follow-up geen klinisch relevant langere overleving, geen QoL-verschil, minder graad 3-4 bijwerkingen maar niet minder stakers → gelijke waarde met cabazitaxel. Groep 2 (niet geschikt voor cabazitaxel) en 3 (na twee taxanen): open-label fase-III RCT VISION (177Lu-PSMA-617 + BSC vs. BSC) – bij ~20 maanden follow-up klinisch relevant langere OS (PASKWIL 2023), QoL gelijk, klinisch relevant meer ernstige bijwerkingen en stakers (te verwachten t.o.v. BSC, acceptabel) → meerwaarde. Onzekerheden: hoge uitval in de VISION-controlearm, heterogene populatie, matige aansluiting bij de Nederlandse praktijk. Olaparib (BRCA), radium-223 (alleen botmetastasen) en de apotheekbereiding 177Lu-PSMA-I&T om pragmatische redenen niet als comparator meegenomen. | W57: Meerwaarde | X57: Groep 1: cabazitaxel (TheraP) → gelijke waarde; groep 2+3: best ondersteunende zorg (VISION) → meerwaarde; apotheekbereiding 177Lu-PSMA-I&T (vergoed, niet geregistreerd) als prijsreferentie | Y57: Hoog (referentiewaarde €80.000) | Z57: 80000 | AA57: Te optimistisch (extrapolaties, utiliteiten, kosten vervolg-/gelijktijdige behandeling aangepast) | AB57: 436.725 (groep 2) en 506.684 (groep 3) na aanpassing door ZIN; groep 1 niet beoordeeld (gelijke waarde) | AC57: Nee | AD57: Groep 1: nettoprijs ≤ cabazitaxel; groep 2+3: 90 volgens KEA, met als anker de prijs van de apotheekbereiding 177Lu-PSMA-I&T (€33.728 vs. €87.570 per behandeling, ca. −60%) en concurrentie van andere lutetium-behandelingen vanaf 2026 | AE57: 90 macrokosten (jaar 3); 70 na substitutie van cabazitaxel (€19.446) en 177Lu-PSMA-I&T (€33.728); scenario's 61–100 | AF57: 1.033 in jaar 3; €87.570 per patiënt per behandeling (4,5 cycli van 6 weken) | AG57: ACP: erkent het belang van beschikbaarheid voor patiënten zonder andere opties, maar weegt ook patiënten met andere aandoeningen en toekomstige patiënten mee; niet opnemen tenzij een forse daling van de vraagprijs. Vanuit maatschappelijk perspectief is een jaarlijkse prijs op het huidige niveau van de ziekenhuisbereiding aangewezen; de commissie is zich bewust dat daarmee ondoelmatige zorg in stand blijft en adviseert daarom een prijsarrangement van maximaal twee jaar (indicatie-uitbreidingen en veranderend behandellandschap). | AH57: Groep 1: prijs ≤ cabazitaxel; groep 2+3: sterke prijsdaling met de apotheekbereiding als referentie en rekening houdend met lutetium-concurrentie vanaf 2026; prijsarrangement van maximaal twee jaar. | AI57: Driedeling met de beroepsgroepen: vs. cabazitaxel (TheraP) gelijke waarde → prijs ≤ cabazitaxel; vs. BSC (VISION) meerwaarde maar ICER €437k–507k → 90% korting volgens KEA. ZIN en ACP verleggen het anker naar de vergoede, niet-geregistreerde apotheekbereiding 177Lu-PSMA-I&T (€33.728 per behandeling, andere kwaliteitseisen, geen eigen OS-data, farmacokinetiek/dosimetrie vergelijkbaar volgens EANM/SNMMI) – een prijs op dat niveau is 'maatschappelijk aangewezen' ondanks dat die ondoelmatige zorg in stand houdt. BI €70 mln (1.033 patiënten) – een van de grootste in de database. Arrangement maximaal twee jaar wegens komende indicatie-uitbreidingen en lutetium-concurrentie. | AJ57: Nog aanvullen (niet in dossier); index: vergoed | AL57: Argumenten volledig | AM57: Bron: brief 12-03-2025 (6 p.) + ACP-advies + FT-rapport + FE-rapport (174 p.) + BIA, gelezen via extract. Eerste radioligand in de sluis; uniek: een magistrale apotheekbereiding als prijsanker voor een geregistreerd product.
A58: INT-103 | B58: Afgerond advies | C58: 45728 | D58: =IF(C58="","",YEAR(C58)) -> 2025 | E58: Indicatie-uitbreiding | F58: talazoparib (Talzenna®) met enzalutamide | G58: talazoparib | H58: Talzenna | I58: uitgezaaide prostaatkanker | J58: Oncologie (solide tumoren) | K58: Alleen vergoeden na prijsdaling | L58: Advies - vergoed talazoparib (Talzenna®) met enzalutamide voor de behandeling van uitgezaaide prostaatkanker | M58: https://www.zorginstituutnederland.nl/documenten/2025/03/12/pakketadvies-talazoparib-talzenna-met-enzalutamide-voor-de-behandeling-van-uitgezaaide-prostaatkanker | N58: Prostaatkanker | O58: 1e lijn | P58: Pfizer | Q58: Nee | S58: Meerwaarde | T58: Voldoet | U58: Directe RCT met klinisch relevant effect | V58: Positief. Bewijs: fase-3 RCT TALAPRO-2 (talazoparib + enzalutamide vs. enzalutamide) bij mCRPC: klinisch relevante verbetering van de overleving; geen klinisch relevant QoL-effect; veiligheidsprofiel duidelijk slechter (waarschijnlijk klinisch relevant meer ernstige bijwerkingen en stakers) maar acceptabel gezien de overlevingswinst. Omdat abirateron en enzalutamide volgens de richtlijn vergelijkbaar effectief zijn en beide worden gebruikt (voorkeur abirateron wegens patentverloop; enzalutamide bij o.a. leverproblemen), acht ZIN de resultaten ook toepasbaar op de vergelijking met abirateron → meerwaarde t.o.v. enzalutamide en abirateron, SWP. De registratiehouder vroeg zelf een smallere indicatie (HRR-mutatie) dan de registratie; de CieBOM adviseerde in april 2024 positief voor de brede populatie op rPFS, met de opmerking dat de rPFS-winst duidelijk groter is bij HRR-mutatie. | W58: Meerwaarde | X58: Enzalutamide (TALAPRO-2, directe RCT) en abirateron (gelijkgesteld; generiek, voorkeur in NL) | Y58: Hoog (referentiewaarde €80.000) | Z58: 80000 | AA58: 186501 | AB58: 186.501 (analyse van voldoende kwaliteit); zelfs bij 100% korting op talazoparib niet kosteneffectief t.o.v. abirateron op lijstprijzen door de prijs van enzalutamide; scenario's met lagere enzalutamide-prijzen doorgerekend | AC58: Nee | AD58: Ten minste 40 op talazoparib, afhankelijk van de decentraal onderhandelde prijs van enzalutamide (ACP-scenario: 60% korting op enzalutamide + 40% op talazoparib) | AE58: 28,5 macrokosten, 19,9 meerkosten (jaar 3); bij hoger testpercentage 32,2 / 22,5 | AF58: 623 in jaar 3 (708 bij hoger HRR-testpercentage); €96.183 per patiënt per behandeling vs. abirateron €21.264 en enzalutamide €50.131 | AG58: ACP: niet opnemen tenzij forse daling van de vraagprijs; omdat het een combinatie met enzalutamide is waarvan de marktexclusiviteit in 2028 afloopt, moeten de prijzen van beide middelen in samenhang worden gezien → prijsarrangement tot het patentverloop van enzalutamide, met het scenario 60% korting op enzalutamide en 40% op talazoparib als uitgangspunt; gepast-gebruikafspraken met nadrukkelijke aandacht voor de HRR-test. | AH58: Alleen HRR-gemuteerde mCRPC zonder chemo-indicatie; korting ≥40% op talazoparib gekoppeld aan de enzalutamide-prijs; arrangement tot patentverloop enzalutamide (2028); gepast-gebruikafspraken rond HRR-testen – nu wordt alleen op BRCA1/2 getest, bij opname moet ook op andere HRR-mutaties worden getest (partijen moeten zich voorbereiden). | AI58: TALAPRO-2: klinisch relevante OS-winst, QoL neutraal, meer toxiciteit acceptabel → meerwaarde t.o.v. enzalutamide én (gelijkgesteld) abirateron; smallere HRR-indicatie door fabrikant zelf aangevraagd. KEA voldoende: ICER €186.501; opvallend: zelfs met 100% korting op talazoparib is de combinatie t.o.v. generiek abirateron niet kosteneffectief door de enzalutamide-lijstprijs → ZIN rekent scenario's met lagere enzalutamide-prijzen → ≥40% op talazoparib, afhankelijk van de enzalutamide-nettoprijs. ACP: prijzen van beide componenten in samenhang, arrangement tot 2028 (patentverloop enzalutamide), scenario 60%/40%. BI €19,9–22,5 mln (623–708 patiënten); HRR-testinfrastructuur als gepast-gebruikvoorwaarde. ZIN herbeoordeelt intussen PARP-remmers bij borstkanker. | AJ58: Nog aanvullen (niet in dossier); index: vergoed | AL58: Argumenten volledig | AM58: Bron: brief 12-03-2025 (5 p.) + ACP-advies + FT-rapport + FE-rapport + BIA, gelezen via extract. Enige PARP-remmer-combinatie bij mCRPC met een positief advies (vgl. INT-075 Akeega en INT-091 olaparib, beide negatief): het verschil is een klinisch relevante OS-winst in de RCT.
A59: INT-104 | B59: Afgerond advies | C59: 45728 | D59: =IF(C59="","",YEAR(C59)) -> 2025 | E59: Initieel | F59: avapritinib (Ayvakyt®) | G59: avapritinib | H59: Ayvakyt | I59: een zeldzame bloedziekte | J59: Hemato-oncologie | K59: Alleen vergoeden na prijsdaling | L59: Advies - vergoed avapritinib (Ayvakyt®) voor de behandeling van een zeldzame bloedziekte | M59: https://www.zorginstituutnederland.nl/documenten/2025/03/12/pakketadvies-avapritinib-ayvakyt-voor-de-behandeling-van-een-zeldzame-bloedziekte | N59: Systemische mastocytose | O59: 2e lijn | P59: Blueprint Medicines | Q59: Ja | S59: Meerwaarde | T59: Voldoet | U59: Indirecte vergelijking geaccepteerd (effect groot/consistent) | V59: Positief. Bewijs: twee enkelarmige studies (EXPLORER, PATHFINDER) indirect vergeleken met een real-world controlecohort van Europese en Amerikaanse patiënten met gevorderde systemische mastocytose. Na ~17 maanden follow-up was de mediane OS met avapritinib niet bereikt vs. 17,2 maanden in het cohort; een ongepubliceerde analyse met ~30 maanden follow-up bevestigt dit (mediaan nog niet bereikt vs. 17,5 maanden) → klinisch relevant overlevingsvoordeel; ook betere respons op ziekteactiviteit, (aanzienlijke) klinisch relevante QoL-verbetering en een gunstiger bijwerkingenprofiel. Bewijskwaliteit zeer laag (zeldzame ziekte, beperkt bewijs voor de bestaande behandelingen, korte follow-up), maar de beperkte data wijzen op een klinisch relevant effect op álle cruciale uitkomsten. Een direct vergelijkende studie acht ZIN niet mogelijk door de zeldzaamheid en een 'rug-tegen-de-muur'-situatie. Conclusie: SWP en meerwaarde t.o.v. midostaurine, cladribine en (peg)interferon-α. | W59: Meerwaarde | X59: Standaard/gebruikelijke behandeling met midostaurine, cladribine en (peg)interferon-α (real-world controlecohort EU/VS; indirecte vergelijking) | Z59: 80000 | AA59: 373840 | AB59: 373.840 (analyse fabrikant van voldoende kwaliteit; geaccepteerd) | AC59: Nee | AD59: 75 | AE59: 5,8 macrokosten (jaar 3); 5,6 na substitutie | AF59: 19 in jaar 3; €353.940 totale kosten per patiënt per jaar; ca. 60 patiënten met AdvSM in Nederland | AG59: ACP: beschikbaarheid belangrijk, maar alleen tegen een maatschappelijk aanvaardbare prijs; niet opnemen tenzij prijsreductie van 75%. Bewust géén 'ten minste' 75% omdat het een zeldzame ziekte met een zeer kleine patiëntengroep en een kleine fabrikant betreft. Bij het arrangement rekening houden met de indicatie-uitbreiding naar indolente SM (grotere groep); gepast-gebruikafspraken maken. ZIN neemt de adviezen over. | AH59: Prijsreductie 75%; indicatie-uitbreiding naar ISM (grotere populatie) meewegen in de onderhandeling; start- en stopcriteria zodat inzet vanaf de tweede lijn bij de juiste patiënten plaatsvindt; dosisverlaging overwegen bij langdurig succesvolle behandeling; behandeling vanuit expertisecentra; ZIN gaat met de beroepsgroep in gesprek over gepaste inzet. | AI59: SWP/meerwaarde op single-arm data + RWD-cohort (OS niet bereikt vs. 17,2–17,5 mnd; respons; QoL; veiligheid) ondanks zeer lage bewijskwaliteit: klinisch relevant effect op alle cruciale uitkomsten; RCT onmogelijk (zeldzaam, rug-tegen-de-muur). KEA van voldoende kwaliteit maar ICER €373.840/QALY ≫ €80.000 → 75% korting nodig; onzekerheden: aanhouden langetermijneffect, gemodelleerde winst bij gestopte maar progressievrije patiënten, utiliteiten. BI 19 patiënten, €5,6 mln. ACP: exact 75% (klein bedrijf, zeldzame ziekte), ISM-uitbreiding meewegen, gepast gebruik (start/stop, dosisverlaging, expertisecentra). | AJ59: Nog aanvullen (niet in dossier) | AL59: Argumenten volledig | AM59: Bron: gebundelde PDF (brief 12-03-2025; ACP-advies; FT-rapport; FE-rapport; BIA), gelezen via extract. Avapritinib werd al vergoed voor GIST.
A60: INT-100 | B60: Afgerond advies | C60: 45708 | D60: =IF(C60="","",YEAR(C60)) -> 2025 | E60: Indicatie-uitbreiding | F60: faricimab (Vabysmo®) | G60: faricimab | H60: Vabysmo | I60: zichtverlies door vochtophoping bij een afgesloten ader in het oog | J60: Oogheelkunde | K60: Alleen vergoeden na prijsdaling | L60: Advies - vergoed faricimab (Vabysmo®) voor de behandeling van zichtverlies door vochtophoping bij een afgesloten ader in het oog | M60: https://www.zorginstituutnederland.nl/documenten/2025/02/20/pakketadvies-sluisgeneesmiddel-faricimab-vabysmo-voor-de-behandeling-van-zichtverlies-door-vochtophoping-bij-een-afgesloten-ader-in-het-oog | N60: Niet-oncologisch (zie Indicatie) | O60: 2e lijn | P60: Roche | Q60: Nee | S60: Gelijke waarde | T60: Voldoet | U60: Niet-inferioriteit / gelijke waarde aangetoond | V60: Positief, als gelijke waarde t.o.v. aflibercept 2 mg. Bewijs: twee vrijwel identieke gerandomiseerde, geblindeerde RCT's (BALATON, COMINO): vergelijkbare klinisch relevante verbetering van zicht en QoL als aflibercept 2 mg. De studies zijn uitgevoerd bij onbehandelde patiënten, terwijl de beroepsgroep aflibercept, ranibizumab en faricimab ná eerstekeus bevacizumab positioneert; door de consistentie van alle cruciale en belangrijke effecten heeft ZIN toch voldoende vertrouwen in gelijke waarde in die positie (geen uitspraak over sequentiële behandeling). Conclusie: SWP. | W60: Gelijke waarde | X60: Aflibercept 2 mg (BALATON/COMINO, directe RCT's); ranibizumab als tweede/derde anti-VEGF na bevacizumab | AC60: Niet beoordeeld | AD60: Geen meerkosten t.o.v. aflibercept 2 mg of ranibizumab (concurrerende anti-VEGF-markt, vertrouwelijke nettoprijzen ziekenhuizen); aflibercept-patent verloopt november 2025 | AE60: 1,1 meerkosten (jaar 3, basisscenario; 3,2 macro) of 1,2 (alternatief scenario, 37,1 macro) – BI vrijwel ongevoelig voor de behandelvolgorde | AF60: 305 in jaar 3 (basisscenario); €6.643 (jaar 1) / €4.380 (vervolgjaren) per patiënt; ca. 116.000 mensen met visusverslechtering door RVO | AG60: Geen ACP-advies (gelijke waarde). | AH60: Opname mits geen meerkosten t.o.v. aflibercept 2 mg of ranibizumab; positie na bevacizumab conform beroepsgroep; comparators zelf nooit door ZIN beoordeeld (via zorgverzekeraars ingestroomd); faricimab voor nAMD en DME niet in de sluis geplaatst. | AI60: Gelijke waarde met aflibercept 2 mg (twee RCT's) → geen KEA; extrapolatie van onbehandelde studiepopulatie naar de positie ná bevacizumab geaccepteerd op consistentie van effecten. BI klein (€1,1–1,2 mln) en volgorde-onafhankelijk; meerkosten door hogere lijstprijs dan ranibizumab. Anti-VEGF-markt is concurrerend met vertrouwelijke ziekenhuisprijzen; ranibizumab generiek, aflibercept-biosimilars vanaf november 2025 → anker daalt. | AJ60: Nog aanvullen (niet in dossier); index: vergoed | AL60: Argumenten volledig | AM60: Bron: brief 20-02-2025 (4 p.) + FT-rapport + BIA, gelezen via extract; geen FE, geen ACP. Tweede oogheelkundedossier (na voretigene, INT-019); enige sluisadvies over een indicatie-uitbreiding waarvan de eerdere indicaties níet in de sluis zaten.
A61: INT-101 | B61: Afgerond advies | C61: 45708 | D61: =IF(C61="","",YEAR(C61)) -> 2025 | E61: Initieel | F61: ublituximab (Briumvi®) | G61: ublituximab | H61: Briumvi | I61: multiple sclerose | J61: Neurologie | K61: Alleen vergoeden na prijsdaling | L61: Advies - vergoed ublituximab (Briumvi®) voor de behandeling van multiple sclerose | M61: https://www.zorginstituutnederland.nl/documenten/2025/02/20/pakketadvies-sluisgeneesmiddel-ublituximab-briumvi-bij-multiple-sclerose | N61: Niet-oncologisch (zie Indicatie) | O61: 2e lijn | P61: Neuraxpharm | Q61: Nee | S61: Gelijke waarde | T61: Voldoet | U61: Niet-inferioriteit / gelijke waarde aangetoond | V61: Positief, als gelijke waarde t.o.v. ocrelizumab. Comparatorkeuze: ublituximab en ocrelizumab zijn beide intramuraal, beide intraveneus, en ofatumumab is in 2022 gelijkwaardig aan ocrelizumab bevonden (ocrelizumab zelf stroomde in 2018 zonder beoordeling in). Bewijs: geen directe vergelijking; NMA en naïeve indirecte vergelijking van ULTIMATE I+II (ublituximab vs. teriflunomide) met OPERA I+II (ocrelizumab): beide geven een klinisch relevante vermindering van relapsen en verlaging van de kans op invaliditeitsprogressie t.o.v. een eerstelijns-DMD/placebo; vergelijkbare bijwerkingenprofielen, geen klinisch relevant verschil in eigenschappen. Beroepsgroep: gelijke plaats met de andere CD20-remmers → SWP, gelijke waarde. | W61: Gelijke waarde | X61: Ocrelizumab (NMA + naïeve ITC ULTIMATE I/II vs. OPERA I/II); ofatumumab eerder gelijkwaardig bevonden (2022) | AC61: Niet beoordeeld | AD61: Nettoprijs niet hoger dan nettoprijs ocrelizumab (KE ocrelizumab nooit getoetst) | AE61: ca. 40 macrokosten (jaar 3); 0,069 meerkosten na substitutie van ocrelizumab (lijstprijzen; werkelijk hoger door verzekeraarsafspraken over ocrelizumab) | AF61: 1.435 in jaar 3; €22.000 per patiënt per jaar (€34.000 met oplaaddosis); ca. 36.500 MS-patiënten in NL (2019) | AG61: Geen ACP-advies (gelijke waarde). | AH61: Opname mits nettoprijs ≤ ocrelizumab; verschuivingen in de CD20-markt verwacht (rituximab-studies, subcutaan ocrelizumab, patentverloop) binnen 3 jaar. | AI61: Derde anti-CD20 bij RMS: gelijke waarde met ocrelizumab via NMA/naïeve ITC (relapsen, invaliditeitsprogressie, veiligheid) → geen KEA; ocrelizumab is zelf nooit op KE getoetst (open instroom 2018). Comparator gekozen op gelijke bekostiging (intramuraal) en toedieningsroute (i.v.). BI nominaal €69.000 (1.435 patiënten), werkelijk hoger door ziekenhuiskortingen; rituximab off-label, s.c.-ocrelizumab en patentverloop als komende marktverschuivingen. | AJ61: Nog aanvullen (niet in dossier); index: vergoed | AL61: Argumenten volledig | AM61: Bron: brief 20-02-2025 (3 p.) + FT-conclusie + BIA, gelezen via extract; geen FE, geen ACP. Eerste MS-dossier in de database; comparatorkeuze expliciet op bekostigingsroute en toedieningsvorm.
A62: INT-099 | B62: Afgerond advies | C62: 45706 | D62: =IF(C62="","",YEAR(C62)) -> 2025 | E62: Herbeoordeling | F62: ciltacabtagene autoleucel (Carvykti®) | G62: ciltacabtagene autoleucel | H62: Carvykti | I62: multipel myeloom | J62: Hemato-oncologie | K62: Alleen vergoeden na prijsdaling | L62: Advies - vergoed ciltacabtagene autoleucel (Carvykti®) voor de behandeling van multipel myeloom | M62: https://www.zorginstituutnederland.nl/documenten/2025/02/18/pakketadvies-ciltacabtagene-autoleucel-carvykti-voor-de-behandeling-van-multipel-myeloom | N62: Multipel myeloom | O62: 3e lijn of later | P62: Janssen | Q62: Ja | R62: Sluis; eerder advies 20-10-2022 (INT-052: niet opnemen wegens onbruikbaar FE-dossier); herindiening KEA | S62: Meerwaarde | T62: Voldoet | U62: Indirecte vergelijking geaccepteerd (effect groot/consistent) | V62: Positief, bevestiging van 2022 (INT-052). CARTITUDE-1 (single-arm) indirect vergeleken met MAMMOTH: 81% vs. 42% in leven na 12 maanden, geschatte winst 28,5 maanden; effectgrootte zeer onzeker door ontbreken van vergelijkende data en immature data (12,4 maanden). Nieuwe data in de herindiening (follow-up 34,5 maanden: 62,9% in leven vs. 33,7% na 2 jaar in het nieuwe controlecohort LocoMMotion) onderschrijven de eerdere conclusie. Bijwerkingen frequent en ernstig maar behandelbaar; met risicobeperkende maatregelen acceptabel gezien de levensbedreigende ziekte en het overlevingseffect. | W62: Meerwaarde | X62: Standaardbehandeling 4e lijn (breed scala, m.n. Pom-Cy-Dex, Elo-Pom-Dex, Kd); FT: extern cohort MAMMOTH; KEA-herindiening: LocoMMotion (sluit volgens beroepsgroep beter aan bij NL) | Z62: 80000 | AA62: Te optimistisch ingeschat (basecase registratiehouder niet gevolgd) | AB62: Range 109.806 (scenario A: wél post-progressie OS-voordeel) tot 142.105 (scenario B: geen post-progressie voordeel) | AC62: Nee | AD62: Ten minste 35 (scenario B); 25 bij scenario A | AE62: 37,9–46,2 (jaar 3; variatie in aandeel dat na aferese daadwerkelijk infusie krijgt; volledige substitutie standaardbehandelingen) | AF62: 140 in jaar 3; €420.000 per patiënt (excl. toediening en monitoring) | AG62: ACP: cilta-cel moet voor RRMM in de 4e lijn op korte termijn beschikbaar komen, maar alleen tegen een maatschappelijk aanvaardbare prijs; vanwege de onzekerheid en de aanzienlijke budgetimpact (kans op verdringing) prijsreductie van ten minste 35%; pay-for-performance-afspraak exploreren; beperkte duur van het arrangement zodat langetermijneffecten én eerste resultaten van het onderzoek naar op de zorglocatie geproduceerde CAR-T (Veelbelovende zorg) bij de volgende onderhandeling bekend zijn; rekening houden met de verwachte vergoedingsaanvraag voor de 2e lijn. ZIN neemt alle adviezen over. | AH62: Prijsreductie ≥35%; bij de onderhandeling rekening houden met komende langetermijndata, indicatie-uitbreiding naar de 2e lijn en mogelijke nieuwe behandelingen (incl. academische CAR-T); pay-for-performance exploreren; kort arrangement. Passende zorg: nationaal register, landelijke CAR-T-tumorboard, geprotocolleerde inzet. | AI62: SWP/meerwaarde bevestigd met 34,5 maanden follow-up en nieuw controlecohort (LocoMMotion). Herbeoordeling KEA: uitgangspunten registratiehouder te optimistisch, maar analyse bruikbaar mits andere cruciale aannames voor PFS-duur, post-progressie-overleving en vervolgbehandelingskosten; door onzekerheid over post-progressie-OS presenteert ZIN een ICER-range (scenario A/B: €109.806–142.105/QALY) → prijsdaling 25–35%, ZIN adviseert ≥35%. ACP: snel beschikbaar maar alleen tegen aanvaardbare prijs; ≥35%; P4P exploreren; kort arrangement (langetermijndata, academische CAR-T, 2e-lijnsaanvraag). BI 140 patiënten, €37,9–46,2 mln. Passende zorg via register en tumorboard. | AJ62: Nog aanvullen (niet in dossier); zie vervolgadvies 2e lijn (INT-138, 27-05-2026) en lopende beoordeling INT-151 | AL62: Argumenten volledig | AM62: Bron: gebundelde PDF (brief 18-02-2025; ACP-advies; FT-rapport; FE-rapport herbeoordeling; BIA), gelezen via extract; de meegeleverde EPAR-productinformatie is niet gebruikt. Vervolg op INT-052 (2022). Let op: 'Vergoeden' in de index vervangen door 'Alleen vergoeden na prijsdaling' (≥35%).
A63: INT-097 | B63: Afgerond advies | C63: 45673 | D63: =IF(C63="","",YEAR(C63)) -> 2025 | E63: Indicatie-uitbreiding | F63: daratumumab (Darzalex®) | G63: daratumumab | H63: Darzalex | I63: een vorm van amyloïdose | J63: Hemato-oncologie | K63: Niet vergoeden | L63: Advies - niet vergoeden daratumumab (Darzalex®) voor de behandeling van een vorm van amyloïdose | M63: https://www.zorginstituutnederland.nl/documenten/2025/01/16/pakketadvies-sluisgeneesmiddel-daratumumab-darzalex | N63: AL-amyloïdose | O63: 1e lijn | P63: Janssen | Q63: Ja | S63: Meerwaarde | T63: Voldoet | U63: Directe RCT met klinisch relevant effect | V63: Positief (het negatieve pakketadvies berust op de onbruikbare KEA). Bewijs: gecontroleerde, open-label fase-3-studie ANDROMEDA (Dara + CyBorD vs. CyBorD) bij nieuw gediagnosticeerde AL-amyloïdose; HOVON gaat Dara-CyBorD in de herziene richtlijn als voorkeursbehandeling in de eerste lijn opnemen. Waarom geaccepteerd: grote toename van complete hematologische respons (53,3% vs. 18,1%) en van cardiale en renale orgaanrespons, uitkomsten met voorspellende waarde voor overlijden en een positieve correlatie met OS; behandeldoel bij AL-amyloïdose is juist een snelle, diepe hematologische respons. OS-data nog immatuur; geen klinisch relevante verandering van QoL in de eerste 24 weken. Ondanks het ontbreken van enkele cruciale langetermijneffecten concludeert ZIN tot meerwaarde t.o.v. CyBorD alleen. | W63: Meerwaarde | X63: Cyclofosfamide, bortezomib en dexamethason (CyBorD) alleen (ANDROMEDA, directe RCT); in de praktijk is daratumumab al een tweedelijnsoptie | AC63: Onzeker | AD63: Niet te bepalen (KEA onbruikbaar); geen onderhandelingsadvies mogelijk | AE63: 13,3 macrokosten (jaar 3); 12,5 na substitutie | AF63: 199 in jaar 3; €131.847 totale kosten per patiënt per jaar | AG63: Niet aan de ACP voorgelegd (geen betrouwbare KE-schatting). | AH63: n.v.t. (negatief advies). ZIN vraagt een nieuw model waarin de overleving primair op de (inmiddels finale) ANDROMEDA-data is gebaseerd en waarin daratumumab als tweedelijnsbehandeling in de comparatorarm is meegenomen. | AI63: SWP en meerwaarde via directe RCT op respons-eindpunten (hematologische en orgaanrespons als gevalideerde voorspellers van overleving; OS immatuur; QoL neutraal). KEA onvoldoende kwaliteit: de gemodelleerde overleving wijkt af van de meest recente ANDROMEDA-data (5-jaarsoverleving in de studie tot 20% hoger dan in het model, in beide armen) en het effect daarvan op de ICER is niet te beredeneren; daratumumab wordt in Nederland al in de tweede lijn ingezet maar die vervolgbehandeling zit niet goed in het model → comparatoroverleving mogelijk onderschat → te optimistische ICER. Geen KE-uitspraak → geen onderhandelingsadvies → niet opnemen; nieuw model op basis van de finale ANDROMEDA-analyse gevraagd. BI 199 patiënten, €12,5 mln. | AJ63: Nog aanvullen (niet in dossier) | AL63: Argumenten volledig | AM63: Bron: gebundelde PDF (brief 16-01-2025; FT-rapport; FE-rapport; BIA), gelezen via extract. Eerste dossier in de database met verwijzing naar het nieuwe 'Beoordelingskader kosteneffectiviteit van zorg (2024)'.
A64: INT-098 | B64: Afgerond advies | C64: 45673 | D64: =IF(C64="","",YEAR(C64)) -> 2025 | E64: Initieel | F64: ripretinib (Qinlock®) | G64: ripretinib | H64: Qinlock | I64: kanker in maag of darmen | J64: Oncologie (solide tumoren) | K64: Niet vergoeden | L64: Advies - niet vergoeden ripretinib (Qinlock®) voor de behandeling van kanker in maag of darmen | M64: https://www.zorginstituutnederland.nl/documenten/2025/01/16/pakketadvies-sluisgeneesmiddelripretinib-qinlock | N64: Sarcoom / GIST | O64: 3e lijn of later | P64: Deciphera | Q64: Nee | S64: Meerwaarde | T64: Voldoet | U64: Directe RCT met klinisch relevant effect | V64: Positief (het negatieve pakketadvies berust op de onbruikbare KEA). Bewijs: INVICTUS (fase 3, dubbelblind, placebogecontroleerd, n=129) bij gevorderde GIST na ≥3 kinaseremmers: mediane OS 15,1 vs. 6,6 maanden, absoluut en relatief klinisch relevant (PASKWIL palliatief); follow-upanalyse 18,2 vs. 6,3 maanden. Ruim 67% van de placebo-arm switchte na progressie naar ripretinib (crossover) – dat het OS-effect desondanks klinisch relevant blijft, vergroot juist het vertrouwen. Mogelijk klinisch relevant QoL-voordeel; mogelijk klinisch relevant meer ernstige bijwerkingen en stakers (vertrouwen laag door korte follow-up en bias-risico), maar goed behandelbaar → gunstige effecten wegen op tegen de ongunstige → SWP. | W64: Meerwaarde | X64: Placebo / best ondersteunende zorg (INVICTUS, directe RCT; standaardalgoritme imatinib → sunitinib → regorafenib → ripretinib) | AC64: Onzeker | AD64: Niet te bepalen (KEA onbruikbaar); geen onderhandelingsadvies mogelijk | AE64: 4,5 (jaar 3; base case met 20% doorbehandeling na progressie eenmaal daags); +1,0 in scenario met dosisverhoging na progressie | AF64: 25 starters in jaar 3 (4e lijn); €164.660 per patiënt bij stoppen bij progressie; +€84.684 (1×daags) of +€212.329 (2×daags) bij doorbehandelen na progressie | AG64: Niet aan de ACP voorgelegd (geen betrouwbare KE-schatting). | AH64: n.v.t. (negatief advies). ZIN heeft de registratiehouder verzocht de ontbrekende scenarioanalyses en essentiële gegevens op korte termijn alsnog aan te leveren; erkent dat de uitkomst teleurstellend is voor patiënten en behandelaren. | AI64: SWP/meerwaarde via INVICTUS (OS 15,1 vs. 6,6 mnd ondanks 67% crossover). KEA onbruikbaar: de registratiehouder leverde essentiële informatie en beschikbare gegevens niet aan, zelfs niet na uitdrukkelijk schriftelijk verzoek, en voerde gevraagde aanvullende analyses niet uit → gebrek aan transparantie, kwaliteit en representativiteit → geen valide KE-uitspraak, geen onderhandelingsadvies → niet opnemen. BI €4,5 mln (25 patiënten); doorbehandeling na progressie met off-label dosisverhoging (21% in INVICTUS, 54% daarvan dosisverhoging) als scenario (+€1,0 mln). | AJ64: Niet opgenomen (negatief advies); herindiening KEA verzocht | AL64: Argumenten volledig | AM64: Bron: brief 16-01-2025 (4 p.) + FT-rapport + FE-rapport + BIA, gelezen via extract; geen ACP. Eerste solide-tumordossier waarin 'niet opnemen wegens onbruikbare KEA' expliciet wordt toegeschreven aan het niet-aanleveren van gevraagde gegevens ('zelfs niet na uitdrukkelijk schriftelijk verzoek').
